Workbook

Sheet Centro Comando
B2: ⬡ CENTRO COMANDO | O2: STORE HOURS ENGINE
B3: Pianificazione turni · copertura · assenze · straordinari — tutto dal vivo
B6: MONTE ORE | G6: RICHIESTE | L6: COPERTURA | Q6: MARGINE
B7: =Personale!$C$41 -> 504 | G7: =OreRichieste!$I$17 -> 553.76609 | L7: =(Personale!$C$41-Personale!$I$41)/OreRichieste!$I$17 -> 0.65731724 | Q7: =Personale!$C$41-Personale!$I$41-OreRichieste!$I$17 -> -189.76609
B11: ▍ MAPPA SETTIMANALE DEI BUCHI
C12: =Copertura!$A$6 -> 0.22916667 | D12: =Copertura!$A$10 -> 0.27083333 | E12: =Copertura!$A$14 -> 0.3125 | F12: =Copertura!$A$18 -> 0.35416667 | G12: =Copertura!$A$22 -> 0.39583333 | H12: =Copertura!$A$26 -> 0.4375 | I12: =Copertura!$A$30 -> 0.47916667 | J12: =Copertura!$A$34 -> 0.52083333 | K12: =Copertura!$A$38 -> 0.5625 | L12: =Copertura!$A$42 -> 0.60416667 | M12: =Copertura!$A$46 -> 0.64583333 | N12: =Copertura!$A$50 -> 0.6875 | O12: =Copertura!$A$54 -> 0.72916667 | P12: =Copertura!$A$58 -> 0.77083333 | Q12: =Copertura!$A$62 -> 0.8125 | R12: =Copertura!$A$66 -> 0.85416667
B13: Lun | C13: =MAX(0,Copertura!$E$6-Copertura!$C$6,Copertura!$E$7-Copertura!$C$7,Copertura!$E$8-Copertura!$C$8,Copertura!$E$9-Copertura!$C$9) -> 0 | D13: =MAX(0,Copertura!$E$10-Copertura!$C$10,Copertura!$E$11-Copertura!$C$11,Copertura!$E$12-Copertura!$C$12,Copertura!$E$13-Copertura!$C$13) -> 0 | E13: =MAX(0,Copertura!$E$14-Copertura!$C$14,Copertura!$E$15-Copertura!$C$15,Copertura!$E$16-Copertura!$C$16,Copertura!$E$17-Copertura!$C$17) -> 0 | F13: =MAX(0,Copertura!$E$18-Copertura!$C$18,Copertura!$E$19-Copertura!$C$19,Copertura!$E$20-Copertura!$C$20,Copertura!$E$21-Copertura!$C$21) -> 0 | G13: =MAX(0,Copertura!$E$22-Copertura!$C$22,Copertura!$E$23-Copertura!$C$23,Copertura!$E$24-Copertura!$C$24,Copertura!$E$25-Copertura!$C$25) -> 0 | H13: =MAX(0,Copertura!$E$26-Copertura!$C$26,Copertura!$E$27-Copertura!$C$27,Copertura!$E$28-Copertura!$C$28,Copertura!$E$29-Copertura!$C$29) -> 0 | I13: =MAX(0,Copertura!$E$30-Copertura!$C$30,Copertura!$E$31-Copertura!$C$31,Copertura!$E$32-Copertura!$C$32,Copertura!$E$33-Copertura!$C$33) -> 1 | J13: =MAX(0,Copertura!$E$34-Copertura!$C$34,Copertura!$E$35-Copertura!$C$35,Copertura!$E$36-Copertura!$C$36,Copertura!$E$37-Copertura!$C$37) -> 0 | K13: =MAX(0,Copertura!$E$38-Copertura!$C$38,Copertura!$E$39-Copertura!$C$39,Copertura!$E$40-Copertura!$C$40,Copertura!$E$41-Copertura!$C$41) -> 0 | L13: =MAX(0,Copertura!$E$42-Copertura!$C$42,Copertura!$E$43-Copertura!$C$43,Copertura!$E$44-Copertura!$C$44,Copertura!$E$45-Copertura!$C$45) -> 0 | M13: =MAX(0,Copertura!$E$46-Copertura!$C$46,Copertura!$E$47-Copertura!$C$47,Copertura!$E$48-Copertura!$C$48,Copertura!$E$49-Copertura!$C$49) -> 0 | N13: =MAX(0,Copertura!$E$50-Copertura!$C$50,Copertura!$E$51-Copertura!$C$51,Copertura!$E$52-Copertura!$C$52,Copertura!$E$53-Copertura!$C$53) -> 0 | O13: =MAX(0,Copertura!$E$54-Copertura!$C$54,Copertura!$E$55-Copertura!$C$55,Copertura!$E$56-Copertura!$C$56,Copertura!$E$57-Copertura!$C$57) -> 0 | P13: =MAX(0,Copertura!$E$58-Copertura!$C$58,Copertura!$E$59-Copertura!$C$59,Copertura!$E$60-Copertura!$C$60,Copertura!$E$61-Copertura!$C$61) -> 0 | Q13: =MAX(0,Copertura!$E$62-Copertura!$C$62,Copertura!$E$63-Copertura!$C$63,Copertura!$E$64-Copertura!$C$64,Copertura!$E$65-Copertura!$C$65) -> 0 | R13: =MAX(0,Copertura!$E$66-Copertura!$C$66,Copertura!$E$67-Copertura!$C$67,Copertura!$E$68-Copertura!$C$68) -> 0
B14: Mar | C14: =MAX(0,Copertura!$I$6-Copertura!$G$6,Copertura!$I$7-Copertura!$G$7,Copertura!$I$8-Copertura!$G$8,Copertura!$I$9-Copertura!$G$9) -> 0 | D14: =MAX(0,Copertura!$I$10-Copertura!$G$10,Copertura!$I$11-Copertura!$G$11,Copertura!$I$12-Copertura!$G$12,Copertura!$I$13-Copertura!$G$13) -> 0 | E14: =MAX(0,Copertura!$I$14-Copertura!$G$14,Copertura!$I$15-Copertura!$G$15,Copertura!$I$16-Copertura!$G$16,Copertura!$I$17-Copertura!$G$17) -> 0 | F14: =MAX(0,Copertura!$I$18-Copertura!$G$18,Copertura!$I$19-Copertura!$G$19,Copertura!$I$20-Copertura!$G$20,Copertura!$I$21-Copertura!$G$21) -> 0 | G14: =MAX(0,Copertura!$I$22-Copertura!$G$22,Copertura!$I$23-Copertura!$G$23,Copertura!$I$24-Copertura!$G$24,Copertura!$I$25-Copertura!$G$25) -> 0 | H14: =MAX(0,Copertura!$I$26-Copertura!$G$26,Copertura!$I$27-Copertura!$G$27,Copertura!$I$28-Copertura!$G$28,Copertura!$I$29-Copertura!$G$29) -> 0 | I14: =MAX(0,Copertura!$I$30-Copertura!$G$30,Copertura!$I$31-Copertura!$G$31,Copertura!$I$32-Copertura!$G$32,Copertura!$I$33-Copertura!$G$33) -> 0 | J14: =MAX(0,Copertura!$I$34-Copertura!$G$34,Copertura!$I$35-Copertura!$G$35,Copertura!$I$36-Copertura!$G$36,Copertura!$I$37-Copertura!$G$37) -> 0 | K14: =MAX(0,Copertura!$I$38-Copertura!$G$38,Copertura!$I$39-Copertura!$G$39,Copertura!$I$40-Copertura!$G$40,Copertura!$I$41-Copertura!$G$41) -> 0 | L14: =MAX(0,Copertura!$I$42-Copertura!$G$42,Copertura!$I$43-Copertura!$G$43,Copertura!$I$44-Copertura!$G$44,Copertura!$I$45-Copertura!$G$45) -> 1 | M14: =MAX(0,Copertura!$I$46-Copertura!$G$46,Copertura!$I$47-Copertura!$G$47,Copertura!$I$48-Copertura!$G$48,Copertura!$I$49-Copertura!$G$49) -> 0 | N14: =MAX(0,Copertura!$I$50-Copertura!$G$50,Copertura!$I$51-Copertura!$G$51,Copertura!$I$52-Copertura!$G$52,Copertura!$I$53-Copertura!$G$53) -> 0 | O14: =MAX(0,Copertura!$I$54-Copertura!$G$54,Copertura!$I$55-Copertura!$G$55,Copertura!$I$56-Copertura!$G$56,Copertura!$I$57-Copertura!$G$57) -> 0 | P14: =MAX(0,Copertura!$I$58-Copertura!$G$58,Copertura!$I$59-Copertura!$G$59,Copertura!$I$60-Copertura!$G$60,Copertura!$I$61-Copertura!$G$61) -> 0 | Q14: =MAX(0,Copertura!$I$62-Copertura!$G$62,Copertura!$I$63-Copertura!$G$63,Copertura!$I$64-Copertura!$G$64,Copertura!$I$65-Copertura!$G$65) -> 0 | R14: =MAX(0,Copertura!$I$66-Copertura!$G$66,Copertura!$I$67-Copertura!$G$67,Copertura!$I$68-Copertura!$G$68) -> 0
B15: Mer | C15: =MAX(0,Copertura!$M$6-Copertura!$K$6,Copertura!$M$7-Copertura!$K$7,Copertura!$M$8-Copertura!$K$8,Copertura!$M$9-Copertura!$K$9) -> 0 | D15: =MAX(0,Copertura!$M$10-Copertura!$K$10,Copertura!$M$11-Copertura!$K$11,Copertura!$M$12-Copertura!$K$12,Copertura!$M$13-Copertura!$K$13) -> 0 | E15: =MAX(0,Copertura!$M$14-Copertura!$K$14,Copertura!$M$15-Copertura!$K$15,Copertura!$M$16-Copertura!$K$16,Copertura!$M$17-Copertura!$K$17) -> 0 | F15: =MAX(0,Copertura!$M$18-Copertura!$K$18,Copertura!$M$19-Copertura!$K$19,Copertura!$M$20-Copertura!$K$20,Copertura!$M$21-Copertura!$K$21) -> 0 | G15: =MAX(0,Copertura!$M$22-Copertura!$K$22,Copertura!$M$23-Copertura!$K$23,Copertura!$M$24-Copertura!$K$24,Copertura!$M$25-Copertura!$K$25) -> 0 | H15: =MAX(0,Copertura!$M$26-Copertura!$K$26,Copertura!$M$27-Copertura!$K$27,Copertura!$M$28-Copertura!$K$28,Copertura!$M$29-Copertura!$K$29) -> 0 | I15: =MAX(0,Copertura!$M$30-Copertura!$K$30,Copertura!$M$31-Copertura!$K$31,Copertura!$M$32-Copertura!$K$32,Copertura!$M$33-Copertura!$K$33) -> 0 | J15: =MAX(0,Copertura!$M$34-Copertura!$K$34,Copertura!$M$35-Copertura!$K$35,Copertura!$M$36-Copertura!$K$36,Copertura!$M$37-Copertura!$K$37) -> 0 | K15: =MAX(0,Copertura!$M$38-Copertura!$K$38,Copertura!$M$39-Copertura!$K$39,Copertura!$M$40-Copertura!$K$40,Copertura!$M$41-Copertura!$K$41) -> 0 | L15: =MAX(0,Copertura!$M$42-Copertura!$K$42,Copertura!$M$43-Copertura!$K$43,Copertura!$M$44-Copertura!$K$44,Copertura!$M$45-Copertura!$K$45) -> 0 | M15: =MAX(0,Copertura!$M$46-Copertura!$K$46,Copertura!$M$47-Copertura!$K$47,Copertura!$M$48-Copertura!$K$48,Copertura!$M$49-Copertura!$K$49) -> 0 | N15: =MAX(0,Copertura!$M$50-Copertura!$K$50,Copertura!$M$51-Copertura!$K$51,Copertura!$M$52-Copertura!$K$52,Copertura!$M$53-Copertura!$K$53) -> 0 | O15: =MAX(0,Copertura!$M$54-Copertura!$K$54,Copertura!$M$55-Copertura!$K$55,Copertura!$M$56-Copertura!$K$56,Copertura!$M$57-Copertura!$K$57) -> 0 | P15: =MAX(0,Copertura!$M$58-Copertura!$K$58,Copertura!$M$59-Copertura!$K$59,Copertura!$M$60-Copertura!$K$60,Copertura!$M$61-Copertura!$K$61) -> 0 | Q15: =MAX(0,Copertura!$M$62-Copertura!$K$62,Copertura!$M$63-Copertura!$K$63,Copertura!$M$64-Copertura!$K$64,Copertura!$M$65-Copertura!$K$65) -> 0 | R15: =MAX(0,Copertura!$M$66-Copertura!$K$66,Copertura!$M$67-Copertura!$K$67,Copertura!$M$68-Copertura!$K$68) -> 0
B16: Gio | C16: =MAX(0,Copertura!$Q$6-Copertura!$O$6,Copertura!$Q$7-Copertura!$O$7,Copertura!$Q$8-Copertura!$O$8,Copertura!$Q$9-Copertura!$O$9) -> 0 | D16: =MAX(0,Copertura!$Q$10-Copertura!$O$10,Copertura!$Q$11-Copertura!$O$11,Copertura!$Q$12-Copertura!$O$12,Copertura!$Q$13-Copertura!$O$13) -> 0 | E16: =MAX(0,Copertura!$Q$14-Copertura!$O$14,Copertura!$Q$15-Copertura!$O$15,Copertura!$Q$16-Copertura!$O$16,Copertura!$Q$17-Copertura!$O$17) -> 0 | F16: =MAX(0,Copertura!$Q$18-Copertura!$O$18,Copertura!$Q$19-Copertura!$O$19,Copertura!$Q$20-Copertura!$O$20,Copertura!$Q$21-Copertura!$O$21) -> 0 | G16: =MAX(0,Copertura!$Q$22-Copertura!$O$22,Copertura!$Q$23-Copertura!$O$23,Copertura!$Q$24-Copertura!$O$24,Copertura!$Q$25-Copertura!$O$25) -> 0 | H16: =MAX(0,Copertura!$Q$26-Copertura!$O$26,Copertura!$Q$27-Copertura!$O$27,Copertura!$Q$28-Copertura!$O$28,Copertura!$Q$29-Copertura!$O$29) -> 0 | I16: =MAX(0,Copertura!$Q$30-Copertura!$O$30,Copertura!$Q$31-Copertura!$O$31,Copertura!$Q$32-Copertura!$O$32,Copertura!$Q$33-Copertura!$O$33) -> 0 | J16: =MAX(0,Copertura!$Q$34-Copertura!$O$34,Copertura!$Q$35-Copertura!$O$35,Copertura!$Q$36-Copertura!$O$36,Copertura!$Q$37-Copertura!$O$37) -> 0 | K16: =MAX(0,Copertura!$Q$38-Copertura!$O$38,Copertura!$Q$39-Copertura!$O$39,Copertura!$Q$40-Copertura!$O$40,Copertura!$Q$41-Copertura!$O$41) -> 0 | L16: =MAX(0,Copertura!$Q$42-Copertura!$O$42,Copertura!$Q$43-Copertura!$O$43,Copertura!$Q$44-Copertura!$O$44,Copertura!$Q$45-Copertura!$O$45) -> 0 | M16: =MAX(0,Copertura!$Q$46-Copertura!$O$46,Copertura!$Q$47-Copertura!$O$47,Copertura!$Q$48-Copertura!$O$48,Copertura!$Q$49-Copertura!$O$49) -> 0 | N16: =MAX(0,Copertura!$Q$50-Copertura!$O$50,Copertura!$Q$51-Copertura!$O$51,Copertura!$Q$52-Copertura!$O$52,Copertura!$Q$53-Copertura!$O$53) -> 0 | O16: =MAX(0,Copertura!$Q$54-Copertura!$O$54,Copertura!$Q$55-Copertura!$O$55,Copertura!$Q$56-Copertura!$O$56,Copertura!$Q$57-Copertura!$O$57) -> 0 | P16: =MAX(0,Copertura!$Q$58-Copertura!$O$58,Copertura!$Q$59-Copertura!$O$59,Copertura!$Q$60-Copertura!$O$60,Copertura!$Q$61-Copertura!$O$61) -> 0 | Q16: =MAX(0,Copertura!$Q$62-Copertura!$O$62,Copertura!$Q$63-Copertura!$O$63,Copertura!$Q$64-Copertura!$O$64,Copertura!$Q$65-Copertura!$O$65) -> 1 | R16: =MAX(0,Copertura!$Q$66-Copertura!$O$66,Copertura!$Q$67-Copertura!$O$67,Copertura!$Q$68-Copertura!$O$68) -> 0
B17: Ven | C17: =MAX(0,Copertura!$U$6-Copertura!$S$6,Copertura!$U$7-Copertura!$S$7,Copertura!$U$8-Copertura!$S$8,Copertura!$U$9-Copertura!$S$9) -> 0 | D17: =MAX(0,Copertura!$U$10-Copertura!$S$10,Copertura!$U$11-Copertura!$S$11,Copertura!$U$12-Copertura!$S$12,Copertura!$U$13-Copertura!$S$13) -> 0 | E17: =MAX(0,Copertura!$U$14-Copertura!$S$14,Copertura!$U$15-Copertura!$S$15,Copertura!$U$16-Copertura!$S$16,Copertura!$U$17-Copertura!$S$17) -> 0 | F17: =MAX(0,Copertura!$U$18-Copertura!$S$18,Copertura!$U$19-Copertura!$S$19,Copertura!$U$20-Copertura!$S$20,Copertura!$U$21-Copertura!$S$21) -> 0 | G17: =MAX(0,Copertura!$U$22-Copertura!$S$22,Copertura!$U$23-Copertura!$S$23,Copertura!$U$24-Copertura!$S$24,Copertura!$U$25-Copertura!$S$25) -> 0 | H17: =MAX(0,Copertura!$U$26-Copertura!$S$26,Copertura!$U$27-Copertura!$S$27,Copertura!$U$28-Copertura!$S$28,Copertura!$U$29-Copertura!$S$29) -> 0 | I17: =MAX(0,Copertura!$U$30-Copertura!$S$30,Copertura!$U$31-Copertura!$S$31,Copertura!$U$32-Copertura!$S$32,Copertura!$U$33-Copertura!$S$33) -> 0 | J17: =MAX(0,Copertura!$U$34-Copertura!$S$34,Copertura!$U$35-Copertura!$S$35,Copertura!$U$36-Copertura!$S$36,Copertura!$U$37-Copertura!$S$37) -> 0 | K17: =MAX(0,Copertura!$U$38-Copertura!$S$38,Copertura!$U$39-Copertura!$S$39,Copertura!$U$40-Copertura!$S$40,Copertura!$U$41-Copertura!$S$41) -> 0 | L17: =MAX(0,Copertura!$U$42-Copertura!$S$42,Copertura!$U$43-Copertura!$S$43,Copertura!$U$44-Copertura!$S$44,Copertura!$U$45-Copertura!$S$45) -> 0 | M17: =MAX(0,Copertura!$U$46-Copertura!$S$46,Copertura!$U$47-Copertura!$S$47,Copertura!$U$48-Copertura!$S$48,Copertura!$U$49-Copertura!$S$49) -> 0 | N17: =MAX(0,Copertura!$U$50-Copertura!$S$50,Copertura!$U$51-Copertura!$S$51,Copertura!$U$52-Copertura!$S$52,Copertura!$U$53-Copertura!$S$53) -> 0 | O17: =MAX(0,Copertura!$U$54-Copertura!$S$54,Copertura!$U$55-Copertura!$S$55,Copertura!$U$56-Copertura!$S$56,Copertura!$U$57-Copertura!$S$57) -> 0 | P17: =MAX(0,Copertura!$U$58-Copertura!$S$58,Copertura!$U$59-Copertura!$S$59,Copertura!$U$60-Copertura!$S$60,Copertura!$U$61-Copertura!$S$61) -> 1 | Q17: =MAX(0,Copertura!$U$62-Copertura!$S$62,Copertura!$U$63-Copertura!$S$63,Copertura!$U$64-Copertura!$S$64,Copertura!$U$65-Copertura!$S$65) -> 0 | R17: =MAX(0,Copertura!$U$66-Copertura!$S$66,Copertura!$U$67-Copertura!$S$67,Copertura!$U$68-Copertura!$S$68) -> 0
B18: Sab | C18: =MAX(0,Copertura!$Y$6-Copertura!$W$6,Copertura!$Y$7-Copertura!$W$7,Copertura!$Y$8-Copertura!$W$8,Copertura!$Y$9-Copertura!$W$9) -> 0 | D18: =MAX(0,Copertura!$Y$10-Copertura!$W$10,Copertura!$Y$11-Copertura!$W$11,Copertura!$Y$12-Copertura!$W$12,Copertura!$Y$13-Copertura!$W$13) -> 0 | E18: =MAX(0,Copertura!$Y$14-Copertura!$W$14,Copertura!$Y$15-Copertura!$W$15,Copertura!$Y$16-Copertura!$W$16,Copertura!$Y$17-Copertura!$W$17) -> 0 | F18: =MAX(0,Copertura!$Y$18-Copertura!$W$18,Copertura!$Y$19-Copertura!$W$19,Copertura!$Y$20-Copertura!$W$20,Copertura!$Y$21-Copertura!$W$21) -> 0 | G18: =MAX(0,Copertura!$Y$22-Copertura!$W$22,Copertura!$Y$23-Copertura!$W$23,Copertura!$Y$24-Copertura!$W$24,Copertura!$Y$25-Copertura!$W$25) -> 0 | H18: =MAX(0,Copertura!$Y$26-Copertura!$W$26,Copertura!$Y$27-Copertura!$W$27,Copertura!$Y$28-Copertura!$W$28,Copertura!$Y$29-Copertura!$W$29) -> 0 | I18: =MAX(0,Copertura!$Y$30-Copertura!$W$30,Copertura!$Y$31-Copertura!$W$31,Copertura!$Y$32-Copertura!$W$32,Copertura!$Y$33-Copertura!$W$33) -> 0 | J18: =MAX(0,Copertura!$Y$34-Copertura!$W$34,Copertura!$Y$35-Copertura!$W$35,Copertura!$Y$36-Copertura!$W$36,Copertura!$Y$37-Copertura!$W$37) -> 0 | K18: =MAX(0,Copertura!$Y$38-Copertura!$W$38,Copertura!$Y$39-Copertura!$W$39,Copertura!$Y$40-Copertura!$W$40,Copertura!$Y$41-Copertura!$W$41) -> 0 | L18: =MAX(0,Copertura!$Y$42-Copertura!$W$42,Copertura!$Y$43-Copertura!$W$43,Copertura!$Y$44-Copertura!$W$44,Copertura!$Y$45-Copertura!$W$45) -> 0 | M18: =MAX(0,Copertura!$Y$46-Copertura!$W$46,Copertura!$Y$47-Copertura!$W$47,Copertura!$Y$48-Copertura!$W$48,Copertura!$Y$49-Copertura!$W$49) -> 0 | N18: =MAX(0,Copertura!$Y$50-Copertura!$W$50,Copertura!$Y$51-Copertura!$W$51,Copertura!$Y$52-Copertura!$W$52,Copertura!$Y$53-Copertura!$W$53) -> 0 | O18: =MAX(0,Copertura!$Y$54-Copertura!$W$54,Copertura!$Y$55-Copertura!$W$55,Copertura!$Y$56-Copertura!$W$56,Copertura!$Y$57-Copertura!$W$57) -> 0 | P18: =MAX(0,Copertura!$Y$58-Copertura!$W$58,Copertura!$Y$59-Copertura!$W$59,Copertura!$Y$60-Copertura!$W$60,Copertura!$Y$61-Copertura!$W$61) -> 0 | Q18: =MAX(0,Copertura!$Y$62-Copertura!$W$62,Copertura!$Y$63-Copertura!$W$63,Copertura!$Y$64-Copertura!$W$64,Copertura!$Y$65-Copertura!$W$65) -> 0 | R18: =MAX(0,Copertura!$Y$66-Copertura!$W$66,Copertura!$Y$67-Copertura!$W$67,Copertura!$Y$68-Copertura!$W$68) -> 0
B19: Dom | C19: =MAX(0,Copertura!$AC$6-Copertura!$AA$6,Copertura!$AC$7-Copertura!$AA$7,Copertura!$AC$8-Copertura!$AA$8,Copertura!$AC$9-Copertura!$AA$9) -> 0 | D19: =MAX(0,Copertura!$AC$10-Copertura!$AA$10,Copertura!$AC$11-Copertura!$AA$11,Copertura!$AC$12-Copertura!$AA$12,Copertura!$AC$13-Copertura!$AA$13) -> 0 | E19: =MAX(0,Copertura!$AC$14-Copertura!$AA$14,Copertura!$AC$15-Copertura!$AA$15,Copertura!$AC$16-Copertura!$AA$16,Copertura!$AC$17-Copertura!$AA$17) -> 0 | F19: =MAX(0,Copertura!$AC$18-Copertura!$AA$18,Copertura!$AC$19-Copertura!$AA$19,Copertura!$AC$20-Copertura!$AA$20,Copertura!$AC$21-Copertura!$AA$21) -> 0 | G19: =MAX(0,Copertura!$AC$22-Copertura!$AA$22,Copertura!$AC$23-Copertura!$AA$23,Copertura!$AC$24-Copertura!$AA$24,Copertura!$AC$25-Copertura!$AA$25) -> 0 | H19: =MAX(0,Copertura!$AC$26-Copertura!$AA$26,Copertura!$AC$27-Copertura!$AA$27,Copertura!$AC$28-Copertura!$AA$28,Copertura!$AC$29-Copertura!$AA$29) -> 0 | I19: =MAX(0,Copertura!$AC$30-Copertura!$AA$30,Copertura!$AC$31-Copertura!$AA$31,Copertura!$AC$32-Copertura!$AA$32,Copertura!$AC$33-Copertura!$AA$33) -> 0 | J19: =MAX(0,Copertura!$AC$34-Copertura!$AA$34,Copertura!$AC$35-Copertura!$AA$35,Copertura!$AC$36-Copertura!$AA$36,Copertura!$AC$37-Copertura!$AA$37) -> 0 | K19: =MAX(0,Copertura!$AC$38-Copertura!$AA$38,Copertura!$AC$39-Copertura!$AA$39,Copertura!$AC$40-Copertura!$AA$40,Copertura!$AC$41-Copertura!$AA$41) -> 0 | L19: =MAX(0,Copertura!$AC$42-Copertura!$AA$42,Copertura!$AC$43-Copertura!$AA$43,Copertura!$AC$44-Copertura!$AA$44,Copertura!$AC$45-Copertura!$AA$45) -> 0 | M19: =MAX(0,Copertura!$AC$46-Copertura!$AA$46,Copertura!$AC$47-Copertura!$AA$47,Copertura!$AC$48-Copertura!$AA$48,Copertura!$AC$49-Copertura!$AA$49) -> 0 | N19: =MAX(0,Copertura!$AC$50-Copertura!$AA$50,Copertura!$AC$51-Copertura!$AA$51,Copertura!$AC$52-Copertura!$AA$52,Copertura!$AC$53-Copertura!$AA$53) -> 0 | O19: =MAX(0,Copertura!$AC$54-Copertura!$AA$54,Copertura!$AC$55-Copertura!$AA$55,Copertura!$AC$56-Copertura!$AA$56,Copertura!$AC$57-Copertura!$AA$57) -> 0 | P19: =MAX(0,Copertura!$AC$58-Copertura!$AA$58,Copertura!$AC$59-Copertura!$AA$59,Copertura!$AC$60-Copertura!$AA$60,Copertura!$AC$61-Copertura!$AA$61) -> 0 | Q19: =MAX(0,Copertura!$AC$62-Copertura!$AA$62,Copertura!$AC$63-Copertura!$AA$63,Copertura!$AC$64-Copertura!$AA$64,Copertura!$AC$65-Copertura!$AA$65) -> 0 | R19: =MAX(0,Copertura!$AC$66-Copertura!$AA$66,Copertura!$AC$67-Copertura!$AA$67,Copertura!$AC$68-Copertura!$AA$68) -> 0
B20: scuro = coperto · giallo = 1 mancante · rosso = 2+ (fasce orarie 5:30→21:00)
B23: ▍ SCENARIO ASSENZE
B25: ASSENZE | F25: ORE PERSE | J25: RESP OK | N25: DEFICIT
B26: =Personale!$H$41 -> 5 ass. | F26: =Personale!$I$41 -> 140 | J26: =(6-SUMPRODUCT(--(Personale!$B$5:$B$40="RESP"),--(Personale!$H$5:$H$40<>""))) -> 5 | N26: =MAX(0,OreRichieste!$I$17-(Personale!$C$41-Personale!$I$41)) -> 189.76609
B29: =IF((6-SUMPRODUCT(--(Personale!$B$5:$B$40="RESP"),--(Personale!$H$5:$H$40<>"")))<2,"◆ CRITICO — meno di 2 responsabili in servizio",IF(MAX(0,OreRichieste!$I$17-(Personale!$C$41-Personale!$I$41))=0,"● TUTTO OK — copertura garantita, nessun intervento",IF(MAX(0,OreRichieste!$I$17-(Personale!$C$41-Personale!$I$41))<=50,"▲ CHIAMA JOLLY — "&ROUNDUP(MAX(0,OreRichieste!$I$17-(Personale!$C$41-Personale!$I$41))/25,0)&" jolly (su 2) coprono il buco",IF(MAX(0,OreRichieste!$I$17-(Personale!$C$41-Personale!$I$41))<=90,"▲ JOLLY + STRAORD — 2 jolly + "&TEXT(MAX(0,OreRichieste!$I$17-(Personale!$C$41-Personale!$I$41))-50,"0")&"h di straordinario","◆ CRITICO — deficit "&TEXT(MAX(0,OreRichieste!$I$17-(Personale!$C$41-Personale!$I$41)),"0")&"h: oltre 2 jolly + straordinari legali")))) -> ◆ CRITICO — deficit 190h: oltre 2 jolly + straordinari legali
B31: Segna le assenze nel foglio Personale (colonna Assenza: F=ferie, M=malattia). Questo semaforo reagisce dal vivo.
B33: ▸ Fogli: Grafici (Daily Planner + dettaglio) · Turni · Personale (organico + assenze) · Copertura
B34: ▸ Generatore: python generatore_turni.py Modello_Ore_LIDL_v3.xlsx [--auto-ot]

Sheet Home
B2: STORE HOURS ENGINE
B4: Modello ore punto vendita · formato discount LIDL · staff polivalente · v2
B8: ="MODELLO SETTIMANA TIPO: € "&ROUND(Parametri!B5/1000,0)&"k · "&ROUND(Parametri!B6/1000,0)&"k pezzi · "&ROUND(OreRichieste!I17,0)&" ore richieste · KPI in linea: "&COUNTIF(Dashboard!G15:G17,"IN LINEA")&"/3 · Anomalie orario: "&SUM(Dashboard!D54:D59) -> MODELLO SETTIMANA TIPO: € 226k · 136k pezzi · 554 ore richieste · KPI in linea: 2/3 · Anomalie orario: 28
B10: NAVIGAZIONE
B12: DASHBOARD | E12: PERSONALE | H12: TURNI
B14: COPERTURA | E14: PARAMETRI | H14: VOLUMI
B16: CASSE + SCO | E16: ORE RICHIESTE | H16: ORGANICO
B19: COME FUNZIONA
B20: MOTORE | E20: ORARIO DI LAVORO | H20: CONTROLLI VIVI
B21: Ore richieste = volumi x standard a pedana (minuti per PLT) + attivita fisse, per attivita e non per reparto. Front-end dimensionato per fascia oraria (coeff. P75-P80) piu presidio SCO. | E21: Da Personale (organico e monte ore) l'algoritmo genera i Turni: ingresso 5:30 Lun-Gio-Sab e 6:00 gli altri giorni, uscita 21:15, stacco 11h anche sul giro Dom->Lun, aperture e chiusure mai sotto le 2 persone, un responsabile sempre in negozio, part time 25h->5h/g e 30h->6h/g. | H21: Turni e Copertura verificano con formule ogni modifica manuale: slot da 15 minuti presenti vs richiesti, presidio responsabile, stacchi, quadratura monte ore. Semafori riassunti in Dashboard e Home.
B28: LEGENDA E ISTRUZIONI
B29: Testo BLU = input modificabile · Sfondo GIALLO = leve principali · Testo VERDE = formula collegata (non toccare)
B30: 1. Parametri: leve del modello, standard e regole orario di lavoro.
B31: 2. Volumi: calibra % per giorno e profilo per fascia con i dati di cassa reali.
B32: 3. Personale: inserisci organico, ruoli e monte ore.
B33: 4. Turni: orario generato; modificabile a mano, i controlli restano attivi.
B34: 5. Copertura e Dashboard: semafori su coperture, stacchi, aperture/chiusure e produttivita.
B35: Nota: i turni sono valori (blu); i vincoli sono formule vive che segnalano ogni violazione.

Sheet Dashboard
B1: DASHBOARD · STORE HOURS ENGINE
B5: FATTURATO / SETTIMANA | D5: PEZZI VENDUTI / SETTIMANA | F5: ORE RICHIESTE / SETTIMANA
B6: =Parametri!B5 -> 226000 | D6: =Parametri!B6 -> 136000 | F6: =OreRichieste!I17 -> 553.76609
B7: ="Scontrino medio: € "&Parametri!B7 -> Scontrino medio: € 27.77 | D7: ="Scontrini: "&ROUND(Parametri!B8,0) -> Scontrini: 8138 | F7: ="Pianificate: "&ROUND(Organico!I7,0)&" h" -> Pianificate: 553 h
B9: PRODUTTIVITA EUR/ORA | D9: PRODUTTIVITA PEZZI/ORA | F9: INCIDENZA COSTO LAVORO
B10: =IFERROR(Parametri!B5/OreRichieste!I17,"") -> 408.11455 | D10: =IFERROR(Parametri!B6/OreRichieste!I17,"") -> 245.59106 | F10: =IFERROR(Organico!I7*Parametri!B10/Parametri!B5,"") -> 0.053783186
B11: =IF(Parametri!B5/OreRichieste!I17<Parametri!B56,"SOTTO TARGET",IF(Parametri!B5/OreRichieste!I17>Parametri!B57,"SOPRA TARGET","IN LINEA")) -> IN LINEA | D11: =IF(Parametri!B6/OreRichieste!I17<Parametri!B54,"SOTTO TARGET",IF(Parametri!B6/OreRichieste!I17>Parametri!B55,"SOPRA TARGET","IN LINEA")) -> SOTTO TARGET | F11: =IF(Organico!I7*Parametri!B10/Parametri!B5<=Parametri!B58,"IN LINEA","SOPRA SOGLIA") -> IN LINEA
B13: VERIFICA PRODUTTIVITA VS BENCHMARK
B14: Indicatore | D14: Su ore richieste | E14: Su ore PLAN | F14: Target | G14: Esito
B15: Produttivita (EUR/ora) | D15: =IFERROR(Parametri!B5/OreRichieste!I17,"") -> 408.11455 | E15: =IFERROR(Parametri!B5/Organico!I7,"") -> 409.04977 | F15: =Parametri!B56&" - "&Parametri!B57&" €/h" -> 340 - 420 €/h | G15: =IF(D15<Parametri!B56,"SOTTO TARGET",IF(D15>Parametri!B57,"SOPRA TARGET","IN LINEA")) -> IN LINEA
B16: Produttivita (pezzi/ora) | D16: =IFERROR(Parametri!B6/OreRichieste!I17,"") -> 245.59106 | E16: =IFERROR(Parametri!B6/Organico!I7,"") -> 246.15385 | F16: =Parametri!B54&" - "&Parametri!B55&" pz/h" -> 280 - 300 pz/h | G16: =IF(D16<Parametri!B54,"SOTTO TARGET",IF(D16>Parametri!B55,"SOPRA TARGET","IN LINEA")) -> SOTTO TARGET
B17: Incidenza costo lavoro | D17: =IFERROR(OreRichieste!I17*Parametri!B10/Parametri!B5,"") -> 0.053906434 | E17: =IFERROR(Organico!I7*Parametri!B10/Parametri!B5,"") -> 0.053783186 | F17: ="max "&ROUND(Parametri!B58*100,1)&"%" -> max 7% | G17: =IF(D17<=Parametri!B58,"IN LINEA","SOPRA SOGLIA") -> IN LINEA
B19: ORE PER GIORNO · richieste vs pianificate
B20: Giorno | C20: Richieste | D20: Pianificate | E20: Gap | F20: Saturazione
B21: Lun | C21: =OreRichieste!B17 -> 86.038955 | D21: =Organico!B7 -> 86 | E21: =D21-C21 -> -0.038954753 | F21: =IFERROR(C21/D21,"") -> 1.000453
B22: Mar | C22: =OreRichieste!C17 -> 69.028528 | D22: =Organico!C7 -> 69 | E22: =D22-C22 -> -0.028527729 | F22: =IFERROR(C22/D22,"") -> 1.0004134
B23: Mer | C23: =OreRichieste!D17 -> 71.662996 | D23: =Organico!D7 -> 71.5 | E23: =D23-C23 -> -0.16299554 | F23: =IFERROR(C23/D23,"") -> 1.0022797
B24: Gio | C24: =OreRichieste!E17 -> 82.673423 | D24: =Organico!E7 -> 82.5 | E24: =D24-C24 -> -0.17342257 | F24: =IFERROR(C24/D24,"") -> 1.0021021
B25: Ven | C25: =OreRichieste!F17 -> 79.414914 | D25: =Organico!F7 -> 79 | E25: =D25-C25 -> -0.41491396 | F25: =IFERROR(C25/D25,"") -> 1.0052521
B26: Sab | C26: =OreRichieste!G17 -> 94.187686 | D26: =Organico!G7 -> 94 | E26: =D26-C26 -> -0.18768643 | F26: =IFERROR(C26/D26,"") -> 1.0019967
B27: Dom | C27: =OreRichieste!H17 -> 70.759592 | D27: =Organico!H7 -> 70.5 | E27: =D27-C27 -> -0.2595921 | F27: =IFERROR(C27/D27,"") -> 1.0036822
B28: Totale | C28: =OreRichieste!I17 -> 553.76609 | D28: =Organico!I7 -> 552.5 | E28: =D28-C28 -> -1.2660931 | F28: =IFERROR(C28/D28,"") -> 1.0022916
B30: MIX ORE PER ATTIVITA · settimana
B31: Attivita | D31: Ore/sett | E31: % sul totale
B32: =OreRichieste!A4 -> Controllo scorte e ordini merce | D32: =OreRichieste!I4 -> 10.5 | E32: =IFERROR(D32/$D$45,"") -> 0.018961074
B33: =OreRichieste!A5 -> Rifornimento FV | D33: =OreRichieste!I5 -> 29.466667 | E33: =IFERROR(D33/$D$45,"") -> 0.053211396
B34: =OreRichieste!A6 -> BAKE: cottura ed esposizione | D34: =OreRichieste!I6 -> 48.733333 | E34: =IFERROR(D34/$D$45,"") -> 0.088003462
B35: =OreRichieste!A7 -> Rifornimento CARNE | D35: =OreRichieste!I7 -> 8.4722963 | E35: =IFERROR(D35/$D$45,"") -> 0.015299413
B36: =OreRichieste!A8 -> Rifornimento SECCHI | D36: =OreRichieste!I8 -> 49.425369 | E36: =IFERROR(D36/$D$45,"") -> 0.089253151
B37: =OreRichieste!A9 -> Rifornimento SURGELATI | D37: =OreRichieste!I9 -> 10.205867 | E37: =IFERROR(D37/$D$45,"") -> 0.018429923
B38: =OreRichieste!A10 -> Rifornimento FRESCHI | D38: =OreRichieste!I10 -> 23.082681 | E38: =IFERROR(D38/$D$45,"") -> 0.041683088
B39: =OreRichieste!A11 -> Allestimento PROMO FOOD | D39: =OreRichieste!I11 -> 3.7603687 | E39: =IFERROR(D39/$D$45,"") -> 0.0067905361
B40: =OreRichieste!A12 -> Allestimento PROMO NF | D40: =OreRichieste!I12 -> 9.6195122 | E40: =IFERROR(D40/$D$45,"") -> 0.017371075
B41: =OreRichieste!A13 -> Barriera casse | D41: =OreRichieste!I13 -> 190 | E41: =IFERROR(D41/$D$45,"") -> 0.34310515
B42: =OreRichieste!A14 -> Presidio SCO | D42: =OreRichieste!I14 -> 68 | E42: =IFERROR(D42/$D$45,"") -> 0.12279553
B43: =OreRichieste!A15 -> Attivita fisse giornaliere | D43: =OreRichieste!I15 -> 80.5 | E43: =IFERROR(D43/$D$45,"") -> 0.14536824
B44: =OreRichieste!A16 -> Attivita settimanali | D44: =OreRichieste!I16 -> 22 | E44: =IFERROR(D44/$D$45,"") -> 0.039727965
B45: Totale | D45: =OreRichieste!I17 -> 553.76609 | E45: =IFERROR(D45/$D$45,"") -> 1
B47: DETTAGLIO OPERATIVO
B48: Costo del lavoro su ore pianificate | D48: =Organico!I7*Parametri!B10 -> 12155
B49: Scontrini per ora di barriera | D49: =IFERROR(Parametri!B8*(1-Parametri!B16)/Casse!I19,"") -> 29.983132
B50: Casse barriera max in contemporanea | D50: =MAX(Casse!B20:H20) -> 3 | E50: =IF(D50<=Parametri!B18,"OK","OLTRE DISPONIBILI") -> OK
B51: Ore presidio SCO / settimana | D51: =Casse!I25 -> 68
B53: CONFORMITA ORARIO DI LAVORO · controlli automatici sui fogli Turni e Copertura
B54: Stacchi sotto le 11 ore (dipendenti) | D54: =COUNTIF(Turni!AD5:AD27,"KO") -> 0 | E54: =IF(D54=0,"OK","KO") -> OK
B55: Dipendenti con ore diverse dal monte ore | D55: =SUMPRODUCT(--(ABS(Turni!AB5:AB27)>0.05)) -> 21 | E55: =IF(D55=0,"OK","KO") -> KO
B56: Slot da 15 min sotto copertura minima | D56: =Copertura!C70+Copertura!G70+Copertura!K70+Copertura!O70+Copertura!S70+Copertura!W70+Copertura!AA70 -> 7 | E56: =IF(D56=0,"OK","KO") -> KO
B57: Slot senza responsabile in negozio | D57: =Copertura!C71+Copertura!G71+Copertura!K71+Copertura!O71+Copertura!S71+Copertura!W71+Copertura!AA71 -> 0 | E57: =IF(D57=0,"OK","KO") -> OK
B58: Aperture con meno di 2 persone | D58: =COUNTIF(Turni!B33:H33,"<"&Parametri!B67) -> 0 | E58: =IF(D58=0,"OK","KO") -> OK
B59: Chiusure con meno di 2 persone | D59: =COUNTIF(Turni!B34:H34,"<"&Parametri!B68) -> 0 | E59: =IF(D59=0,"OK","KO") -> OK

Sheet Personale
A1: ORGANICO E MONTE ORE · input del generatore turni | J1: Costo_orario | K1: Straordinario_sett
A2: Modifica nomi, ruoli e monte ore in blu. Ore/giorno = monte ore / giorni lavorativi (regola part time 25h->5h, 30h->6h).
A4: Dipendente | B4: Ruolo | C4: Monte ore | D4: Giorni lav. | E4: Ore/giorno | F4: Riposi | H4: Assenza | I4: Ore perse | L4: Lun | M4: Mar | N4: Mer | O4: Gio | P4: Ven | Q4: Sab | R4: Dom | S4: OreP
A5: RESP 01 | B5: RESP | C5: 38 | D5: 6 | E5: =IF(D5>0,C5/D5,0) -> 6.3333333 | F5: =7-D5 -> 1 | I5: =IF($H5<>"",$C5,0) -> 0
A6: RESP 02 | B6: RESP | C6: 25 | D6: 6 | E6: =IF(D6>0,C6/D6,0) -> 4.1666667 | F6: =7-D6 -> 1 | I6: =IF($H6<>"",$C6,0) -> 0
A7: RESP 03 | B7: RESP | C7: 25 | D7: 5 | E7: =IF(D7>0,C7/D7,0) -> 5 | F7: =7-D7 -> 2 | I7: =IF($H7<>"",$C7,0) -> 0
A8: RESP 04 | B8: RESP | C8: 25 | D8: 5 | E8: =IF(D8>0,C8/D8,0) -> 5 | F8: =7-D8 -> 2 | I8: =IF($H8<>"",$C8,0) -> 0
A9: RESP 05 | B9: RESP | C9: 40 | D9: 6 | E9: =IF(D9>0,C9/D9,0) -> 6.6666667 | F9: =7-D9 -> 1 | H9: M | I9: =IF($H9<>"",$C9,0) -> 40
A10: RESP 06 | B10: RESP | C10: 25 | D10: 5 | E10: =IF(D10>0,C10/D10,0) -> 5 | F10: =7-D10 -> 2 | I10: =IF($H10<>"",$C10,0) -> 0
A11: RESP 07 | B11: RESP | C11: 25 | D11: 5 | E11: =IF(D11>0,C11/D11,0) -> 5 | F11: =7-D11 -> 2 | I11: =IF($H11<>"",$C11,0) -> 0
A12: ADDETTO 01 | B12: ADDETTO | C12: 25 | D12: 5 | E12: =IF(D12>0,C12/D12,0) -> 5 | F12: =7-D12 -> 2 | I12: =IF($H12<>"",$C12,0) -> 0
A13: ADDETTO 02 | B13: ADDETTO | C13: 20 | D13: 5 | E13: =IF(D13>0,C13/D13,0) -> 4 | F13: =7-D13 -> 2 | I13: =IF($H13<>"",$C13,0) -> 0
A14: ADDETTO 03 | B14: ADDETTO | C14: 25 | D14: 5 | E14: =IF(D14>0,C14/D14,0) -> 5 | F14: =7-D14 -> 2 | I14: =IF($H14<>"",$C14,0) -> 0
A15: ADDETTO 04 | B15: ADDETTO | C15: 25 | D15: 5 | E15: =IF(D15>0,C15/D15,0) -> 5 | F15: =7-D15 -> 2 | I15: =IF($H15<>"",$C15,0) -> 0
A16: ADDETTO 05 | B16: ADDETTO | C16: 25 | D16: 5 | E16: =IF(D16>0,C16/D16,0) -> 5 | F16: =7-D16 -> 2 | I16: =IF($H16<>"",$C16,0) -> 0
A17: ADDETTO 06 | B17: ADDETTO | C17: 25 | D17: 5 | E17: =IF(D17>0,C17/D17,0) -> 5 | F17: =7-D17 -> 2 | I17: =IF($H17<>"",$C17,0) -> 0
A18: ADDETTO 07 | B18: ADDETTO | C18: 25 | D18: 5 | E18: =IF(D18>0,C18/D18,0) -> 5 | F18: =7-D18 -> 2 | I18: =IF($H18<>"",$C18,0) -> 0
A19: ADDETTO 08 | B19: ADDETTO | C19: 25 | D19: 5 | E19: =IF(D19>0,C19/D19,0) -> 5 | F19: =7-D19 -> 2 | I19: =IF($H19<>"",$C19,0) -> 0
A20: ADDETTO 09 | B20: ADDETTO | C20: 30 | D20: 5 | E20: =IF(D20>0,C20/D20,0) -> 6 | F20: =7-D20 -> 2 | I20: =IF($H20<>"",$C20,0) -> 0
A21: ADDETTO 10 | B21: ADDETTO | C21: 25 | D21: 5 | E21: =IF(D21>0,C21/D21,0) -> 5 | F21: =7-D21 -> 2 | I21: =IF($H21<>"",$C21,0) -> 0
A22: ADDETTO 11 | B22: ADDETTO | C22: 25 | D22: 5 | E22: =IF(D22>0,C22/D22,0) -> 5 | F22: =7-D22 -> 2 | H22: M | I22: =IF($H22<>"",$C22,0) -> 25
A23: ADDETTO 12 | B23: ADDETTO | C23: 25 | D23: 5 | E23: =IF(D23>0,C23/D23,0) -> 5 | F23: =7-D23 -> 2 | H23: M | I23: =IF($H23<>"",$C23,0) -> 25
A24: ADDETTO 13 | B24: ADDETTO | C24: 30 | D24: 5 | E24: =IF(D24>0,C24/D24,0) -> 6 | F24: =7-D24 -> 2 | I24: =IF($H24<>"",$C24,0) -> 0
A25: ADDETTO 14 | B25: ADDETTO | C25: 25 | D25: 5 | E25: =IF(D25>0,C25/D25,0) -> 5 | F25: =7-D25 -> 2 | H25: M | I25: =IF($H25<>"",$C25,0) -> 25
A26: ADDETTO 15 | B26: ADDETTO | C26: 25 | D26: 5 | E26: =IF(D26>0,C26/D26,0) -> 5 | F26: =7-D26 -> 2 | I26: =IF($H26<>"",$C26,0) -> 0
A27: ADDETTO 16 | B27: ADDETTO | C27: 20 | D27: 5 | E27: =IF(D27>0,C27/D27,0) -> 4 | F27: =7-D27 -> 2 | I27: =IF($H27<>"",$C27,0) -> 0
A28: ADDETTO 17 | B28: ADDETTO | C28: 25 | D28: 5 | E28: =IF(D28>0,C28/D28,0) -> 5 | F28: =7-D28 -> 2 | H28: M | I28: =IF($H28<>"",$C28,0) -> 25
A29: ADDETTO 18 | B29: ADDETTO | C29: 8 | D29: 1 | E29: =IF(D29>0,C29/D29,0) -> 8 | F29: =7-D29 -> 6 | I29: =IF($H29<>"",$C29,0) -> 0
A30: FRANCESCON | B30: ADDETTO | C30: 8 | D30: 1 | E30: =IF(D30>0,C30/D30,0) -> 8 | F30: =7-D30 -> 6 | I30: =IF($H30<>"",$C30,0) -> 0
E31: =IF(D31>0,C31/D31,0) -> 0 | F31: =7-D31 -> 7 | I31: =IF($H31<>"",$C31,0) -> 0
E32: =IF(D32>0,C32/D32,0) -> 0 | F32: =7-D32 -> 7 | I32: =IF($H32<>"",$C32,0) -> 0
E33: =IF(D33>0,C33/D33,0) -> 0 | F33: =7-D33 -> 7 | I33: =IF($H33<>"",$C33,0) -> 0
E34: =IF(D34>0,C34/D34,0) -> 0 | F34: =7-D34 -> 7 | I34: =IF($H34<>"",$C34,0) -> 0
E35: =IF(D35>0,C35/D35,0) -> 0 | F35: =7-D35 -> 7 | I35: =IF($H35<>"",$C35,0) -> 0
E36: =IF(D36>0,C36/D36,0) -> 0 | F36: =7-D36 -> 7 | I36: =IF($H36<>"",$C36,0) -> 0
E37: =IF(D37>0,C37/D37,0) -> 0 | F37: =7-D37 -> 7 | I37: =IF($H37<>"",$C37,0) -> 0
E38: =IF(D38>0,C38/D38,0) -> 0 | F38: =7-D38 -> 7 | I38: =IF($H38<>"",$C38,0) -> 0
E39: =IF(D39>0,C39/D39,0) -> 0 | F39: =7-D39 -> 7 | I39: =IF($H39<>"",$C39,0) -> 0
E40: =IF(D40>0,C40/D40,0) -> 0 | F40: =7-D40 -> 7 | I40: =IF($H40<>"",$C40,0) -> 0
A41: Totale | B41: =COUNTA(A5:A40)&" teste" -> 26 teste | C41: =SUM(C5:C40)-I31 -> 504 | H41: =COUNTA(H5:H40)&" ass." -> 5 ass. | I41: =SUM(I5:I40) -> 140
A43: Ore richieste dal modello (settimana) | B43: =OreRichieste!I17 -> 553.76609
A44: Margine organico (monte ore - richieste) | B44: =C41-B43 -> -49.766093
A45: Verifica dimensionamento | B45: =IF(B44>=0,"OK","KO: organico insufficiente") -> KO: organico insufficiente
A47: Un margine del 4-8% copre code di rifornimento, picchi e flessibilita; ferie e malattie vanno gestite a parte.

Sheet Turni
A1: ORARIO DI LAVORO SETTIMANALE · generato dall'algoritmo, modificabile
F3: Lun | I3: Mar | L3: Mer | O3: Gio | R3: Ven | U3: Sab | X3: Dom
A4: Dipendente | B4: Ruolo | C4: Monte | D4: GG | E4: h/g | F4: In | G4: Out | H4: Ore | I4: In | J4: Out | K4: Ore | L4: In | M4: Out | N4: Ore | O4: In | P4: Out | Q4: Ore | R4: In | S4: Out | T4: Ore | U4: In | V4: Out | W4: Ore | X4: In | Y4: Out | Z4: Ore | AA4: Tot | AB4: Delta | AC4: GG | AD4: Stacco
A5: {=IFERROR(INDEX(Personale!$A$5:$A$40,SMALL(IF(Personale!$H$5:$H$40="",ROW(Personale!$A$5:$A$40)-ROW(Personale!$A$5)+1),1)),"")} -> DE PICCOLI | B5: =IFERROR(VLOOKUP($A5,Personale!$A$5:$E$40,2,0),"") -> RESP | C5: =IFERROR(VLOOKUP($A5,Personale!$A$5:$E$40,3,0),0) -> 38 | D5: =IFERROR(VLOOKUP($A5,Personale!$A$5:$E$40,4,0),0) -> 6 | E5: =IFERROR(VLOOKUP($A5,Personale!$A$5:$E$40,5,0),0) -> 6.3333333 | F5: 0.58333333 | G5: 0.83333333 | H5: =IF(AND(ISNUMBER(F5),ISNUMBER(G5)),(G5-F5)*24,0) -> 6 | I5: R | J5: R | K5: =IF(AND(ISNUMBER(I5),ISNUMBER(J5)),(J5-I5)*24,0) -> 0 | L5: 0.45833333 | M5: 0.72916667 | N5: =IF(AND(ISNUMBER(L5),ISNUMBER(M5)),(M5-L5)*24,0) -> 6.5 | O5: 0.61458333 | P5: 0.88541667 | Q5: =IF(AND(ISNUMBER(O5),ISNUMBER(P5)),(P5-O5)*24,0) -> 6.5 | R5: 0.52083333 | S5: 0.83333333 | T5: =IF(AND(ISNUMBER(R5),ISNUMBER(S5)),(S5-R5)*24,0) -> 7.5 | U5: 0.33333333 | V5: 0.58333333 | W5: =IF(AND(ISNUMBER(U5),ISNUMBER(V5)),(V5-U5)*24,0) -> 6 | X5: 0.33333333 | Y5: 0.64583333 | Z5: =IF(AND(ISNUMBER(X5),ISNUMBER(Y5)),(Y5-X5)*24,0) -> 7.5 | AA5: =H5+K5+N5+Q5+T5+W5+Z5 -> 40 | AB5: =AA5-C5 -> 2 | AC5: =(H5>0)+(K5>0)+(N5>0)+(Q5>0)+(T5>0)+(W5>0)+(Z5>0) -> 6 | AD5: =IF(OR(IF(ISNUMBER(G5)*ISNUMBER(I5),(I5+1-G5)*24<Parametri!$B$65),IF(ISNUMBER(J5)*ISNUMBER(L5),(L5+1-J5)*24<Parametri!$B$65),IF(ISNUMBER(M5)*ISNUMBER(O5),(O5+1-M5)*24<Parametri!$B$65),IF(ISNUMBER(P5)*ISNUMBER(R5),(R5+1-P5)*24<Parametri!$B$65),IF(ISNUMBER(S5)*ISNUMBER(U5),(U5+1-S5)*24<Parametri!$B$65),IF(ISNUMBER(V5)*ISNUMBER(X5),(X5+1-V5)*24<Parametri!$B$65),IF(ISNUMBER(Y5)*ISNUMBER(F5),(F5+1-Y5)*24<Parametri!$B$65)),"KO","OK") -> OK
A6: {=IFERROR(INDEX(Personale!$A$5:$A$40,SMALL(IF(Personale!$H$5:$H$40="",ROW(Personale!$A$5:$A$40)-ROW(Personale!$A$5)+1),2)),"")} -> DA PARE’ | B6: =IFERROR(VLOOKUP($A6,Personale!$A$5:$E$40,2,0),"") -> RESP | C6: =IFERROR(VLOOKUP($A6,Personale!$A$5:$E$40,3,0),0) -> 25 | D6: =IFERROR(VLOOKUP($A6,Personale!$A$5:$E$40,4,0),0) -> 6 | E6: =IFERROR(VLOOKUP($A6,Personale!$A$5:$E$40,5,0),0) -> 4.1666667 | F6: 0.69791667 | G6: 0.88541667 | H6: =IF(AND(ISNUMBER(F6),ISNUMBER(G6)),(G6-F6)*24,0) -> 4.5 | I6: 0.63541667 | J6: 0.88541667 | K6: =IF(AND(ISNUMBER(I6),ISNUMBER(J6)),(J6-I6)*24,0) -> 6 | L6: 0.71875 | M6: 0.88541667 | N6: =IF(AND(ISNUMBER(L6),ISNUMBER(M6)),(M6-L6)*24,0) -> 4 | O6: 0.71875 | P6: 0.88541667 | Q6: =IF(AND(ISNUMBER(O6),ISNUMBER(P6)),(P6-O6)*24,0) -> 4 | R6: 0.67708333 | S6: 0.88541667 | T6: =IF(AND(ISNUMBER(R6),ISNUMBER(S6)),(S6-R6)*24,0) -> 5 | U6: 0.71875 | V6: 0.88541667 | W6: =IF(AND(ISNUMBER(U6),ISNUMBER(V6)),(V6-U6)*24,0) -> 4 | X6: R | Y6: R | Z6: =IF(AND(ISNUMBER(X6),ISNUMBER(Y6)),(Y6-X6)*24,0) -> 0 | AA6: =H6+K6+N6+Q6+T6+W6+Z6 -> 27.5 | AB6: =AA6-C6 -> 2.5 | AC6: =(H6>0)+(K6>0)+(N6>0)+(Q6>0)+(T6>0)+(W6>0)+(Z6>0) -> 6 | AD6: =IF(OR(IF(ISNUMBER(G6)*ISNUMBER(I6),(I6+1-G6)*24<Parametri!$B$65),IF(ISNUMBER(J6)*ISNUMBER(L6),(L6+1-J6)*24<Parametri!$B$65),IF(ISNUMBER(M6)*ISNUMBER(O6),(O6+1-M6)*24<Parametri!$B$65),IF(ISNUMBER(P6)*ISNUMBER(R6),(R6+1-P6)*24<Parametri!$B$65),IF(ISNUMBER(S6)*ISNUMBER(U6),(U6+1-S6)*24<Parametri!$B$65),IF(ISNUMBER(V6)*ISNUMBER(X6),(X6+1-V6)*24<Parametri!$B$65),IF(ISNUMBER(Y6)*ISNUMBER(F6),(F6+1-Y6)*24<Parametri!$B$65)),"KO","OK") -> OK
A7: {=IFERROR(INDEX(Personale!$A$5:$A$40,SMALL(IF(Personale!$H$5:$H$40="",ROW(Personale!$A$5:$A$40)-ROW(Personale!$A$5)+1),3)),"")} -> DE PELLEGRIN | B7: =IFERROR(VLOOKUP($A7,Personale!$A$5:$E$40,2,0),"") -> RESP | C7: =IFERROR(VLOOKUP($A7,Personale!$A$5:$E$40,3,0),0) -> 25 | D7: =IFERROR(VLOOKUP($A7,Personale!$A$5:$E$40,4,0),0) -> 5 | E7: =IFERROR(VLOOKUP($A7,Personale!$A$5:$E$40,5,0),0) -> 5 | F7: 0.22916667 | G7: 0.4375 | H7: =IF(AND(ISNUMBER(F7),ISNUMBER(G7)),(G7-F7)*24,0) -> 5 | I7: 0.25 | J7: 0.47916667 | K7: =IF(AND(ISNUMBER(I7),ISNUMBER(J7)),(J7-I7)*24,0) -> 5.5 | L7: R | M7: R | N7: =IF(AND(ISNUMBER(L7),ISNUMBER(M7)),(M7-L7)*24,0) -> 0 | O7: 0.22916667 | P7: 0.45833333 | Q7: =IF(AND(ISNUMBER(O7),ISNUMBER(P7)),(P7-O7)*24,0) -> 5.5 | R7: 0.25 | S7: 0.52083333 | T7: =IF(AND(ISNUMBER(R7),ISNUMBER(S7)),(S7-R7)*24,0) -> 6.5 | U7: 0.22916667 | V7: 0.4375 | W7: =IF(AND(ISNUMBER(U7),ISNUMBER(V7)),(V7-U7)*24,0) -> 5 | X7: R | Y7: R | Z7: =IF(AND(ISNUMBER(X7),ISNUMBER(Y7)),(Y7-X7)*24,0) -> 0 | AA7: =H7+K7+N7+Q7+T7+W7+Z7 -> 27.5 | AB7: =AA7-C7 -> 2.5 | AC7: =(H7>0)+(K7>0)+(N7>0)+(Q7>0)+(T7>0)+(W7>0)+(Z7>0) -> 5 | AD7: =IF(OR(IF(ISNUMBER(G7)*ISNUMBER(I7),(I7+1-G7)*24<Parametri!$B$65),IF(ISNUMBER(J7)*ISNUMBER(L7),(L7+1-J7)*24<Parametri!$B$65),IF(ISNUMBER(M7)*ISNUMBER(O7),(O7+1-M7)*24<Parametri!$B$65),IF(ISNUMBER(P7)*ISNUMBER(R7),(R7+1-P7)*24<Parametri!$B$65),IF(ISNUMBER(S7)*ISNUMBER(U7),(U7+1-S7)*24<Parametri!$B$65),IF(ISNUMBER(V7)*ISNUMBER(X7),(X7+1-V7)*24<Parametri!$B$65),IF(ISNUMBER(Y7)*ISNUMBER(F7),(F7+1-Y7)*24<Parametri!$B$65)),"KO","OK") -> OK
A8: {=IFERROR(INDEX(Personale!$A$5:$A$40,SMALL(IF(Personale!$H$5:$H$40="",ROW(Personale!$A$5:$A$40)-ROW(Personale!$A$5)+1),4)),"")} -> DUBON | B8: =IFERROR(VLOOKUP($A8,Personale!$A$5:$E$40,2,0),"") -> RESP | C8: =IFERROR(VLOOKUP($A8,Personale!$A$5:$E$40,3,0),0) -> 25 | D8: =IFERROR(VLOOKUP($A8,Personale!$A$5:$E$40,4,0),0) -> 5 | E8: =IFERROR(VLOOKUP($A8,Personale!$A$5:$E$40,5,0),0) -> 5 | F8: 0.47916667 | G8: 0.6875 | H8: =IF(AND(ISNUMBER(F8),ISNUMBER(G8)),(G8-F8)*24,0) -> 5 | I8: R | J8: R | K8: =IF(AND(ISNUMBER(I8),ISNUMBER(J8)),(J8-I8)*24,0) -> 0 | L8: R | M8: R | N8: =IF(AND(ISNUMBER(L8),ISNUMBER(M8)),(M8-L8)*24,0) -> 0 | O8: 0.41666667 | P8: 0.625 | Q8: =IF(AND(ISNUMBER(O8),ISNUMBER(P8)),(P8-O8)*24,0) -> 5 | R8: 0.25 | S8: 0.47916667 | T8: =IF(AND(ISNUMBER(R8),ISNUMBER(S8)),(S8-R8)*24,0) -> 5.5 | U8: 0.67708333 | V8: 0.88541667 | W8: =IF(AND(ISNUMBER(U8),ISNUMBER(V8)),(V8-U8)*24,0) -> 5 | X8: 0.59375 | Y8: 0.88541667 | Z8: =IF(AND(ISNUMBER(X8),ISNUMBER(Y8)),(Y8-X8)*24,0) -> 7 | AA8: =H8+K8+N8+Q8+T8+W8+Z8 -> 27.5 | AB8: =AA8-C8 -> 2.5 | AC8: =(H8>0)+(K8>0)+(N8>0)+(Q8>0)+(T8>0)+(W8>0)+(Z8>0) -> 5 | AD8: =IF(OR(IF(ISNUMBER(G8)*ISNUMBER(I8),(I8+1-G8)*24<Parametri!$B$65),IF(ISNUMBER(J8)*ISNUMBER(L8),(L8+1-J8)*24<Parametri!$B$65),IF(ISNUMBER(M8)*ISNUMBER(O8),(O8+1-M8)*24<Parametri!$B$65),IF(ISNUMBER(P8)*ISNUMBER(R8),(R8+1-P8)*24<Parametri!$B$65),IF(ISNUMBER(S8)*ISNUMBER(U8),(U8+1-S8)*24<Parametri!$B$65),IF(ISNUMBER(V8)*ISNUMBER(X8),(X8+1-V8)*24<Parametri!$B$65),IF(ISNUMBER(Y8)*ISNUMBER(F8),(F8+1-Y8)*24<Parametri!$B$65)),"KO","OK") -> OK
A9: {=IFERROR(INDEX(Personale!$A$5:$A$40,SMALL(IF(Personale!$H$5:$H$40="",ROW(Personale!$A$5:$A$40)-ROW(Personale!$A$5)+1),5)),"")} -> MUNERATI | B9: =IFERROR(VLOOKUP($A9,Personale!$A$5:$E$40,2,0),"") -> RESP | C9: =IFERROR(VLOOKUP($A9,Personale!$A$5:$E$40,3,0),0) -> 25 | D9: =IFERROR(VLOOKUP($A9,Personale!$A$5:$E$40,4,0),0) -> 5 | E9: =IFERROR(VLOOKUP($A9,Personale!$A$5:$E$40,5,0),0) -> 5 | F9: 0.22916667 | G9: 0.4375 | H9: =IF(AND(ISNUMBER(F9),ISNUMBER(G9)),(G9-F9)*24,0) -> 5 | I9: 0.47916667 | J9: 0.6875 | K9: =IF(AND(ISNUMBER(I9),ISNUMBER(J9)),(J9-I9)*24,0) -> 5 | L9: 0.25 | M9: 0.47916667 | N9: =IF(AND(ISNUMBER(L9),ISNUMBER(M9)),(M9-L9)*24,0) -> 5.5 | O9: 0.22916667 | P9: 0.5 | Q9: =IF(AND(ISNUMBER(O9),ISNUMBER(P9)),(P9-O9)*24,0) -> 6.5 | R9: R | S9: R | T9: =IF(AND(ISNUMBER(R9),ISNUMBER(S9)),(S9-R9)*24,0) -> 0 | U9: 0.22916667 | V9: 0.45833333 | W9: =IF(AND(ISNUMBER(U9),ISNUMBER(V9)),(V9-U9)*24,0) -> 5.5 | X9: R | Y9: R | Z9: =IF(AND(ISNUMBER(X9),ISNUMBER(Y9)),(Y9-X9)*24,0) -> 0 | AA9: =H9+K9+N9+Q9+T9+W9+Z9 -> 27.5 | AB9: =AA9-C9 -> 2.5 | AC9: =(H9>0)+(K9>0)+(N9>0)+(Q9>0)+(T9>0)+(W9>0)+(Z9>0) -> 5 | AD9: =IF(OR(IF(ISNUMBER(G9)*ISNUMBER(I9),(I9+1-G9)*24<Parametri!$B$65),IF(ISNUMBER(J9)*ISNUMBER(L9),(L9+1-J9)*24<Parametri!$B$65),IF(ISNUMBER(M9)*ISNUMBER(O9),(O9+1-M9)*24<Parametri!$B$65),IF(ISNUMBER(P9)*ISNUMBER(R9),(R9+1-P9)*24<Parametri!$B$65),IF(ISNUMBER(S9)*ISNUMBER(U9),(U9+1-S9)*24<Parametri!$B$65),IF(ISNUMBER(V9)*ISNUMBER(X9),(X9+1-V9)*24<Parametri!$B$65),IF(ISNUMBER(Y9)*ISNUMBER(F9),(F9+1-Y9)*24<Parametri!$B$65)),"KO","OK") -> OK
A10: {=IFERROR(INDEX(Personale!$A$5:$A$40,SMALL(IF(Personale!$H$5:$H$40="",ROW(Personale!$A$5:$A$40)-ROW(Personale!$A$5)+1),6)),"")} -> SEGAT | B10: =IFERROR(VLOOKUP($A10,Personale!$A$5:$E$40,2,0),"") -> RESP | C10: =IFERROR(VLOOKUP($A10,Personale!$A$5:$E$40,3,0),0) -> 25 | D10: =IFERROR(VLOOKUP($A10,Personale!$A$5:$E$40,4,0),0) -> 5 | E10: =IFERROR(VLOOKUP($A10,Personale!$A$5:$E$40,5,0),0) -> 5 | F10: 0.22916667 | G10: 0.47916667 | H10: =IF(AND(ISNUMBER(F10),ISNUMBER(G10)),(G10-F10)*24,0) -> 6 | I10: R | J10: R | K10: =IF(AND(ISNUMBER(I10),ISNUMBER(J10)),(J10-I10)*24,0) -> 0 | L10: R | M10: R | N10: =IF(AND(ISNUMBER(L10),ISNUMBER(M10)),(M10-L10)*24,0) -> 0 | O10: 0.22916667 | P10: 0.45833333 | Q10: =IF(AND(ISNUMBER(O10),ISNUMBER(P10)),(P10-O10)*24,0) -> 5.5 | R10: 0.47916667 | S10: 0.6875 | T10: =IF(AND(ISNUMBER(R10),ISNUMBER(S10)),(S10-R10)*24,0) -> 5 | U10: 0.5 | V10: 0.70833333 | W10: =IF(AND(ISNUMBER(U10),ISNUMBER(V10)),(V10-U10)*24,0) -> 5 | X10: 0.25 | Y10: 0.5 | Z10: =IF(AND(ISNUMBER(X10),ISNUMBER(Y10)),(Y10-X10)*24,0) -> 6 | AA10: =H10+K10+N10+Q10+T10+W10+Z10 -> 27.5 | AB10: =AA10-C10 -> 2.5 | AC10: =(H10>0)+(K10>0)+(N10>0)+(Q10>0)+(T10>0)+(W10>0)+(Z10>0) -> 5 | AD10: =IF(OR(IF(ISNUMBER(G10)*ISNUMBER(I10),(I10+1-G10)*24<Parametri!$B$65),IF(ISNUMBER(J10)*ISNUMBER(L10),(L10+1-J10)*24<Parametri!$B$65),IF(ISNUMBER(M10)*ISNUMBER(O10),(O10+1-M10)*24<Parametri!$B$65),IF(ISNUMBER(P10)*ISNUMBER(R10),(R10+1-P10)*24<Parametri!$B$65),IF(ISNUMBER(S10)*ISNUMBER(U10),(U10+1-S10)*24<Parametri!$B$65),IF(ISNUMBER(V10)*ISNUMBER(X10),(X10+1-V10)*24<Parametri!$B$65),IF(ISNUMBER(Y10)*ISNUMBER(F10),(F10+1-Y10)*24<Parametri!$B$65)),"KO","OK") -> OK
A11: {=IFERROR(INDEX(Personale!$A$5:$A$40,SMALL(IF(Personale!$H$5:$H$40="",ROW(Personale!$A$5:$A$40)-ROW(Personale!$A$5)+1),7)),"")} -> ANDREOLI | B11: =IFERROR(VLOOKUP($A11,Personale!$A$5:$E$40,2,0),"") -> ADDETTO | C11: =IFERROR(VLOOKUP($A11,Personale!$A$5:$E$40,3,0),0) -> 25 | D11: =IFERROR(VLOOKUP($A11,Personale!$A$5:$E$40,4,0),0) -> 5 | E11: =IFERROR(VLOOKUP($A11,Personale!$A$5:$E$40,5,0),0) -> 5 | F11: R | G11: R | H11: =IF(AND(ISNUMBER(F11),ISNUMBER(G11)),(G11-F11)*24,0) -> 0 | I11: R | J11: R | K11: =IF(AND(ISNUMBER(I11),ISNUMBER(J11)),(J11-I11)*24,0) -> 0 | L11: 0.61458333 | M11: 0.88541667 | N11: =IF(AND(ISNUMBER(L11),ISNUMBER(M11)),(M11-L11)*24,0) -> 6.5 | O11: 0.67708333 | P11: 0.88541667 | Q11: =IF(AND(ISNUMBER(O11),ISNUMBER(P11)),(P11-O11)*24,0) -> 5 | R11: 0.58333333 | S11: 0.83333333 | T11: =IF(AND(ISNUMBER(R11),ISNUMBER(S11)),(S11-R11)*24,0) -> 6 | U11: 0.625 | V11: 0.83333333 | W11: =IF(AND(ISNUMBER(U11),ISNUMBER(V11)),(V11-U11)*24,0) -> 5 | X11: 0.47916667 | Y11: 0.6875 | Z11: =IF(AND(ISNUMBER(X11),ISNUMBER(Y11)),(Y11-X11)*24,0) -> 5 | AA11: =H11+K11+N11+Q11+T11+W11+Z11 -> 27.5 | AB11: =AA11-C11 -> 2.5 | AC11: =(H11>0)+(K11>0)+(N11>0)+(Q11>0)+(T11>0)+(W11>0)+(Z11>0) -> 5 | AD11: =IF(OR(IF(ISNUMBER(G11)*ISNUMBER(I11),(I11+1-G11)*24<Parametri!$B$65),IF(ISNUMBER(J11)*ISNUMBER(L11),(L11+1-J11)*24<Parametri!$B$65),IF(ISNUMBER(M11)*ISNUMBER(O11),(O11+1-M11)*24<Parametri!$B$65),IF(ISNUMBER(P11)*ISNUMBER(R11),(R11+1-P11)*24<Parametri!$B$65),IF(ISNUMBER(S11)*ISNUMBER(U11),(U11+1-S11)*24<Parametri!$B$65),IF(ISNUMBER(V11)*ISNUMBER(X11),(X11+1-V11)*24<Parametri!$B$65),IF(ISNUMBER(Y11)*ISNUMBER(F11),(F11+1-Y11)*24<Parametri!$B$65)),"KO","OK") -> OK
A12: {=IFERROR(INDEX(Personale!$A$5:$A$40,SMALL(IF(Personale!$H$5:$H$40="",ROW(Personale!$A$5:$A$40)-ROW(Personale!$A$5)+1),8)),"")} -> BELLUCCO | B12: =IFERROR(VLOOKUP($A12,Personale!$A$5:$E$40,2,0),"") -> ADDETTO | C12: =IFERROR(VLOOKUP($A12,Personale!$A$5:$E$40,3,0),0) -> 20 | D12: =IFERROR(VLOOKUP($A12,Personale!$A$5:$E$40,4,0),0) -> 5 | E12: =IFERROR(VLOOKUP($A12,Personale!$A$5:$E$40,5,0),0) -> 4 | F12: 0.69791667 | G12: 0.88541667 | H12: =IF(AND(ISNUMBER(F12),ISNUMBER(G12)),(G12-F12)*24,0) -> 4.5 | I12: R | J12: R | K12: =IF(AND(ISNUMBER(I12),ISNUMBER(J12)),(J12-I12)*24,0) -> 0 | L12: 0.25 | M12: 0.45833333 | N12: =IF(AND(ISNUMBER(L12),ISNUMBER(M12)),(M12-L12)*24,0) -> 5 | O12: R | P12: R | Q12: =IF(AND(ISNUMBER(O12),ISNUMBER(P12)),(P12-O12)*24,0) -> 0 | R12: 0.25 | S12: 0.41666667 | T12: =IF(AND(ISNUMBER(R12),ISNUMBER(S12)),(S12-R12)*24,0) -> 4 | U12: 0.22916667 | V12: 0.39583333 | W12: =IF(AND(ISNUMBER(U12),ISNUMBER(V12)),(V12-U12)*24,0) -> 4 | X12: 0.625 | Y12: 0.83333333 | Z12: =IF(AND(ISNUMBER(X12),ISNUMBER(Y12)),(Y12-X12)*24,0) -> 5 | AA12: =H12+K12+N12+Q12+T12+W12+Z12 -> 22.5 | AB12: =AA12-C12 -> 2.5 | AC12: =(H12>0)+(K12>0)+(N12>0)+(Q12>0)+(T12>0)+(W12>0)+(Z12>0) -> 5 | AD12: =IF(OR(IF(ISNUMBER(G12)*ISNUMBER(I12),(I12+1-G12)*24<Parametri!$B$65),IF(ISNUMBER(J12)*ISNUMBER(L12),(L12+1-J12)*24<Parametri!$B$65),IF(ISNUMBER(M12)*ISNUMBER(O12),(O12+1-M12)*24<Parametri!$B$65),IF(ISNUMBER(P12)*ISNUMBER(R12),(R12+1-P12)*24<Parametri!$B$65),IF(ISNUMBER(S12)*ISNUMBER(U12),(U12+1-S12)*24<Parametri!$B$65),IF(ISNUMBER(V12)*ISNUMBER(X12),(X12+1-V12)*24<Parametri!$B$65),IF(ISNUMBER(Y12)*ISNUMBER(F12),(F12+1-Y12)*24<Parametri!$B$65)),"KO","OK") -> OK
A13: {=IFERROR(INDEX(Personale!$A$5:$A$40,SMALL(IF(Personale!$H$5:$H$40="",ROW(Personale!$A$5:$A$40)-ROW(Personale!$A$5)+1),9)),"")} -> BUORO | B13: =IFERROR(VLOOKUP($A13,Personale!$A$5:$E$40,2,0),"") -> ADDETTO | C13: =IFERROR(VLOOKUP($A13,Personale!$A$5:$E$40,3,0),0) -> 25 | D13: =IFERROR(VLOOKUP($A13,Personale!$A$5:$E$40,4,0),0) -> 5 | E13: =IFERROR(VLOOKUP($A13,Personale!$A$5:$E$40,5,0),0) -> 5 | F13: 0.45833333 | G13: 0.70833333 | H13: =IF(AND(ISNUMBER(F13),ISNUMBER(G13)),(G13-F13)*24,0) -> 6 | I13: 0.5625 | J13: 0.83333333 | K13: =IF(AND(ISNUMBER(I13),ISNUMBER(J13)),(J13-I13)*24,0) -> 6.5 | L13: R | M13: R | N13: =IF(AND(ISNUMBER(L13),ISNUMBER(M13)),(M13-L13)*24,0) -> 0 | O13: 0.22916667 | P13: 0.4375 | Q13: =IF(AND(ISNUMBER(O13),ISNUMBER(P13)),(P13-O13)*24,0) -> 5 | R13: 0.67708333 | S13: 0.88541667 | T13: =IF(AND(ISNUMBER(R13),ISNUMBER(S13)),(S13-R13)*24,0) -> 5 | U13: R | V13: R | W13: =IF(AND(ISNUMBER(U13),ISNUMBER(V13)),(V13-U13)*24,0) -> 0 | X13: 0.54166667 | Y13: 0.75 | Z13: =IF(AND(ISNUMBER(X13),ISNUMBER(Y13)),(Y13-X13)*24,0) -> 5 | AA13: =H13+K13+N13+Q13+T13+W13+Z13 -> 27.5 | AB13: =AA13-C13 -> 2.5 | AC13: =(H13>0)+(K13>0)+(N13>0)+(Q13>0)+(T13>0)+(W13>0)+(Z13>0) -> 5 | AD13: =IF(OR(IF(ISNUMBER(G13)*ISNUMBER(I13),(I13+1-G13)*24<Parametri!$B$65),IF(ISNUMBER(J13)*ISNUMBER(L13),(L13+1-J13)*24<Parametri!$B$65),IF(ISNUMBER(M13)*ISNUMBER(O13),(O13+1-M13)*24<Parametri!$B$65),IF(ISNUMBER(P13)*ISNUMBER(R13),(R13+1-P13)*24<Parametri!$B$65),IF(ISNUMBER(S13)*ISNUMBER(U13),(U13+1-S13)*24<Parametri!$B$65),IF(ISNUMBER(V13)*ISNUMBER(X13),(X13+1-V13)*24<Parametri!$B$65),IF(ISNUMBER(Y13)*ISNUMBER(F13),(F13+1-Y13)*24<Parametri!$B$65)),"KO","OK") -> OK
A14: {=IFERROR(INDEX(Personale!$A$5:$A$40,SMALL(IF(Personale!$H$5:$H$40="",ROW(Personale!$A$5:$A$40)-ROW(Personale!$A$5)+1),10)),"")} -> CANOVA | B14: =IFERROR(VLOOKUP($A14,Personale!$A$5:$E$40,2,0),"") -> ADDETTO | C14: =IFERROR(VLOOKUP($A14,Personale!$A$5:$E$40,3,0),0) -> 25 | D14: =IFERROR(VLOOKUP($A14,Personale!$A$5:$E$40,4,0),0) -> 5 | E14: =IFERROR(VLOOKUP($A14,Personale!$A$5:$E$40,5,0),0) -> 5 | F14: 0.67708333 | G14: 0.88541667 | H14: =IF(AND(ISNUMBER(F14),ISNUMBER(G14)),(G14-F14)*24,0) -> 5 | I14: R | J14: R | K14: =IF(AND(ISNUMBER(I14),ISNUMBER(J14)),(J14-I14)*24,0) -> 0 | L14: 0.47916667 | M14: 0.6875 | N14: =IF(AND(ISNUMBER(L14),ISNUMBER(M14)),(M14-L14)*24,0) -> 5 | O14: R | P14: R | Q14: =IF(AND(ISNUMBER(O14),ISNUMBER(P14)),(P14-O14)*24,0) -> 0 | R14: 0.41666667 | S14: 0.6875 | T14: =IF(AND(ISNUMBER(R14),ISNUMBER(S14)),(S14-R14)*24,0) -> 6.5 | U14: 0.22916667 | V14: 0.4375 | W14: =IF(AND(ISNUMBER(U14),ISNUMBER(V14)),(V14-U14)*24,0) -> 5 | X14: 0.35416667 | Y14: 0.60416667 | Z14: =IF(AND(ISNUMBER(X14),ISNUMBER(Y14)),(Y14-X14)*24,0) -> 6 | AA14: =H14+K14+N14+Q14+T14+W14+Z14 -> 27.5 | AB14: =AA14-C14 -> 2.5 | AC14: =(H14>0)+(K14>0)+(N14>0)+(Q14>0)+(T14>0)+(W14>0)+(Z14>0) -> 5 | AD14: =IF(OR(IF(ISNUMBER(G14)*ISNUMBER(I14),(I14+1-G14)*24<Parametri!$B$65),IF(ISNUMBER(J14)*ISNUMBER(L14),(L14+1-J14)*24<Parametri!$B$65),IF(ISNUMBER(M14)*ISNUMBER(O14),(O14+1-M14)*24<Parametri!$B$65),IF(ISNUMBER(P14)*ISNUMBER(R14),(R14+1-P14)*24<Parametri!$B$65),IF(ISNUMBER(S14)*ISNUMBER(U14),(U14+1-S14)*24<Parametri!$B$65),IF(ISNUMBER(V14)*ISNUMBER(X14),(X14+1-V14)*24<Parametri!$B$65),IF(ISNUMBER(Y14)*ISNUMBER(F14),(F14+1-Y14)*24<Parametri!$B$65)),"KO","OK") -> OK
A15: {=IFERROR(INDEX(Personale!$A$5:$A$40,SMALL(IF(Personale!$H$5:$H$40="",ROW(Personale!$A$5:$A$40)-ROW(Personale!$A$5)+1),11)),"")} -> CHIERZI | B15: =IFERROR(VLOOKUP($A15,Personale!$A$5:$E$40,2,0),"") -> ADDETTO | C15: =IFERROR(VLOOKUP($A15,Personale!$A$5:$E$40,3,0),0) -> 25 | D15: =IFERROR(VLOOKUP($A15,Personale!$A$5:$E$40,4,0),0) -> 5 | E15: =IFERROR(VLOOKUP($A15,Personale!$A$5:$E$40,5,0),0) -> 5 | F15: 0.22916667 | G15: 0.4375 | H15: =IF(AND(ISNUMBER(F15),ISNUMBER(G15)),(G15-F15)*24,0) -> 5 | I15: 0.25 | J15: 0.5 | K15: =IF(AND(ISNUMBER(I15),ISNUMBER(J15)),(J15-I15)*24,0) -> 6 | L15: 0.66666667 | M15: 0.875 | N15: =IF(AND(ISNUMBER(L15),ISNUMBER(M15)),(M15-L15)*24,0) -> 5 | O15: 0.5625 | P15: 0.8125 | Q15: =IF(AND(ISNUMBER(O15),ISNUMBER(P15)),(P15-O15)*24,0) -> 6 | R15: R | S15: R | T15: =IF(AND(ISNUMBER(R15),ISNUMBER(S15)),(S15-R15)*24,0) -> 0 | U15: 0.60416667 | V15: 0.83333333 | W15: =IF(AND(ISNUMBER(U15),ISNUMBER(V15)),(V15-U15)*24,0) -> 5.5 | X15: R | Y15: R | Z15: =IF(AND(ISNUMBER(X15),ISNUMBER(Y15)),(Y15-X15)*24,0) -> 0 | AA15: =H15+K15+N15+Q15+T15+W15+Z15 -> 27.5 | AB15: =AA15-C15 -> 2.5 | AC15: =(H15>0)+(K15>0)+(N15>0)+(Q15>0)+(T15>0)+(W15>0)+(Z15>0) -> 5 | AD15: =IF(OR(IF(ISNUMBER(G15)*ISNUMBER(I15),(I15+1-G15)*24<Parametri!$B$65),IF(ISNUMBER(J15)*ISNUMBER(L15),(L15+1-J15)*24<Parametri!$B$65),IF(ISNUMBER(M15)*ISNUMBER(O15),(O15+1-M15)*24<Parametri!$B$65),IF(ISNUMBER(P15)*ISNUMBER(R15),(R15+1-P15)*24<Parametri!$B$65),IF(ISNUMBER(S15)*ISNUMBER(U15),(U15+1-S15)*24<Parametri!$B$65),IF(ISNUMBER(V15)*ISNUMBER(X15),(X15+1-V15)*24<Parametri!$B$65),IF(ISNUMBER(Y15)*ISNUMBER(F15),(F15+1-Y15)*24<Parametri!$B$65)),"KO","OK") -> OK
A16: {=IFERROR(INDEX(Personale!$A$5:$A$40,SMALL(IF(Personale!$H$5:$H$40="",ROW(Personale!$A$5:$A$40)-ROW(Personale!$A$5)+1),12)),"")} -> BUGRYM | B16: =IFERROR(VLOOKUP($A16,Personale!$A$5:$E$40,2,0),"") -> ADDETTO | C16: =IFERROR(VLOOKUP($A16,Personale!$A$5:$E$40,3,0),0) -> 25 | D16: =IFERROR(VLOOKUP($A16,Personale!$A$5:$E$40,4,0),0) -> 5 | E16: =IFERROR(VLOOKUP($A16,Personale!$A$5:$E$40,5,0),0) -> 5 | F16: R | G16: R | H16: =IF(AND(ISNUMBER(F16),ISNUMBER(G16)),(G16-F16)*24,0) -> 0 | I16: 0.52083333 | J16: 0.75 | K16: =IF(AND(ISNUMBER(I16),ISNUMBER(J16)),(J16-I16)*24,0) -> 5.5 | L16: R | M16: R | N16: =IF(AND(ISNUMBER(L16),ISNUMBER(M16)),(M16-L16)*24,0) -> 0 | O16: 0.45833333 | P16: 0.6875 | Q16: =IF(AND(ISNUMBER(O16),ISNUMBER(P16)),(P16-O16)*24,0) -> 5.5 | R16: 0.5625 | S16: 0.77083333 | T16: =IF(AND(ISNUMBER(R16),ISNUMBER(S16)),(S16-R16)*24,0) -> 5 | U16: 0.67708333 | V16: 0.88541667 | W16: =IF(AND(ISNUMBER(U16),ISNUMBER(V16)),(V16-U16)*24,0) -> 5 | X16: 0.61458333 | Y16: 0.88541667 | Z16: =IF(AND(ISNUMBER(X16),ISNUMBER(Y16)),(Y16-X16)*24,0) -> 6.5 | AA16: =H16+K16+N16+Q16+T16+W16+Z16 -> 27.5 | AB16: =AA16-C16 -> 2.5 | AC16: =(H16>0)+(K16>0)+(N16>0)+(Q16>0)+(T16>0)+(W16>0)+(Z16>0) -> 5 | AD16: =IF(OR(IF(ISNUMBER(G16)*ISNUMBER(I16),(I16+1-G16)*24<Parametri!$B$65),IF(ISNUMBER(J16)*ISNUMBER(L16),(L16+1-J16)*24<Parametri!$B$65),IF(ISNUMBER(M16)*ISNUMBER(O16),(O16+1-M16)*24<Parametri!$B$65),IF(ISNUMBER(P16)*ISNUMBER(R16),(R16+1-P16)*24<Parametri!$B$65),IF(ISNUMBER(S16)*ISNUMBER(U16),(U16+1-S16)*24<Parametri!$B$65),IF(ISNUMBER(V16)*ISNUMBER(X16),(X16+1-V16)*24<Parametri!$B$65),IF(ISNUMBER(Y16)*ISNUMBER(F16),(F16+1-Y16)*24<Parametri!$B$65)),"KO","OK") -> OK
A17: {=IFERROR(INDEX(Personale!$A$5:$A$40,SMALL(IF(Personale!$H$5:$H$40="",ROW(Personale!$A$5:$A$40)-ROW(Personale!$A$5)+1),13)),"")} -> DAL ZOT | B17: =IFERROR(VLOOKUP($A17,Personale!$A$5:$E$40,2,0),"") -> ADDETTO | C17: =IFERROR(VLOOKUP($A17,Personale!$A$5:$E$40,3,0),0) -> 25 | D17: =IFERROR(VLOOKUP($A17,Personale!$A$5:$E$40,4,0),0) -> 5 | E17: =IFERROR(VLOOKUP($A17,Personale!$A$5:$E$40,5,0),0) -> 5 | F17: 0.41666667 | G17: 0.625 | H17: =IF(AND(ISNUMBER(F17),ISNUMBER(G17)),(G17-F17)*24,0) -> 5 | I17: 0.25 | J17: 0.45833333 | K17: =IF(AND(ISNUMBER(I17),ISNUMBER(J17)),(J17-I17)*24,0) -> 5 | L17: 0.25 | M17: 0.54166667 | N17: =IF(AND(ISNUMBER(L17),ISNUMBER(M17)),(M17-L17)*24,0) -> 7 | O17: R | P17: R | Q17: =IF(AND(ISNUMBER(O17),ISNUMBER(P17)),(P17-O17)*24,0) -> 0 | R17: 0.33333333 | S17: 0.5625 | T17: =IF(AND(ISNUMBER(R17),ISNUMBER(S17)),(S17-R17)*24,0) -> 5.5 | U17: R | V17: R | W17: =IF(AND(ISNUMBER(U17),ISNUMBER(V17)),(V17-U17)*24,0) -> 0 | X17: 0.67708333 | Y17: 0.88541667 | Z17: =IF(AND(ISNUMBER(X17),ISNUMBER(Y17)),(Y17-X17)*24,0) -> 5 | AA17: =H17+K17+N17+Q17+T17+W17+Z17 -> 27.5 | AB17: =AA17-C17 -> 2.5 | AC17: =(H17>0)+(K17>0)+(N17>0)+(Q17>0)+(T17>0)+(W17>0)+(Z17>0) -> 5 | AD17: =IF(OR(IF(ISNUMBER(G17)*ISNUMBER(I17),(I17+1-G17)*24<Parametri!$B$65),IF(ISNUMBER(J17)*ISNUMBER(L17),(L17+1-J17)*24<Parametri!$B$65),IF(ISNUMBER(M17)*ISNUMBER(O17),(O17+1-M17)*24<Parametri!$B$65),IF(ISNUMBER(P17)*ISNUMBER(R17),(R17+1-P17)*24<Parametri!$B$65),IF(ISNUMBER(S17)*ISNUMBER(U17),(U17+1-S17)*24<Parametri!$B$65),IF(ISNUMBER(V17)*ISNUMBER(X17),(X17+1-V17)*24<Parametri!$B$65),IF(ISNUMBER(Y17)*ISNUMBER(F17),(F17+1-Y17)*24<Parametri!$B$65)),"KO","OK") -> OK
A18: {=IFERROR(INDEX(Personale!$A$5:$A$40,SMALL(IF(Personale!$H$5:$H$40="",ROW(Personale!$A$5:$A$40)-ROW(Personale!$A$5)+1),14)),"")} -> DE NARDIN | B18: =IFERROR(VLOOKUP($A18,Personale!$A$5:$E$40,2,0),"") -> ADDETTO | C18: =IFERROR(VLOOKUP($A18,Personale!$A$5:$E$40,3,0),0) -> 25 | D18: =IFERROR(VLOOKUP($A18,Personale!$A$5:$E$40,4,0),0) -> 5 | E18: =IFERROR(VLOOKUP($A18,Personale!$A$5:$E$40,5,0),0) -> 5 | F18: 0.22916667 | G18: 0.47916667 | H18: =IF(AND(ISNUMBER(F18),ISNUMBER(G18)),(G18-F18)*24,0) -> 6 | I18: R | J18: R | K18: =IF(AND(ISNUMBER(I18),ISNUMBER(J18)),(J18-I18)*24,0) -> 0 | L18: 0.625 | M18: 0.83333333 | N18: =IF(AND(ISNUMBER(L18),ISNUMBER(M18)),(M18-L18)*24,0) -> 5 | O18: 0.33333333 | P18: 0.5625 | Q18: =IF(AND(ISNUMBER(O18),ISNUMBER(P18)),(P18-O18)*24,0) -> 5.5 | R18: R | S18: R | T18: =IF(AND(ISNUMBER(R18),ISNUMBER(S18)),(S18-R18)*24,0) -> 0 | U18: 0.45833333 | V18: 0.6875 | W18: =IF(AND(ISNUMBER(U18),ISNUMBER(V18)),(V18-U18)*24,0) -> 5.5 | X18: 0.25 | Y18: 0.47916667 | Z18: =IF(AND(ISNUMBER(X18),ISNUMBER(Y18)),(Y18-X18)*24,0) -> 5.5 | AA18: =H18+K18+N18+Q18+T18+W18+Z18 -> 27.5 | AB18: =AA18-C18 -> 2.5 | AC18: =(H18>0)+(K18>0)+(N18>0)+(Q18>0)+(T18>0)+(W18>0)+(Z18>0) -> 5 | AD18: =IF(OR(IF(ISNUMBER(G18)*ISNUMBER(I18),(I18+1-G18)*24<Parametri!$B$65),IF(ISNUMBER(J18)*ISNUMBER(L18),(L18+1-J18)*24<Parametri!$B$65),IF(ISNUMBER(M18)*ISNUMBER(O18),(O18+1-M18)*24<Parametri!$B$65),IF(ISNUMBER(P18)*ISNUMBER(R18),(R18+1-P18)*24<Parametri!$B$65),IF(ISNUMBER(S18)*ISNUMBER(U18),(U18+1-S18)*24<Parametri!$B$65),IF(ISNUMBER(V18)*ISNUMBER(X18),(X18+1-V18)*24<Parametri!$B$65),IF(ISNUMBER(Y18)*ISNUMBER(F18),(F18+1-Y18)*24<Parametri!$B$65)),"KO","OK") -> OK
A19: {=IFERROR(INDEX(Personale!$A$5:$A$40,SMALL(IF(Personale!$H$5:$H$40="",ROW(Personale!$A$5:$A$40)-ROW(Personale!$A$5)+1),15)),"")} -> DE VIDO | B19: =IFERROR(VLOOKUP($A19,Personale!$A$5:$E$40,2,0),"") -> ADDETTO | C19: =IFERROR(VLOOKUP($A19,Personale!$A$5:$E$40,3,0),0) -> 30 | D19: =IFERROR(VLOOKUP($A19,Personale!$A$5:$E$40,4,0),0) -> 5 | E19: =IFERROR(VLOOKUP($A19,Personale!$A$5:$E$40,5,0),0) -> 6 | F19: 0.58333333 | G19: 0.83333333 | H19: =IF(AND(ISNUMBER(F19),ISNUMBER(G19)),(G19-F19)*24,0) -> 6 | I19: 0.61458333 | J19: 0.88541667 | K19: =IF(AND(ISNUMBER(I19),ISNUMBER(J19)),(J19-I19)*24,0) -> 6.5 | L19: 0.35416667 | M19: 0.625 | N19: =IF(AND(ISNUMBER(L19),ISNUMBER(M19)),(M19-L19)*24,0) -> 6.5 | O19: R | P19: R | Q19: =IF(AND(ISNUMBER(O19),ISNUMBER(P19)),(P19-O19)*24,0) -> 0 | R19: 0.25 | S19: 0.52083333 | T19: =IF(AND(ISNUMBER(R19),ISNUMBER(S19)),(S19-R19)*24,0) -> 6.5 | U19: R | V19: R | W19: =IF(AND(ISNUMBER(U19),ISNUMBER(V19)),(V19-U19)*24,0) -> 0 | X19: 0.25 | Y19: 0.54166667 | Z19: =IF(AND(ISNUMBER(X19),ISNUMBER(Y19)),(Y19-X19)*24,0) -> 7 | AA19: =H19+K19+N19+Q19+T19+W19+Z19 -> 32.5 | AB19: =AA19-C19 -> 2.5 | AC19: =(H19>0)+(K19>0)+(N19>0)+(Q19>0)+(T19>0)+(W19>0)+(Z19>0) -> 5 | AD19: =IF(OR(IF(ISNUMBER(G19)*ISNUMBER(I19),(I19+1-G19)*24<Parametri!$B$65),IF(ISNUMBER(J19)*ISNUMBER(L19),(L19+1-J19)*24<Parametri!$B$65),IF(ISNUMBER(M19)*ISNUMBER(O19),(O19+1-M19)*24<Parametri!$B$65),IF(ISNUMBER(P19)*ISNUMBER(R19),(R19+1-P19)*24<Parametri!$B$65),IF(ISNUMBER(S19)*ISNUMBER(U19),(U19+1-S19)*24<Parametri!$B$65),IF(ISNUMBER(V19)*ISNUMBER(X19),(X19+1-V19)*24<Parametri!$B$65),IF(ISNUMBER(Y19)*ISNUMBER(F19),(F19+1-Y19)*24<Parametri!$B$65)),"KO","OK") -> OK
A20: {=IFERROR(INDEX(Personale!$A$5:$A$40,SMALL(IF(Personale!$H$5:$H$40="",ROW(Personale!$A$5:$A$40)-ROW(Personale!$A$5)+1),16)),"")} -> GALLINA | B20: =IFERROR(VLOOKUP($A20,Personale!$A$5:$E$40,2,0),"") -> ADDETTO | C20: =IFERROR(VLOOKUP($A20,Personale!$A$5:$E$40,3,0),0) -> 25 | D20: =IFERROR(VLOOKUP($A20,Personale!$A$5:$E$40,4,0),0) -> 5 | E20: =IFERROR(VLOOKUP($A20,Personale!$A$5:$E$40,5,0),0) -> 5 | F20: R | G20: R | H20: =IF(AND(ISNUMBER(F20),ISNUMBER(G20)),(G20-F20)*24,0) -> 0 | I20: 0.25 | J20: 0.52083333 | K20: =IF(AND(ISNUMBER(I20),ISNUMBER(J20)),(J20-I20)*24,0) -> 6.5 | L20: 0.54166667 | M20: 0.75 | N20: =IF(AND(ISNUMBER(L20),ISNUMBER(M20)),(M20-L20)*24,0) -> 5 | O20: 0.54166667 | P20: 0.79166667 | Q20: =IF(AND(ISNUMBER(O20),ISNUMBER(P20)),(P20-O20)*24,0) -> 6 | R20: 0.67708333 | S20: 0.88541667 | T20: =IF(AND(ISNUMBER(R20),ISNUMBER(S20)),(S20-R20)*24,0) -> 5 | U20: 0.66666667 | V20: 0.875 | W20: =IF(AND(ISNUMBER(U20),ISNUMBER(V20)),(V20-U20)*24,0) -> 5 | X20: R | Y20: R | Z20: =IF(AND(ISNUMBER(X20),ISNUMBER(Y20)),(Y20-X20)*24,0) -> 0 | AA20: =H20+K20+N20+Q20+T20+W20+Z20 -> 27.5 | AB20: =AA20-C20 -> 2.5 | AC20: =(H20>0)+(K20>0)+(N20>0)+(Q20>0)+(T20>0)+(W20>0)+(Z20>0) -> 5 | AD20: =IF(OR(IF(ISNUMBER(G20)*ISNUMBER(I20),(I20+1-G20)*24<Parametri!$B$65),IF(ISNUMBER(J20)*ISNUMBER(L20),(L20+1-J20)*24<Parametri!$B$65),IF(ISNUMBER(M20)*ISNUMBER(O20),(O20+1-M20)*24<Parametri!$B$65),IF(ISNUMBER(P20)*ISNUMBER(R20),(R20+1-P20)*24<Parametri!$B$65),IF(ISNUMBER(S20)*ISNUMBER(U20),(U20+1-S20)*24<Parametri!$B$65),IF(ISNUMBER(V20)*ISNUMBER(X20),(X20+1-V20)*24<Parametri!$B$65),IF(ISNUMBER(Y20)*ISNUMBER(F20),(F20+1-Y20)*24<Parametri!$B$65)),"KO","OK") -> OK
A21: {=IFERROR(INDEX(Personale!$A$5:$A$40,SMALL(IF(Personale!$H$5:$H$40="",ROW(Personale!$A$5:$A$40)-ROW(Personale!$A$5)+1),17)),"")} -> MARZANO | B21: =IFERROR(VLOOKUP($A21,Personale!$A$5:$E$40,2,0),"") -> ADDETTO | C21: =IFERROR(VLOOKUP($A21,Personale!$A$5:$E$40,3,0),0) -> 30 | D21: =IFERROR(VLOOKUP($A21,Personale!$A$5:$E$40,4,0),0) -> 5 | E21: =IFERROR(VLOOKUP($A21,Personale!$A$5:$E$40,5,0),0) -> 6 | F21: 0.33333333 | G21: 0.58333333 | H21: =IF(AND(ISNUMBER(F21),ISNUMBER(G21)),(G21-F21)*24,0) -> 6 | I21: 0.375 | J21: 0.625 | K21: =IF(AND(ISNUMBER(I21),ISNUMBER(J21)),(J21-I21)*24,0) -> 6 | L21: 0.25 | M21: 0.5 | N21: =IF(AND(ISNUMBER(L21),ISNUMBER(M21)),(M21-L21)*24,0) -> 6 | O21: 0.22916667 | P21: 0.54166667 | Q21: =IF(AND(ISNUMBER(O21),ISNUMBER(P21)),(P21-O21)*24,0) -> 7.5 | R21: R | S21: R | T21: =IF(AND(ISNUMBER(R21),ISNUMBER(S21)),(S21-R21)*24,0) -> 0 | U21: 0.375 | V21: 0.64583333 | W21: =IF(AND(ISNUMBER(U21),ISNUMBER(V21)),(V21-U21)*24,0) -> 6.5 | X21: R | Y21: R | Z21: =IF(AND(ISNUMBER(X21),ISNUMBER(Y21)),(Y21-X21)*24,0) -> 0 | AA21: =H21+K21+N21+Q21+T21+W21+Z21 -> 32 | AB21: =AA21-C21 -> 2 | AC21: =(H21>0)+(K21>0)+(N21>0)+(Q21>0)+(T21>0)+(W21>0)+(Z21>0) -> 5 | AD21: =IF(OR(IF(ISNUMBER(G21)*ISNUMBER(I21),(I21+1-G21)*24<Parametri!$B$65),IF(ISNUMBER(J21)*ISNUMBER(L21),(L21+1-J21)*24<Parametri!$B$65),IF(ISNUMBER(M21)*ISNUMBER(O21),(O21+1-M21)*24<Parametri!$B$65),IF(ISNUMBER(P21)*ISNUMBER(R21),(R21+1-P21)*24<Parametri!$B$65),IF(ISNUMBER(S21)*ISNUMBER(U21),(U21+1-S21)*24<Parametri!$B$65),IF(ISNUMBER(V21)*ISNUMBER(X21),(X21+1-V21)*24<Parametri!$B$65),IF(ISNUMBER(Y21)*ISNUMBER(F21),(F21+1-Y21)*24<Parametri!$B$65)),"KO","OK") -> OK
A22: {=IFERROR(INDEX(Personale!$A$5:$A$40,SMALL(IF(Personale!$H$5:$H$40="",ROW(Personale!$A$5:$A$40)-ROW(Personale!$A$5)+1),18)),"")} -> RIGONI | B22: =IFERROR(VLOOKUP($A22,Personale!$A$5:$E$40,2,0),"") -> ADDETTO | C22: =IFERROR(VLOOKUP($A22,Personale!$A$5:$E$40,3,0),0) -> 25 | D22: =IFERROR(VLOOKUP($A22,Personale!$A$5:$E$40,4,0),0) -> 5 | E22: =IFERROR(VLOOKUP($A22,Personale!$A$5:$E$40,5,0),0) -> 5 | F22: 0.54166667 | G22: 0.79166667 | H22: =IF(AND(ISNUMBER(F22),ISNUMBER(G22)),(G22-F22)*24,0) -> 6 | I22: 0.33333333 | J22: 0.5625 | K22: =IF(AND(ISNUMBER(I22),ISNUMBER(J22)),(J22-I22)*24,0) -> 5.5 | L22: R | M22: R | N22: =IF(AND(ISNUMBER(L22),ISNUMBER(M22)),(M22-L22)*24,0) -> 0 | O22: 0.625 | P22: 0.83333333 | Q22: =IF(AND(ISNUMBER(O22),ISNUMBER(P22)),(P22-O22)*24,0) -> 5 | R22: 0.33333333 | S22: 0.58333333 | T22: =IF(AND(ISNUMBER(R22),ISNUMBER(S22)),(S22-R22)*24,0) -> 6 | U22: R | V22: R | W22: =IF(AND(ISNUMBER(U22),ISNUMBER(V22)),(V22-U22)*24,0) -> 0 | X22: 0.25 | Y22: 0.45833333 | Z22: =IF(AND(ISNUMBER(X22),ISNUMBER(Y22)),(Y22-X22)*24,0) -> 5 | AA22: =H22+K22+N22+Q22+T22+W22+Z22 -> 27.5 | AB22: =AA22-C22 -> 2.5 | AC22: =(H22>0)+(K22>0)+(N22>0)+(Q22>0)+(T22>0)+(W22>0)+(Z22>0) -> 5 | AD22: =IF(OR(IF(ISNUMBER(G22)*ISNUMBER(I22),(I22+1-G22)*24<Parametri!$B$65),IF(ISNUMBER(J22)*ISNUMBER(L22),(L22+1-J22)*24<Parametri!$B$65),IF(ISNUMBER(M22)*ISNUMBER(O22),(O22+1-M22)*24<Parametri!$B$65),IF(ISNUMBER(P22)*ISNUMBER(R22),(R22+1-P22)*24<Parametri!$B$65),IF(ISNUMBER(S22)*ISNUMBER(U22),(U22+1-S22)*24<Parametri!$B$65),IF(ISNUMBER(V22)*ISNUMBER(X22),(X22+1-V22)*24<Parametri!$B$65),IF(ISNUMBER(Y22)*ISNUMBER(F22),(F22+1-Y22)*24<Parametri!$B$65)),"KO","OK") -> OK
A23: {=IFERROR(INDEX(Personale!$A$5:$A$40,SMALL(IF(Personale!$H$5:$H$40="",ROW(Personale!$A$5:$A$40)-ROW(Personale!$A$5)+1),19)),"")} -> SCHENA | B23: =IFERROR(VLOOKUP($A23,Personale!$A$5:$E$40,2,0),"") -> ADDETTO | C23: =IFERROR(VLOOKUP($A23,Personale!$A$5:$E$40,3,0),0) -> 20 | D23: =IFERROR(VLOOKUP($A23,Personale!$A$5:$E$40,4,0),0) -> 5 | E23: =IFERROR(VLOOKUP($A23,Personale!$A$5:$E$40,5,0),0) -> 4 | F23: 0.33333333 | G23: 0.54166667 | H23: =IF(AND(ISNUMBER(F23),ISNUMBER(G23)),(G23-F23)*24,0) -> 5 | I23: 0.66666667 | J23: 0.875 | K23: =IF(AND(ISNUMBER(I23),ISNUMBER(J23)),(J23-I23)*24,0) -> 5 | L23: 0.33333333 | M23: 0.52083333 | N23: =IF(AND(ISNUMBER(L23),ISNUMBER(M23)),(M23-L23)*24,0) -> 4.5 | O23: 0.45833333 | P23: 0.625 | Q23: =IF(AND(ISNUMBER(O23),ISNUMBER(P23)),(P23-O23)*24,0) -> 4 | R23: R | S23: R | T23: =IF(AND(ISNUMBER(R23),ISNUMBER(S23)),(S23-R23)*24,0) -> 0 | U23: 0.33333333 | V23: 0.5 | W23: =IF(AND(ISNUMBER(U23),ISNUMBER(V23)),(V23-U23)*24,0) -> 4 | X23: R | Y23: R | Z23: =IF(AND(ISNUMBER(X23),ISNUMBER(Y23)),(Y23-X23)*24,0) -> 0 | AA23: =H23+K23+N23+Q23+T23+W23+Z23 -> 22.5 | AB23: =AA23-C23 -> 2.5 | AC23: =(H23>0)+(K23>0)+(N23>0)+(Q23>0)+(T23>0)+(W23>0)+(Z23>0) -> 5 | AD23: =IF(OR(IF(ISNUMBER(G23)*ISNUMBER(I23),(I23+1-G23)*24<Parametri!$B$65),IF(ISNUMBER(J23)*ISNUMBER(L23),(L23+1-J23)*24<Parametri!$B$65),IF(ISNUMBER(M23)*ISNUMBER(O23),(O23+1-M23)*24<Parametri!$B$65),IF(ISNUMBER(P23)*ISNUMBER(R23),(R23+1-P23)*24<Parametri!$B$65),IF(ISNUMBER(S23)*ISNUMBER(U23),(U23+1-S23)*24<Parametri!$B$65),IF(ISNUMBER(V23)*ISNUMBER(X23),(X23+1-V23)*24<Parametri!$B$65),IF(ISNUMBER(Y23)*ISNUMBER(F23),(F23+1-Y23)*24<Parametri!$B$65)),"KO","OK") -> OK
A24: {=IFERROR(INDEX(Personale!$A$5:$A$40,SMALL(IF(Personale!$H$5:$H$40="",ROW(Personale!$A$5:$A$40)-ROW(Personale!$A$5)+1),20)),"")} -> TAMBURLIN | B24: =IFERROR(VLOOKUP($A24,Personale!$A$5:$E$40,2,0),"") -> ADDETTO | C24: =IFERROR(VLOOKUP($A24,Personale!$A$5:$E$40,3,0),0) -> 8 | D24: =IFERROR(VLOOKUP($A24,Personale!$A$5:$E$40,4,0),0) -> 1 | E24: =IFERROR(VLOOKUP($A24,Personale!$A$5:$E$40,5,0),0) -> 8 | F24: R | G24: R | H24: =IF(AND(ISNUMBER(F24),ISNUMBER(G24)),(G24-F24)*24,0) -> 0 | I24: R | J24: R | K24: =IF(AND(ISNUMBER(I24),ISNUMBER(J24)),(J24-I24)*24,0) -> 0 | L24: R | M24: R | N24: =IF(AND(ISNUMBER(L24),ISNUMBER(M24)),(M24-L24)*24,0) -> 0 | O24: R | P24: R | Q24: =IF(AND(ISNUMBER(O24),ISNUMBER(P24)),(P24-O24)*24,0) -> 0 | R24: R | S24: R | T24: =IF(AND(ISNUMBER(R24),ISNUMBER(S24)),(S24-R24)*24,0) -> 0 | U24: 0.39583333 | V24: 0.77083333 | W24: =IF(AND(ISNUMBER(U24),ISNUMBER(V24)),(V24-U24)*24,0) -> 9 | X24: R | Y24: R | Z24: =IF(AND(ISNUMBER(X24),ISNUMBER(Y24)),(Y24-X24)*24,0) -> 0 | AA24: =H24+K24+N24+Q24+T24+W24+Z24 -> 9 | AB24: =AA24-C24 -> 1 | AC24: =(H24>0)+(K24>0)+(N24>0)+(Q24>0)+(T24>0)+(W24>0)+(Z24>0) -> 1 | AD24: =IF(OR(IF(ISNUMBER(G24)*ISNUMBER(I24),(I24+1-G24)*24<Parametri!$B$65),IF(ISNUMBER(J24)*ISNUMBER(L24),(L24+1-J24)*24<Parametri!$B$65),IF(ISNUMBER(M24)*ISNUMBER(O24),(O24+1-M24)*24<Parametri!$B$65),IF(ISNUMBER(P24)*ISNUMBER(R24),(R24+1-P24)*24<Parametri!$B$65),IF(ISNUMBER(S24)*ISNUMBER(U24),(U24+1-S24)*24<Parametri!$B$65),IF(ISNUMBER(V24)*ISNUMBER(X24),(X24+1-V24)*24<Parametri!$B$65),IF(ISNUMBER(Y24)*ISNUMBER(F24),(F24+1-Y24)*24<Parametri!$B$65)),"KO","OK") -> OK
A25: {=IFERROR(INDEX(Personale!$A$5:$A$40,SMALL(IF(Personale!$H$5:$H$40="",ROW(Personale!$A$5:$A$40)-ROW(Personale!$A$5)+1),21)),"")} -> FRANCESCON | B25: =IFERROR(VLOOKUP($A25,Personale!$A$5:$E$40,2,0),"") -> ADDETTO | C25: =IFERROR(VLOOKUP($A25,Personale!$A$5:$E$40,3,0),0) -> 8 | D25: =IFERROR(VLOOKUP($A25,Personale!$A$5:$E$40,4,0),0) -> 1 | E25: =IFERROR(VLOOKUP($A25,Personale!$A$5:$E$40,5,0),0) -> 8 | F25: R | G25: R | H25: =IF(AND(ISNUMBER(F25),ISNUMBER(G25)),(G25-F25)*24,0) -> 0 | I25: R | J25: R | K25: =IF(AND(ISNUMBER(I25),ISNUMBER(J25)),(J25-I25)*24,0) -> 0 | L25: R | M25: R | N25: =IF(AND(ISNUMBER(L25),ISNUMBER(M25)),(M25-L25)*24,0) -> 0 | O25: R | P25: R | Q25: =IF(AND(ISNUMBER(O25),ISNUMBER(P25)),(P25-O25)*24,0) -> 0 | R25: R | S25: R | T25: =IF(AND(ISNUMBER(R25),ISNUMBER(S25)),(S25-R25)*24,0) -> 0 | U25: 0.22916667 | V25: 0.60416667 | W25: =IF(AND(ISNUMBER(U25),ISNUMBER(V25)),(V25-U25)*24,0) -> 9 | X25: R | Y25: R | Z25: =IF(AND(ISNUMBER(X25),ISNUMBER(Y25)),(Y25-X25)*24,0) -> 0 | AA25: =H25+K25+N25+Q25+T25+W25+Z25 -> 9 | AB25: =AA25-C25 -> 1 | AC25: =(H25>0)+(K25>0)+(N25>0)+(Q25>0)+(T25>0)+(W25>0)+(Z25>0) -> 1 | AD25: =IF(OR(IF(ISNUMBER(G25)*ISNUMBER(I25),(I25+1-G25)*24<Parametri!$B$65),IF(ISNUMBER(J25)*ISNUMBER(L25),(L25+1-J25)*24<Parametri!$B$65),IF(ISNUMBER(M25)*ISNUMBER(O25),(O25+1-M25)*24<Parametri!$B$65),IF(ISNUMBER(P25)*ISNUMBER(R25),(R25+1-P25)*24<Parametri!$B$65),IF(ISNUMBER(S25)*ISNUMBER(U25),(U25+1-S25)*24<Parametri!$B$65),IF(ISNUMBER(V25)*ISNUMBER(X25),(X25+1-V25)*24<Parametri!$B$65),IF(ISNUMBER(Y25)*ISNUMBER(F25),(F25+1-Y25)*24<Parametri!$B$65)),"KO","OK") -> OK
A26: =IFERROR(INDEX(Personale!$A$5:$A$40,SMALL(IF(Personale!$H$5:$H$40="",ROW(Personale!$A$5:$A$40)-ROW(Personale!$A$5)+1),22)),"") -> 0 | B26: =IFERROR(VLOOKUP($A26,Personale!$A$5:$E$40,2,0),"") | C26: =IFERROR(VLOOKUP($A26,Personale!$A$5:$E$40,3,0),0) -> 0 | D26: =IFERROR(VLOOKUP($A26,Personale!$A$5:$E$40,4,0),0) -> 0 | E26: =IFERROR(VLOOKUP($A26,Personale!$A$5:$E$40,5,0),0) -> 0 | F26: R | G26: R | H26: =IF(AND(ISNUMBER(F26),ISNUMBER(G26)),(G26-F26)*24,0) -> 0 | I26: R | J26: R | K26: =IF(AND(ISNUMBER(I26),ISNUMBER(J26)),(J26-I26)*24,0) -> 0 | L26: R | M26: R | N26: =IF(AND(ISNUMBER(L26),ISNUMBER(M26)),(M26-L26)*24,0) -> 0 | O26: R | P26: R | Q26: =IF(AND(ISNUMBER(O26),ISNUMBER(P26)),(P26-O26)*24,0) -> 0 | R26: R | S26: R | T26: =IF(AND(ISNUMBER(R26),ISNUMBER(S26)),(S26-R26)*24,0) -> 0 | U26: R | V26: R | W26: =IF(AND(ISNUMBER(U26),ISNUMBER(V26)),(V26-U26)*24,0) -> 0 | X26: R | Y26: R | Z26: =IF(AND(ISNUMBER(X26),ISNUMBER(Y26)),(Y26-X26)*24,0) -> 0 | AA26: =H26+K26+N26+Q26+T26+W26+Z26 -> 0 | AB26: =AA26-C26 -> 0 | AC26: =(H26>0)+(K26>0)+(N26>0)+(Q26>0)+(T26>0)+(W26>0)+(Z26>0) -> 0 | AD26: =IF(OR(IF(ISNUMBER(G26)*ISNUMBER(I26),(I26+1-G26)*24<Parametri!$B$65),IF(ISNUMBER(J26)*ISNUMBER(L26),(L26+1-J26)*24<Parametri!$B$65),IF(ISNUMBER(M26)*ISNUMBER(O26),(O26+1-M26)*24<Parametri!$B$65),IF(ISNUMBER(P26)*ISNUMBER(R26),(R26+1-P26)*24<Parametri!$B$65),IF(ISNUMBER(S26)*ISNUMBER(U26),(U26+1-S26)*24<Parametri!$B$65),IF(ISNUMBER(V26)*ISNUMBER(X26),(X26+1-V26)*24<Parametri!$B$65),IF(ISNUMBER(Y26)*ISNUMBER(F26),(F26+1-Y26)*24<Parametri!$B$65)),"KO","OK") -> OK
A27: =Personale!A41 -> Totale | B27: =Personale!B41 -> 26 teste | C27: =Personale!C41 -> 504 | D27: =Personale!D41 -> 0 | E27: =Personale!E41 -> 0
A29: RIEPILOGO GIORNALIERO E CONTROLLI
A30: Voce | B30: Lun | C30: Mar | D30: Mer | E30: Gio | F30: Ven | G30: Sab | H30: Dom | I30: Tot
A31: Ore pianificate | B31: =SUM(H5:H27) -> 86 | C31: =SUM(K5:K27) -> 69 | D31: =SUM(N5:N27) -> 71.5 | E31: =SUM(Q5:Q27) -> 82.5 | F31: =SUM(T5:T27) -> 79 | G31: =SUM(W5:W27) -> 94 | H31: =SUM(Z5:Z27) -> 70.5 | I31: =SUM(B31:H31) -> 552.5
A32: Presenti (teste) | B32: =SUMPRODUCT(--(H5:H27>0)) -> 16 | C32: =SUMPRODUCT(--(K5:K27>0)) -> 12 | D32: =SUMPRODUCT(--(N5:N27>0)) -> 13 | E32: =SUMPRODUCT(--(Q5:Q27>0)) -> 15 | F32: =SUMPRODUCT(--(T5:T27>0)) -> 14 | G32: =SUMPRODUCT(--(W5:W27>0)) -> 17 | H32: =SUMPRODUCT(--(Z5:Z27>0)) -> 12 | I32: =SUM(B32:H32) -> 99
A33: Ingressi all'apertura | B33: =COUNTIF(F5:F27,Parametri!B$63) -> 5 | C33: =COUNTIF(I5:I27,Parametri!C$63) -> 4 | D33: =COUNTIF(L5:L27,Parametri!D$63) -> 4 | E33: =COUNTIF(O5:O27,Parametri!E$63) -> 5 | F33: =COUNTIF(R5:R27,Parametri!F$63) -> 4 | G33: =COUNTIF(U5:U27,Parametri!G$63) -> 5 | H33: =COUNTIF(X5:X27,Parametri!H$63) -> 4
A34: Uscite alla chiusura | B34: =COUNTIF(G5:G27,Parametri!B$64) -> 3 | C34: =COUNTIF(J5:J27,Parametri!C$64) -> 2 | D34: =COUNTIF(M5:M27,Parametri!D$64) -> 2 | E34: =COUNTIF(P5:P27,Parametri!E$64) -> 3 | F34: =COUNTIF(S5:S27,Parametri!F$64) -> 3 | G34: =COUNTIF(V5:V27,Parametri!G$64) -> 3 | H34: =COUNTIF(Y5:Y27,Parametri!H$64) -> 3
A35: Riposi | B35: =COUNTIF(F5:F27,"R") -> 6 | C35: =COUNTIF(I5:I27,"R") -> 10 | D35: =COUNTIF(L5:L27,"R") -> 9 | E35: =COUNTIF(O5:O27,"R") -> 7 | F35: =COUNTIF(R5:R27,"R") -> 8 | G35: =COUNTIF(U5:U27,"R") -> 5 | H35: =COUNTIF(X5:X27,"R") -> 10 | I35: =SUM(B35:H35) -> 55
A36: Esito apertura / chiusura | B36: =IF(AND(B33>=Parametri!$B$67,B34>=Parametri!$B$68),"OK","KO") -> OK | C36: =IF(AND(C33>=Parametri!$B$67,C34>=Parametri!$B$68),"OK","KO") -> OK | D36: =IF(AND(D33>=Parametri!$B$67,D34>=Parametri!$B$68),"OK","KO") -> OK | E36: =IF(AND(E33>=Parametri!$B$67,E34>=Parametri!$B$68),"OK","KO") -> OK | F36: =IF(AND(F33>=Parametri!$B$67,F34>=Parametri!$B$68),"OK","KO") -> OK | G36: =IF(AND(G33>=Parametri!$B$67,G34>=Parametri!$B$68),"OK","KO") -> OK | H36: =IF(AND(H33>=Parametri!$B$67,H34>=Parametri!$B$68),"OK","KO") -> OK
A37: Ingressi non in coppia (info) | B37: =SUMPRODUCT((COUNTIF(F$5:F$27,F5:F27)=1)*ISNUMBER(F5:F27)) -> 5 | C37: =SUMPRODUCT((COUNTIF(I$5:I$27,I5:I27)=1)*ISNUMBER(I5:I27)) -> 8 | D37: =SUMPRODUCT((COUNTIF(L$5:L$27,L5:L27)=1)*ISNUMBER(L5:L27)) -> 9 | E37: =SUMPRODUCT((COUNTIF(O$5:O$27,O5:O27)=1)*ISNUMBER(O5:O27)) -> 8 | F37: =SUMPRODUCT((COUNTIF(R$5:R$27,R5:R27)=1)*ISNUMBER(R5:R27)) -> 5 | G37: =SUMPRODUCT((COUNTIF(U$5:U$27,U5:U27)=1)*ISNUMBER(U5:U27)) -> 8 | H37: =SUMPRODUCT((COUNTIF(X$5:X$27,X5:X27)=1)*ISNUMBER(X5:X27)) -> 8
A38: Uscite non in coppia (info) | B38: =SUMPRODUCT((COUNTIF(G$5:G$27,G5:G27)=1)*ISNUMBER(G5:G27)) -> 6 | C38: =SUMPRODUCT((COUNTIF(J$5:J$27,J5:J27)=1)*ISNUMBER(J5:J27)) -> 10 | D38: =SUMPRODUCT((COUNTIF(M$5:M$27,M5:M27)=1)*ISNUMBER(M5:M27)) -> 11 | E38: =SUMPRODUCT((COUNTIF(P$5:P$27,P5:P27)=1)*ISNUMBER(P5:P27)) -> 8 | F38: =SUMPRODUCT((COUNTIF(S$5:S$27,S5:S27)=1)*ISNUMBER(S5:S27)) -> 5 | G38: =SUMPRODUCT((COUNTIF(V$5:V$27,V5:V27)=1)*ISNUMBER(V5:V27)) -> 10 | H38: =SUMPRODUCT((COUNTIF(Y$5:Y$27,Y5:Y27)=1)*ISNUMBER(Y5:Y27)) -> 9
A39: Con una presenza minima di 2 sempre garantita, gli ingressi/uscite intermedi avvengono a negozio presidiato.

Sheet Copertura
A1: COPERTURA A SLOT DI 15 MINUTI · presenti vs richiesti, con presidio responsabile
A2: Richiesti = casse necessarie + presidio SCO + attivita operative distribuite col profilo pesi (col. B, modificabile), minimo 2 persone.
C3: Lun | G3: Mar | K3: Mer | O3: Gio | S3: Ven | W3: Sab | AA3: Dom
A4: Ora | B4: Peso | C4: Pres | D4: Resp | E4: Rich | F4: Esito | G4: Pres | H4: Resp | I4: Rich | J4: Esito | K4: Pres | L4: Resp | M4: Rich | N4: Esito | O4: Pres | P4: Resp | Q4: Rich | R4: Esito | S4: Pres | T4: Resp | U4: Rich | V4: Esito | W4: Pres | X4: Resp | Y4: Rich | Z4: Esito | AA4: Pres | AB4: Resp | AC4: Rich | AD4: Esito | AE4: Etich.
A6: 0.22916667 | B6: 2.2 | C6: =SUMPRODUCT((Turni!$F$5:$F$27<=$A6)*(Turni!$G$5:$G$27>$A6)) -> 5 | D6: =SUMPRODUCT((Turni!$F$5:$F$27<=$A6)*(Turni!$G$5:$G$27>$A6)*(Turni!$B$5:$B$27="RESP")) -> 3 | E6: =IF($A6<Parametri!B$63,0,MAX(Parametri!$B$66,IF(AND($A6>=8/24,$A6<21/24),INDEX(Casse!B$6:B$18,INT($A6*24)-7)+Parametri!$B$17,0)+INT((OreRichieste!B$17-Casse!B$19-Casse!B$25)*$B6/SUMIFS($B$6:$B$68,$A$6:$A$68,">="&Parametri!B$63)/0.25))) -> 5 | F6: =IF(C6<E6,"KO",IF(AND(C6>0,D6=0),"NO RESP","OK")) -> OK | G6: =SUMPRODUCT((Turni!$I$5:$I$27<=$A6)*(Turni!$J$5:$J$27>$A6)) -> 0 | H6: =SUMPRODUCT((Turni!$I$5:$I$27<=$A6)*(Turni!$J$5:$J$27>$A6)*(Turni!$B$5:$B$27="RESP")) -> 0 | I6: =IF($A6<Parametri!C$63,0,MAX(Parametri!$B$66,IF(AND($A6>=8/24,$A6<21/24),INDEX(Casse!C$6:C$18,INT($A6*24)-7)+Parametri!$B$17,0)+INT((OreRichieste!C$17-Casse!C$19-Casse!C$25)*$B6/SUMIFS($B$6:$B$68,$A$6:$A$68,">="&Parametri!C$63)/0.25))) -> 0 | J6: =IF(G6<I6,"KO",IF(AND(G6>0,H6=0),"NO RESP","OK")) -> OK | K6: =SUMPRODUCT((Turni!$L$5:$L$27<=$A6)*(Turni!$M$5:$M$27>$A6)) -> 0 | L6: =SUMPRODUCT((Turni!$L$5:$L$27<=$A6)*(Turni!$M$5:$M$27>$A6)*(Turni!$B$5:$B$27="RESP")) -> 0 | M6: =IF($A6<Parametri!D$63,0,MAX(Parametri!$B$66,IF(AND($A6>=8/24,$A6<21/24),INDEX(Casse!D$6:D$18,INT($A6*24)-7)+Parametri!$B$17,0)+INT((OreRichieste!D$17-Casse!D$19-Casse!D$25)*$B6/SUMIFS($B$6:$B$68,$A$6:$A$68,">="&Parametri!D$63)/0.25))) -> 0 | N6: =IF(K6<M6,"KO",IF(AND(K6>0,L6=0),"NO RESP","OK")) -> OK | O6: =SUMPRODUCT((Turni!$O$5:$O$27<=$A6)*(Turni!$P$5:$P$27>$A6)) -> 5 | P6: =SUMPRODUCT((Turni!$O$5:$O$27<=$A6)*(Turni!$P$5:$P$27>$A6)*(Turni!$B$5:$B$27="RESP")) -> 3 | Q6: =IF($A6<Parametri!E$63,0,MAX(Parametri!$B$66,IF(AND($A6>=8/24,$A6<21/24),INDEX(Casse!E$6:E$18,INT($A6*24)-7)+Parametri!$B$17,0)+INT((OreRichieste!E$17-Casse!E$19-Casse!E$25)*$B6/SUMIFS($B$6:$B$68,$A$6:$A$68,">="&Parametri!E$63)/0.25))) -> 5 | R6: =IF(O6<Q6,"KO",IF(AND(O6>0,P6=0),"NO RESP","OK")) -> OK | S6: =SUMPRODUCT((Turni!$R$5:$R$27<=$A6)*(Turni!$S$5:$S$27>$A6)) -> 0 | T6: =SUMPRODUCT((Turni!$R$5:$R$27<=$A6)*(Turni!$S$5:$S$27>$A6)*(Turni!$B$5:$B$27="RESP")) -> 0 | U6: =IF($A6<Parametri!F$63,0,MAX(Parametri!$B$66,IF(AND($A6>=8/24,$A6<21/24),INDEX(Casse!F$6:F$18,INT($A6*24)-7)+Parametri!$B$17,0)+INT((OreRichieste!F$17-Casse!F$19-Casse!F$25)*$B6/SUMIFS($B$6:$B$68,$A$6:$A$68,">="&Parametri!F$63)/0.25))) -> 0 | V6: =IF(S6<U6,"KO",IF(AND(S6>0,T6=0),"NO RESP","OK")) -> OK | W6: =SUMPRODUCT((Turni!$U$5:$U$27<=$A6)*(Turni!$V$5:$V$27>$A6)) -> 5 | X6: =SUMPRODUCT((Turni!$U$5:$U$27<=$A6)*(Turni!$V$5:$V$27>$A6)*(Turni!$B$5:$B$27="RESP")) -> 2 | Y6: =IF($A6<Parametri!G$63,0,MAX(Parametri!$B$66,IF(AND($A6>=8/24,$A6<21/24),INDEX(Casse!G$6:G$18,INT($A6*24)-7)+Parametri!$B$17,0)+INT((OreRichieste!G$17-Casse!G$19-Casse!G$25)*$B6/SUMIFS($B$6:$B$68,$A$6:$A$68,">="&Parametri!G$63)/0.25))) -> 5 | Z6: =IF(W6<Y6,"KO",IF(AND(W6>0,X6=0),"NO RESP","OK")) -> OK | AA6: =SUMPRODUCT((Turni!$X$5:$X$27<=$A6)*(Turni!$Y$5:$Y$27>$A6)) -> 0 | AB6: =SUMPRODUCT((Turni!$X$5:$X$27<=$A6)*(Turni!$Y$5:$Y$27>$A6)*(Turni!$B$5:$B$27="RESP")) -> 0 | AC6: =IF($A6<Parametri!H$63,0,MAX(Parametri!$B$66,IF(AND($A6>=8/24,$A6<21/24),INDEX(Casse!H$6:H$18,INT($A6*24)-7)+Parametri!$B$17,0)+INT((OreRichieste!H$17-Casse!H$19-Casse!H$25)*$B6/SUMIFS($B$6:$B$68,$A$6:$A$68,">="&Parametri!H$63)/0.25))) -> 0 | AD6: =IF(AA6<AC6,"KO",IF(AND(AA6>0,AB6=0),"NO RESP","OK")) -> OK | AE6: 05:30
A7: 0.23958333 | B7: 2.2 | C7: =SUMPRODUCT((Turni!$F$5:$F$27<=$A7)*(Turni!$G$5:$G$27>$A7)) -> 5 | D7: =SUMPRODUCT((Turni!$F$5:$F$27<=$A7)*(Turni!$G$5:$G$27>$A7)*(Turni!$B$5:$B$27="RESP")) -> 3 | E7: =IF($A7<Parametri!B$63,0,MAX(Parametri!$B$66,IF(AND($A7>=8/24,$A7<21/24),INDEX(Casse!B$6:B$18,INT($A7*24)-7)+Parametri!$B$17,0)+INT((OreRichieste!B$17-Casse!B$19-Casse!B$25)*$B7/SUMIFS($B$6:$B$68,$A$6:$A$68,">="&Parametri!B$63)/0.25))) -> 5 | F7: =IF(C7<E7,"KO",IF(AND(C7>0,D7=0),"NO RESP","OK")) -> OK | G7: =SUMPRODUCT((Turni!$I$5:$I$27<=$A7)*(Turni!$J$5:$J$27>$A7)) -> 0 | H7: =SUMPRODUCT((Turni!$I$5:$I$27<=$A7)*(Turni!$J$5:$J$27>$A7)*(Turni!$B$5:$B$27="RESP")) -> 0 | I7: =IF($A7<Parametri!C$63,0,MAX(Parametri!$B$66,IF(AND($A7>=8/24,$A7<21/24),INDEX(Casse!C$6:C$18,INT($A7*24)-7)+Parametri!$B$17,0)+INT((OreRichieste!C$17-Casse!C$19-Casse!C$25)*$B7/SUMIFS($B$6:$B$68,$A$6:$A$68,">="&Parametri!C$63)/0.25))) -> 0 | J7: =IF(G7<I7,"KO",IF(AND(G7>0,H7=0),"NO RESP","OK")) -> OK | K7: =SUMPRODUCT((Turni!$L$5:$L$27<=$A7)*(Turni!$M$5:$M$27>$A7)) -> 0 | L7: =SUMPRODUCT((Turni!$L$5:$L$27<=$A7)*(Turni!$M$5:$M$27>$A7)*(Turni!$B$5:$B$27="RESP")) -> 0 | M7: =IF($A7<Parametri!D$63,0,MAX(Parametri!$B$66,IF(AND($A7>=8/24,$A7<21/24),INDEX(Casse!D$6:D$18,INT($A7*24)-7)+Parametri!$B$17,0)+INT((OreRichieste!D$17-Casse!D$19-Casse!D$25)*$B7/SUMIFS($B$6:$B$68,$A$6:$A$68,">="&Parametri!D$63)/0.25))) -> 0 | N7: =IF(K7<M7,"KO",IF(AND(K7>0,L7=0),"NO RESP","OK")) -> OK | O7: =SUMPRODUCT((Turni!$O$5:$O$27<=$A7)*(Turni!$P$5:$P$27>$A7)) -> 5 | P7: =SUMPRODUCT((Turni!$O$5:$O$27<=$A7)*(Turni!$P$5:$P$27>$A7)*(Turni!$B$5:$B$27="RESP")) -> 3 | Q7: =IF($A7<Parametri!E$63,0,MAX(Parametri!$B$66,IF(AND($A7>=8/24,$A7<21/24),INDEX(Casse!E$6:E$18,INT($A7*24)-7)+Parametri!$B$17,0)+INT((OreRichieste!E$17-Casse!E$19-Casse!E$25)*$B7/SUMIFS($B$6:$B$68,$A$6:$A$68,">="&Parametri!E$63)/0.25))) -> 5 | R7: =IF(O7<Q7,"KO",IF(AND(O7>0,P7=0),"NO RESP","OK")) -> OK | S7: =SUMPRODUCT((Turni!$R$5:$R$27<=$A7)*(Turni!$S$5:$S$27>$A7)) -> 0 | T7: =SUMPRODUCT((Turni!$R$5:$R$27<=$A7)*(Turni!$S$5:$S$27>$A7)*(Turni!$B$5:$B$27="RESP")) -> 0 | U7: =IF($A7<Parametri!F$63,0,MAX(Parametri!$B$66,IF(AND($A7>=8/24,$A7<21/24),INDEX(Casse!F$6:F$18,INT($A7*24)-7)+Parametri!$B$17,0)+INT((OreRichieste!F$17-Casse!F$19-Casse!F$25)*$B7/SUMIFS($B$6:$B$68,$A$6:$A$68,">="&Parametri!F$63)/0.25))) -> 0 | V7: =IF(S7<U7,"KO",IF(AND(S7>0,T7=0),"NO RESP","OK")) -> OK | W7: =SUMPRODUCT((Turni!$U$5:$U$27<=$A7)*(Turni!$V$5:$V$27>$A7)) -> 5 | X7: =SUMPRODUCT((Turni!$U$5:$U$27<=$A7)*(Turni!$V$5:$V$27>$A7)*(Turni!$B$5:$B$27="RESP")) -> 2 | Y7: =IF($A7<Parametri!G$63,0,MAX(Parametri!$B$66,IF(AND($A7>=8/24,$A7<21/24),INDEX(Casse!G$6:G$18,INT($A7*24)-7)+Parametri!$B$17,0)+INT((OreRichieste!G$17-Casse!G$19-Casse!G$25)*$B7/SUMIFS($B$6:$B$68,$A$6:$A$68,">="&Parametri!G$63)/0.25))) -> 5 | Z7: =IF(W7<Y7,"KO",IF(AND(W7>0,X7=0),"NO RESP","OK")) -> OK | AA7: =SUMPRODUCT((Turni!$X$5:$X$27<=$A7)*(Turni!$Y$5:$Y$27>$A7)) -> 0 | AB7: =SUMPRODUCT((Turni!$X$5:$X$27<=$A7)*(Turni!$Y$5:$Y$27>$A7)*(Turni!$B$5:$B$27="RESP")) -> 0 | AC7: =IF($A7<Parametri!H$63,0,MAX(Parametri!$B$66,IF(AND($A7>=8/24,$A7<21/24),INDEX(Casse!H$6:H$18,INT($A7*24)-7)+Parametri!$B$17,0)+INT((OreRichieste!H$17-Casse!H$19-Casse!H$25)*$B7/SUMIFS($B$6:$B$68,$A$6:$A$68,">="&Parametri!H$63)/0.25))) -> 0 | AD7: =IF(AA7<AC7,"KO",IF(AND(AA7>0,AB7=0),"NO RESP","OK")) -> OK | AE7: 05:45
A8: 0.25 | B8: 2.2 | C8: =SUMPRODUCT((Turni!$F$5:$F$27<=$A8)*(Turni!$G$5:$G$27>$A8)) -> 5 | D8: =SUMPRODUCT((Turni!$F$5:$F$27<=$A8)*(Turni!$G$5:$G$27>$A8)*(Turni!$B$5:$B$27="RESP")) -> 3 | E8: =IF($A8<Parametri!B$63,0,MAX(Parametri!$B$66,IF(AND($A8>=8/24,$A8<21/24),INDEX(Casse!B$6:B$18,INT($A8*24)-7)+Parametri!$B$17,0)+INT((OreRichieste!B$17-Casse!B$19-Casse!B$25)*$B8/SUMIFS($B$6:$B$68,$A$6:$A$68,">="&Parametri!B$63)/0.25))) -> 5 | F8: =IF(C8<E8,"KO",IF(AND(C8>0,D8=0),"NO RESP","OK")) -> OK | G8: =SUMPRODUCT((Turni!$I$5:$I$27<=$A8)*(Turni!$J$5:$J$27>$A8)) -> 4 | H8: =SUMPRODUCT((Turni!$I$5:$I$27<=$A8)*(Turni!$J$5:$J$27>$A8)*(Turni!$B$5:$B$27="RESP")) -> 1 | I8: =IF($A8<Parametri!C$63,0,MAX(Parametri!$B$66,IF(AND($A8>=8/24,$A8<21/24),INDEX(Casse!C$6:C$18,INT($A8*24)-7)+Parametri!$B$17,0)+INT((OreRichieste!C$17-Casse!C$19-Casse!C$25)*$B8/SUMIFS($B$6:$B$68,$A$6:$A$68,">="&Parametri!C$63)/0.25))) -> 4 | J8: =IF(G8<I8,"KO",IF(AND(G8>0,H8=0),"NO RESP","OK")) -> OK | K8: =SUMPRODUCT((Turni!$L$5:$L$27<=$A8)*(Turni!$M$5:$M$27>$A8)) -> 4 | L8: =SUMPRODUCT((Turni!$L$5:$L$27<=$A8)*(Turni!$M$5:$M$27>$A8)*(Turni!$B$5:$B$27="RESP")) -> 1 | M8: =IF($A8<Parametri!D$63,0,MAX(Parametri!$B$66,IF(AND($A8>=8/24,$A8<21/24),INDEX(Casse!D$6:D$18,INT($A8*24)-7)+Parametri!$B$17,0)+INT((OreRichieste!D$17-Casse!D$19-Casse!D$25)*$B8/SUMIFS($B$6:$B$68,$A$6:$A$68,">="&Parametri!D$63)/0.25))) -> 4 | N8: =IF(K8<M8,"KO",IF(AND(K8>0,L8=0),"NO RESP","OK")) -> OK | O8: =SUMPRODUCT((Turni!$O$5:$O$27<=$A8)*(Turni!$P$5:$P$27>$A8)) -> 5 | P8: =SUMPRODUCT((Turni!$O$5:$O$27<=$A8)*(Turni!$P$5:$P$27>$A8)*(Turni!$B$5:$B$27="RESP")) -> 3 | Q8: =IF($A8<Parametri!E$63,0,MAX(Parametri!$B$66,IF(AND($A8>=8/24,$A8<21/24),INDEX(Casse!E$6:E$18,INT($A8*24)-7)+Parametri!$B$17,0)+INT((OreRichieste!E$17-Casse!E$19-Casse!E$25)*$B8/SUMIFS($B$6:$B$68,$A$6:$A$68,">="&Parametri!E$63)/0.25))) -> 5 | R8: =IF(O8<Q8,"KO",IF(AND(O8>0,P8=0),"NO RESP","OK")) -> OK | S8: =SUMPRODUCT((Turni!$R$5:$R$27<=$A8)*(Turni!$S$5:$S$27>$A8)) -> 4 | T8: =SUMPRODUCT((Turni!$R$5:$R$27<=$A8)*(Turni!$S$5:$S$27>$A8)*(Turni!$B$5:$B$27="RESP")) -> 2 | U8: =IF($A8<Parametri!F$63,0,MAX(Parametri!$B$66,IF(AND($A8>=8/24,$A8<21/24),INDEX(Casse!F$6:F$18,INT($A8*24)-7)+Parametri!$B$17,0)+INT((OreRichieste!F$17-Casse!F$19-Casse!F$25)*$B8/SUMIFS($B$6:$B$68,$A$6:$A$68,">="&Parametri!F$63)/0.25))) -> 4 | V8: =IF(S8<U8,"KO",IF(AND(S8>0,T8=0),"NO RESP","OK")) -> OK | W8: =SUMPRODUCT((Turni!$U$5:$U$27<=$A8)*(Turni!$V$5:$V$27>$A8)) -> 5 | X8: =SUMPRODUCT((Turni!$U$5:$U$27<=$A8)*(Turni!$V$5:$V$27>$A8)*(Turni!$B$5:$B$27="RESP")) -> 2 | Y8: =IF($A8<Parametri!G$63,0,MAX(Parametri!$B$66,IF(AND($A8>=8/24,$A8<21/24),INDEX(Casse!G$6:G$18,INT($A8*24)-7)+Parametri!$B$17,0)+INT((OreRichieste!G$17-Casse!G$19-Casse!G$25)*$B8/SUMIFS($B$6:$B$68,$A$6:$A$68,">="&Parametri!G$63)/0.25))) -> 5 | Z8: =IF(W8<Y8,"KO",IF(AND(W8>0,X8=0),"NO RESP","OK")) -> OK | AA8: =SUMPRODUCT((Turni!$X$5:$X$27<=$A8)*(Turni!$Y$5:$Y$27>$A8)) -> 4 | AB8: =SUMPRODUCT((Turni!$X$5:$X$27<=$A8)*(Turni!$Y$5:$Y$27>$A8)*(Turni!$B$5:$B$27="RESP")) -> 1 | AC8: =IF($A8<Parametri!H$63,0,MAX(Parametri!$B$66,IF(AND($A8>=8/24,$A8<21/24),INDEX(Casse!H$6:H$18,INT($A8*24)-7)+Parametri!$B$17,0)+INT((OreRichieste!H$17-Casse!H$19-Casse!H$25)*$B8/SUMIFS($B$6:$B$68,$A$6:$A$68,">="&Parametri!H$63)/0.25))) -> 4 | AD8: =IF(AA8<AC8,"KO",IF(AND(AA8>0,AB8=0),"NO RESP","OK")) -> OK | AE8: 06:00
A9: 0.26041667 | B9: 2.2 | C9: =SUMPRODUCT((Turni!$F$5:$F$27<=$A9)*(Turni!$G$5:$G$27>$A9)) -> 5 | D9: =SUMPRODUCT((Turni!$F$5:$F$27<=$A9)*(Turni!$G$5:$G$27>$A9)*(Turni!$B$5:$B$27="RESP")) -> 3 | E9: =IF($A9<Parametri!B$63,0,MAX(Parametri!$B$66,IF(AND($A9>=8/24,$A9<21/24),INDEX(Casse!B$6:B$18,INT($A9*24)-7)+Parametri!$B$17,0)+INT((OreRichieste!B$17-Casse!B$19-Casse!B$25)*$B9/SUMIFS($B$6:$B$68,$A$6:$A$68,">="&Parametri!B$63)/0.25))) -> 5 | F9: =IF(C9<E9,"KO",IF(AND(C9>0,D9=0),"NO RESP","OK")) -> OK | G9: =SUMPRODUCT((Turni!$I$5:$I$27<=$A9)*(Turni!$J$5:$J$27>$A9)) -> 4 | H9: =SUMPRODUCT((Turni!$I$5:$I$27<=$A9)*(Turni!$J$5:$J$27>$A9)*(Turni!$B$5:$B$27="RESP")) -> 1 | I9: =IF($A9<Parametri!C$63,0,MAX(Parametri!$B$66,IF(AND($A9>=8/24,$A9<21/24),INDEX(Casse!C$6:C$18,INT($A9*24)-7)+Parametri!$B$17,0)+INT((OreRichieste!C$17-Casse!C$19-Casse!C$25)*$B9/SUMIFS($B$6:$B$68,$A$6:$A$68,">="&Parametri!C$63)/0.25))) -> 4 | J9: =IF(G9<I9,"KO",IF(AND(G9>0,H9=0),"NO RESP","OK")) -> OK | K9: =SUMPRODUCT((Turni!$L$5:$L$27<=$A9)*(Turni!$M$5:$M$27>$A9)) -> 4 | L9: =SUMPRODUCT((Turni!$L$5:$L$27<=$A9)*(Turni!$M$5:$M$27>$A9)*(Turni!$B$5:$B$27="RESP")) -> 1 | M9: =IF($A9<Parametri!D$63,0,MAX(Parametri!$B$66,IF(AND($A9>=8/24,$A9<21/24),INDEX(Casse!D$6:D$18,INT($A9*24)-7)+Parametri!$B$17,0)+INT((OreRichieste!D$17-Casse!D$19-Casse!D$25)*$B9/SUMIFS($B$6:$B$68,$A$6:$A$68,">="&Parametri!D$63)/0.25))) -> 4 | N9: =IF(K9<M9,"KO",IF(AND(K9>0,L9=0),"NO RESP","OK")) -> OK | O9: =SUMPRODUCT((Turni!$O$5:$O$27<=$A9)*(Turni!$P$5:$P$27>$A9)) -> 5 | P9: =SUMPRODUCT((Turni!$O$5:$O$27<=$A9)*(Turni!$P$5:$P$27>$A9)*(Turni!$B$5:$B$27="RESP")) -> 3 | Q9: =IF($A9<Parametri!E$63,0,MAX(Parametri!$B$66,IF(AND($A9>=8/24,$A9<21/24),INDEX(Casse!E$6:E$18,INT($A9*24)-7)+Parametri!$B$17,0)+INT((OreRichieste!E$17-Casse!E$19-Casse!E$25)*$B9/SUMIFS($B$6:$B$68,$A$6:$A$68,">="&Parametri!E$63)/0.25))) -> 5 | R9: =IF(O9<Q9,"KO",IF(AND(O9>0,P9=0),"NO RESP","OK")) -> OK | S9: =SUMPRODUCT((Turni!$R$5:$R$27<=$A9)*(Turni!$S$5:$S$27>$A9)) -> 4 | T9: =SUMPRODUCT((Turni!$R$5:$R$27<=$A9)*(Turni!$S$5:$S$27>$A9)*(Turni!$B$5:$B$27="RESP")) -> 2 | U9: =IF($A9<Parametri!F$63,0,MAX(Parametri!$B$66,IF(AND($A9>=8/24,$A9<21/24),INDEX(Casse!F$6:F$18,INT($A9*24)-7)+Parametri!$B$17,0)+INT((OreRichieste!F$17-Casse!F$19-Casse!F$25)*$B9/SUMIFS($B$6:$B$68,$A$6:$A$68,">="&Parametri!F$63)/0.25))) -> 4 | V9: =IF(S9<U9,"KO",IF(AND(S9>0,T9=0),"NO RESP","OK")) -> OK | W9: =SUMPRODUCT((Turni!$U$5:$U$27<=$A9)*(Turni!$V$5:$V$27>$A9)) -> 5 | X9: =SUMPRODUCT((Turni!$U$5:$U$27<=$A9)*(Turni!$V$5:$V$27>$A9)*(Turni!$B$5:$B$27="RESP")) -> 2 | Y9: =IF($A9<Parametri!G$63,0,MAX(Parametri!$B$66,IF(AND($A9>=8/24,$A9<21/24),INDEX(Casse!G$6:G$18,INT($A9*24)-7)+Parametri!$B$17,0)+INT((OreRichieste!G$17-Casse!G$19-Casse!G$25)*$B9/SUMIFS($B$6:$B$68,$A$6:$A$68,">="&Parametri!G$63)/0.25))) -> 5 | Z9: =IF(W9<Y9,"KO",IF(AND(W9>0,X9=0),"NO RESP","OK")) -> OK | AA9: =SUMPRODUCT((Turni!$X$5:$X$27<=$A9)*(Turni!$Y$5:$Y$27>$A9)) -> 4 | AB9: =SUMPRODUCT((Turni!$X$5:$X$27<=$A9)*(Turni!$Y$5:$Y$27>$A9)*(Turni!$B$5:$B$27="RESP")) -> 1 | AC9: =IF($A9<Parametri!H$63,0,MAX(Parametri!$B$66,IF(AND($A9>=8/24,$A9<21/24),INDEX(Casse!H$6:H$18,INT($A9*24)-7)+Parametri!$B$17,0)+INT((OreRichieste!H$17-Casse!H$19-Casse!H$25)*$B9/SUMIFS($B$6:$B$68,$A$6:$A$68,">="&Parametri!H$63)/0.25))) -> 4 | AD9: =IF(AA9<AC9,"KO",IF(AND(AA9>0,AB9=0),"NO RESP","OK")) -> OK | AE9: 06:15
A10: 0.27083333 | B10: 2.2 | C10: =SUMPRODUCT((Turni!$F$5:$F$27<=$A10)*(Turni!$G$5:$G$27>$A10)) -> 5 | D10: =SUMPRODUCT((Turni!$F$5:$F$27<=$A10)*(Turni!$G$5:$G$27>$A10)*(Turni!$B$5:$B$27="RESP")) -> 3 | E10: =IF($A10<Parametri!B$63,0,MAX(Parametri!$B$66,IF(AND($A10>=8/24,$A10<21/24),INDEX(Casse!B$6:B$18,INT($A10*24)-7)+Parametri!$B$17,0)+INT((OreRichieste!B$17-Casse!B$19-Casse!B$25)*$B10/SUMIFS($B$6:$B$68,$A$6:$A$68,">="&Parametri!B$63)/0.25))) -> 5 | F10: =IF(C10<E10,"KO",IF(AND(C10>0,D10=0),"NO RESP","OK")) -> OK | G10: =SUMPRODUCT((Turni!$I$5:$I$27<=$A10)*(Turni!$J$5:$J$27>$A10)) -> 4 | H10: =SUMPRODUCT((Turni!$I$5:$I$27<=$A10)*(Turni!$J$5:$J$27>$A10)*(Turni!$B$5:$B$27="RESP")) -> 1 | I10: =IF($A10<Parametri!C$63,0,MAX(Parametri!$B$66,IF(AND($A10>=8/24,$A10<21/24),INDEX(Casse!C$6:C$18,INT($A10*24)-7)+Parametri!$B$17,0)+INT((OreRichieste!C$17-Casse!C$19-Casse!C$25)*$B10/SUMIFS($B$6:$B$68,$A$6:$A$68,">="&Parametri!C$63)/0.25))) -> 4 | J10: =IF(G10<I10,"KO",IF(AND(G10>0,H10=0),"NO RESP","OK")) -> OK | K10: =SUMPRODUCT((Turni!$L$5:$L$27<=$A10)*(Turni!$M$5:$M$27>$A10)) -> 4 | L10: =SUMPRODUCT((Turni!$L$5:$L$27<=$A10)*(Turni!$M$5:$M$27>$A10)*(Turni!$B$5:$B$27="RESP")) -> 1 | M10: =IF($A10<Parametri!D$63,0,MAX(Parametri!$B$66,IF(AND($A10>=8/24,$A10<21/24),INDEX(Casse!D$6:D$18,INT($A10*24)-7)+Parametri!$B$17,0)+INT((OreRichieste!D$17-Casse!D$19-Casse!D$25)*$B10/SUMIFS($B$6:$B$68,$A$6:$A$68,">="&Parametri!D$63)/0.25))) -> 4 | N10: =IF(K10<M10,"KO",IF(AND(K10>0,L10=0),"NO RESP","OK")) -> OK | O10: =SUMPRODUCT((Turni!$O$5:$O$27<=$A10)*(Turni!$P$5:$P$27>$A10)) -> 5 | P10: =SUMPRODUCT((Turni!$O$5:$O$27<=$A10)*(Turni!$P$5:$P$27>$A10)*(Turni!$B$5:$B$27="RESP")) -> 3 | Q10: =IF($A10<Parametri!E$63,0,MAX(Parametri!$B$66,IF(AND($A10>=8/24,$A10<21/24),INDEX(Casse!E$6:E$18,INT($A10*24)-7)+Parametri!$B$17,0)+INT((OreRichieste!E$17-Casse!E$19-Casse!E$25)*$B10/SUMIFS($B$6:$B$68,$A$6:$A$68,">="&Parametri!E$63)/0.25))) -> 5 | R10: =IF(O10<Q10,"KO",IF(AND(O10>0,P10=0),"NO RESP","OK")) -> OK | S10: =SUMPRODUCT((Turni!$R$5:$R$27<=$A10)*(Turni!$S$5:$S$27>$A10)) -> 4 | T10: =SUMPRODUCT((Turni!$R$5:$R$27<=$A10)*(Turni!$S$5:$S$27>$A10)*(Turni!$B$5:$B$27="RESP")) -> 2 | U10: =IF($A10<Parametri!F$63,0,MAX(Parametri!$B$66,IF(AND($A10>=8/24,$A10<21/24),INDEX(Casse!F$6:F$18,INT($A10*24)-7)+Parametri!$B$17,0)+INT((OreRichieste!F$17-Casse!F$19-Casse!F$25)*$B10/SUMIFS($B$6:$B$68,$A$6:$A$68,">="&Parametri!F$63)/0.25))) -> 4 | V10: =IF(S10<U10,"KO",IF(AND(S10>0,T10=0),"NO RESP","OK")) -> OK | W10: =SUMPRODUCT((Turni!$U$5:$U$27<=$A10)*(Turni!$V$5:$V$27>$A10)) -> 5 | X10: =SUMPRODUCT((Turni!$U$5:$U$27<=$A10)*(Turni!$V$5:$V$27>$A10)*(Turni!$B$5:$B$27="RESP")) -> 2 | Y10: =IF($A10<Parametri!G$63,0,MAX(Parametri!$B$66,IF(AND($A10>=8/24,$A10<21/24),INDEX(Casse!G$6:G$18,INT($A10*24)-7)+Parametri!$B$17,0)+INT((OreRichieste!G$17-Casse!G$19-Casse!G$25)*$B10/SUMIFS($B$6:$B$68,$A$6:$A$68,">="&Parametri!G$63)/0.25))) -> 5 | Z10: =IF(W10<Y10,"KO",IF(AND(W10>0,X10=0),"NO RESP","OK")) -> OK | AA10: =SUMPRODUCT((Turni!$X$5:$X$27<=$A10)*(Turni!$Y$5:$Y$27>$A10)) -> 4 | AB10: =SUMPRODUCT((Turni!$X$5:$X$27<=$A10)*(Turni!$Y$5:$Y$27>$A10)*(Turni!$B$5:$B$27="RESP")) -> 1 | AC10: =IF($A10<Parametri!H$63,0,MAX(Parametri!$B$66,IF(AND($A10>=8/24,$A10<21/24),INDEX(Casse!H$6:H$18,INT($A10*24)-7)+Parametri!$B$17,0)+INT((OreRichieste!H$17-Casse!H$19-Casse!H$25)*$B10/SUMIFS($B$6:$B$68,$A$6:$A$68,">="&Parametri!H$63)/0.25))) -> 4 | AD10: =IF(AA10<AC10,"KO",IF(AND(AA10>0,AB10=0),"NO RESP","OK")) -> OK | AE10: 06:30
A11: 0.28125 | B11: 2.2 | C11: =SUMPRODUCT((Turni!$F$5:$F$27<=$A11)*(Turni!$G$5:$G$27>$A11)) -> 5 | D11: =SUMPRODUCT((Turni!$F$5:$F$27<=$A11)*(Turni!$G$5:$G$27>$A11)*(Turni!$B$5:$B$27="RESP")) -> 3 | E11: =IF($A11<Parametri!B$63,0,MAX(Parametri!$B$66,IF(AND($A11>=8/24,$A11<21/24),INDEX(Casse!B$6:B$18,INT($A11*24)-7)+Parametri!$B$17,0)+INT((OreRichieste!B$17-Casse!B$19-Casse!B$25)*$B11/SUMIFS($B$6:$B$68,$A$6:$A$68,">="&Parametri!B$63)/0.25))) -> 5 | F11: =IF(C11<E11,"KO",IF(AND(C11>0,D11=0),"NO RESP","OK")) -> OK | G11: =SUMPRODUCT((Turni!$I$5:$I$27<=$A11)*(Turni!$J$5:$J$27>$A11)) -> 4 | H11: =SUMPRODUCT((Turni!$I$5:$I$27<=$A11)*(Turni!$J$5:$J$27>$A11)*(Turni!$B$5:$B$27="RESP")) -> 1 | I11: =IF($A11<Parametri!C$63,0,MAX(Parametri!$B$66,IF(AND($A11>=8/24,$A11<21/24),INDEX(Casse!C$6:C$18,INT($A11*24)-7)+Parametri!$B$17,0)+INT((OreRichieste!C$17-Casse!C$19-Casse!C$25)*$B11/SUMIFS($B$6:$B$68,$A$6:$A$68,">="&Parametri!C$63)/0.25))) -> 4 | J11: =IF(G11<I11,"KO",IF(AND(G11>0,H11=0),"NO RESP","OK")) -> OK | K11: =SUMPRODUCT((Turni!$L$5:$L$27<=$A11)*(Turni!$M$5:$M$27>$A11)) -> 4 | L11: =SUMPRODUCT((Turni!$L$5:$L$27<=$A11)*(Turni!$M$5:$M$27>$A11)*(Turni!$B$5:$B$27="RESP")) -> 1 | M11: =IF($A11<Parametri!D$63,0,MAX(Parametri!$B$66,IF(AND($A11>=8/24,$A11<21/24),INDEX(Casse!D$6:D$18,INT($A11*24)-7)+Parametri!$B$17,0)+INT((OreRichieste!D$17-Casse!D$19-Casse!D$25)*$B11/SUMIFS($B$6:$B$68,$A$6:$A$68,">="&Parametri!D$63)/0.25))) -> 4 | N11: =IF(K11<M11,"KO",IF(AND(K11>0,L11=0),"NO RESP","OK")) -> OK | O11: =SUMPRODUCT((Turni!$O$5:$O$27<=$A11)*(Turni!$P$5:$P$27>$A11)) -> 5 | P11: =SUMPRODUCT((Turni!$O$5:$O$27<=$A11)*(Turni!$P$5:$P$27>$A11)*(Turni!$B$5:$B$27="RESP")) -> 3 | Q11: =IF($A11<Parametri!E$63,0,MAX(Parametri!$B$66,IF(AND($A11>=8/24,$A11<21/24),INDEX(Casse!E$6:E$18,INT($A11*24)-7)+Parametri!$B$17,0)+INT((OreRichieste!E$17-Casse!E$19-Casse!E$25)*$B11/SUMIFS($B$6:$B$68,$A$6:$A$68,">="&Parametri!E$63)/0.25))) -> 5 | R11: =IF(O11<Q11,"KO",IF(AND(O11>0,P11=0),"NO RESP","OK")) -> OK | S11: =SUMPRODUCT((Turni!$R$5:$R$27<=$A11)*(Turni!$S$5:$S$27>$A11)) -> 4 | T11: =SUMPRODUCT((Turni!$R$5:$R$27<=$A11)*(Turni!$S$5:$S$27>$A11)*(Turni!$B$5:$B$27="RESP")) -> 2 | U11: =IF($A11<Parametri!F$63,0,MAX(Parametri!$B$66,IF(AND($A11>=8/24,$A11<21/24),INDEX(Casse!F$6:F$18,INT($A11*24)-7)+Parametri!$B$17,0)+INT((OreRichieste!F$17-Casse!F$19-Casse!F$25)*$B11/SUMIFS($B$6:$B$68,$A$6:$A$68,">="&Parametri!F$63)/0.25))) -> 4 | V11: =IF(S11<U11,"KO",IF(AND(S11>0,T11=0),"NO RESP","OK")) -> OK | W11: =SUMPRODUCT((Turni!$U$5:$U$27<=$A11)*(Turni!$V$5:$V$27>$A11)) -> 5 | X11: =SUMPRODUCT((Turni!$U$5:$U$27<=$A11)*(Turni!$V$5:$V$27>$A11)*(Turni!$B$5:$B$27="RESP")) -> 2 | Y11: =IF($A11<Parametri!G$63,0,MAX(Parametri!$B$66,IF(AND($A11>=8/24,$A11<21/24),INDEX(Casse!G$6:G$18,INT($A11*24)-7)+Parametri!$B$17,0)+INT((OreRichieste!G$17-Casse!G$19-Casse!G$25)*$B11/SUMIFS($B$6:$B$68,$A$6:$A$68,">="&Parametri!G$63)/0.25))) -> 5 | Z11: =IF(W11<Y11,"KO",IF(AND(W11>0,X11=0),"NO RESP","OK")) -> OK | AA11: =SUMPRODUCT((Turni!$X$5:$X$27<=$A11)*(Turni!$Y$5:$Y$27>$A11)) -> 4 | AB11: =SUMPRODUCT((Turni!$X$5:$X$27<=$A11)*(Turni!$Y$5:$Y$27>$A11)*(Turni!$B$5:$B$27="RESP")) -> 1 | AC11: =IF($A11<Parametri!H$63,0,MAX(Parametri!$B$66,IF(AND($A11>=8/24,$A11<21/24),INDEX(Casse!H$6:H$18,INT($A11*24)-7)+Parametri!$B$17,0)+INT((OreRichieste!H$17-Casse!H$19-Casse!H$25)*$B11/SUMIFS($B$6:$B$68,$A$6:$A$68,">="&Parametri!H$63)/0.25))) -> 4 | AD11: =IF(AA11<AC11,"KO",IF(AND(AA11>0,AB11=0),"NO RESP","OK")) -> OK | AE11: 06:45
A12: 0.29166667 | B12: 2.2 | C12: =SUMPRODUCT((Turni!$F$5:$F$27<=$A12)*(Turni!$G$5:$G$27>$A12)) -> 5 | D12: =SUMPRODUCT((Turni!$F$5:$F$27<=$A12)*(Turni!$G$5:$G$27>$A12)*(Turni!$B$5:$B$27="RESP")) -> 3 | E12: =IF($A12<Parametri!B$63,0,MAX(Parametri!$B$66,IF(AND($A12>=8/24,$A12<21/24),INDEX(Casse!B$6:B$18,INT($A12*24)-7)+Parametri!$B$17,0)+INT((OreRichieste!B$17-Casse!B$19-Casse!B$25)*$B12/SUMIFS($B$6:$B$68,$A$6:$A$68,">="&Parametri!B$63)/0.25))) -> 5 | F12: =IF(C12<E12,"KO",IF(AND(C12>0,D12=0),"NO RESP","OK")) -> OK | G12: =SUMPRODUCT((Turni!$I$5:$I$27<=$A12)*(Turni!$J$5:$J$27>$A12)) -> 4 | H12: =SUMPRODUCT((Turni!$I$5:$I$27<=$A12)*(Turni!$J$5:$J$27>$A12)*(Turni!$B$5:$B$27="RESP")) -> 1 | I12: =IF($A12<Parametri!C$63,0,MAX(Parametri!$B$66,IF(AND($A12>=8/24,$A12<21/24),INDEX(Casse!C$6:C$18,INT($A12*24)-7)+Parametri!$B$17,0)+INT((OreRichieste!C$17-Casse!C$19-Casse!C$25)*$B12/SUMIFS($B$6:$B$68,$A$6:$A$68,">="&Parametri!C$63)/0.25))) -> 4 | J12: =IF(G12<I12,"KO",IF(AND(G12>0,H12=0),"NO RESP","OK")) -> OK | K12: =SUMPRODUCT((Turni!$L$5:$L$27<=$A12)*(Turni!$M$5:$M$27>$A12)) -> 4 | L12: =SUMPRODUCT((Turni!$L$5:$L$27<=$A12)*(Turni!$M$5:$M$27>$A12)*(Turni!$B$5:$B$27="RESP")) -> 1 | M12: =IF($A12<Parametri!D$63,0,MAX(Parametri!$B$66,IF(AND($A12>=8/24,$A12<21/24),INDEX(Casse!D$6:D$18,INT($A12*24)-7)+Parametri!$B$17,0)+INT((OreRichieste!D$17-Casse!D$19-Casse!D$25)*$B12/SUMIFS($B$6:$B$68,$A$6:$A$68,">="&Parametri!D$63)/0.25))) -> 4 | N12: =IF(K12<M12,"KO",IF(AND(K12>0,L12=0),"NO RESP","OK")) -> OK | O12: =SUMPRODUCT((Turni!$O$5:$O$27<=$A12)*(Turni!$P$5:$P$27>$A12)) -> 5 | P12: =SUMPRODUCT((Turni!$O$5:$O$27<=$A12)*(Turni!$P$5:$P$27>$A12)*(Turni!$B$5:$B$27="RESP")) -> 3 | Q12: =IF($A12<Parametri!E$63,0,MAX(Parametri!$B$66,IF(AND($A12>=8/24,$A12<21/24),INDEX(Casse!E$6:E$18,INT($A12*24)-7)+Parametri!$B$17,0)+INT((OreRichieste!E$17-Casse!E$19-Casse!E$25)*$B12/SUMIFS($B$6:$B$68,$A$6:$A$68,">="&Parametri!E$63)/0.25))) -> 5 | R12: =IF(O12<Q12,"KO",IF(AND(O12>0,P12=0),"NO RESP","OK")) -> OK | S12: =SUMPRODUCT((Turni!$R$5:$R$27<=$A12)*(Turni!$S$5:$S$27>$A12)) -> 4 | T12: =SUMPRODUCT((Turni!$R$5:$R$27<=$A12)*(Turni!$S$5:$S$27>$A12)*(Turni!$B$5:$B$27="RESP")) -> 2 | U12: =IF($A12<Parametri!F$63,0,MAX(Parametri!$B$66,IF(AND($A12>=8/24,$A12<21/24),INDEX(Casse!F$6:F$18,INT($A12*24)-7)+Parametri!$B$17,0)+INT((OreRichieste!F$17-Casse!F$19-Casse!F$25)*$B12/SUMIFS($B$6:$B$68,$A$6:$A$68,">="&Parametri!F$63)/0.25))) -> 4 | V12: =IF(S12<U12,"KO",IF(AND(S12>0,T12=0),"NO RESP","OK")) -> OK | W12: =SUMPRODUCT((Turni!$U$5:$U$27<=$A12)*(Turni!$V$5:$V$27>$A12)) -> 5 | X12: =SUMPRODUCT((Turni!$U$5:$U$27<=$A12)*(Turni!$V$5:$V$27>$A12)*(Turni!$B$5:$B$27="RESP")) -> 2 | Y12: =IF($A12<Parametri!G$63,0,MAX(Parametri!$B$66,IF(AND($A12>=8/24,$A12<21/24),INDEX(Casse!G$6:G$18,INT($A12*24)-7)+Parametri!$B$17,0)+INT((OreRichieste!G$17-Casse!G$19-Casse!G$25)*$B12/SUMIFS($B$6:$B$68,$A$6:$A$68,">="&Parametri!G$63)/0.25))) -> 5 | Z12: =IF(W12<Y12,"KO",IF(AND(W12>0,X12=0),"NO RESP","OK")) -> OK | AA12: =SUMPRODUCT((Turni!$X$5:$X$27<=$A12)*(Turni!$Y$5:$Y$27>$A12)) -> 4 | AB12: =SUMPRODUCT((Turni!$X$5:$X$27<=$A12)*(Turni!$Y$5:$Y$27>$A12)*(Turni!$B$5:$B$27="RESP")) -> 1 | AC12: =IF($A12<Parametri!H$63,0,MAX(Parametri!$B$66,IF(AND($A12>=8/24,$A12<21/24),INDEX(Casse!H$6:H$18,INT($A12*24)-7)+Parametri!$B$17,0)+INT((OreRichieste!H$17-Casse!H$19-Casse!H$25)*$B12/SUMIFS($B$6:$B$68,$A$6:$A$68,">="&Parametri!H$63)/0.25))) -> 4 | AD12: =IF(AA12<AC12,"KO",IF(AND(AA12>0,AB12=0),"NO RESP","OK")) -> OK | AE12: 07:00
A13: 0.30208333 | B13: 2.2 | C13: =SUMPRODUCT((Turni!$F$5:$F$27<=$A13)*(Turni!$G$5:$G$27>$A13)) -> 5 | D13: =SUMPRODUCT((Turni!$F$5:$F$27<=$A13)*(Turni!$G$5:$G$27>$A13)*(Turni!$B$5:$B$27="RESP")) -> 3 | E13: =IF($A13<Parametri!B$63,0,MAX(Parametri!$B$66,IF(AND($A13>=8/24,$A13<21/24),INDEX(Casse!B$6:B$18,INT($A13*24)-7)+Parametri!$B$17,0)+INT((OreRichieste!B$17-Casse!B$19-Casse!B$25)*$B13/SUMIFS($B$6:$B$68,$A$6:$A$68,">="&Parametri!B$63)/0.25))) -> 5 | F13: =IF(C13<E13,"KO",IF(AND(C13>0,D13=0),"NO RESP","OK")) -> OK | G13: =SUMPRODUCT((Turni!$I$5:$I$27<=$A13)*(Turni!$J$5:$J$27>$A13)) -> 4 | H13: =SUMPRODUCT((Turni!$I$5:$I$27<=$A13)*(Turni!$J$5:$J$27>$A13)*(Turni!$B$5:$B$27="RESP")) -> 1 | I13: =IF($A13<Parametri!C$63,0,MAX(Parametri!$B$66,IF(AND($A13>=8/24,$A13<21/24),INDEX(Casse!C$6:C$18,INT($A13*24)-7)+Parametri!$B$17,0)+INT((OreRichieste!C$17-Casse!C$19-Casse!C$25)*$B13/SUMIFS($B$6:$B$68,$A$6:$A$68,">="&Parametri!C$63)/0.25))) -> 4 | J13: =IF(G13<I13,"KO",IF(AND(G13>0,H13=0),"NO RESP","OK")) -> OK | K13: =SUMPRODUCT((Turni!$L$5:$L$27<=$A13)*(Turni!$M$5:$M$27>$A13)) -> 4 | L13: =SUMPRODUCT((Turni!$L$5:$L$27<=$A13)*(Turni!$M$5:$M$27>$A13)*(Turni!$B$5:$B$27="RESP")) -> 1 | M13: =IF($A13<Parametri!D$63,0,MAX(Parametri!$B$66,IF(AND($A13>=8/24,$A13<21/24),INDEX(Casse!D$6:D$18,INT($A13*24)-7)+Parametri!$B$17,0)+INT((OreRichieste!D$17-Casse!D$19-Casse!D$25)*$B13/SUMIFS($B$6:$B$68,$A$6:$A$68,">="&Parametri!D$63)/0.25))) -> 4 | N13: =IF(K13<M13,"KO",IF(AND(K13>0,L13=0),"NO RESP","OK")) -> OK | O13: =SUMPRODUCT((Turni!$O$5:$O$27<=$A13)*(Turni!$P$5:$P$27>$A13)) -> 5 | P13: =SUMPRODUCT((Turni!$O$5:$O$27<=$A13)*(Turni!$P$5:$P$27>$A13)*(Turni!$B$5:$B$27="RESP")) -> 3 | Q13: =IF($A13<Parametri!E$63,0,MAX(Parametri!$B$66,IF(AND($A13>=8/24,$A13<21/24),INDEX(Casse!E$6:E$18,INT($A13*24)-7)+Parametri!$B$17,0)+INT((OreRichieste!E$17-Casse!E$19-Casse!E$25)*$B13/SUMIFS($B$6:$B$68,$A$6:$A$68,">="&Parametri!E$63)/0.25))) -> 5 | R13: =IF(O13<Q13,"KO",IF(AND(O13>0,P13=0),"NO RESP","OK")) -> OK | S13: =SUMPRODUCT((Turni!$R$5:$R$27<=$A13)*(Turni!$S$5:$S$27>$A13)) -> 4 | T13: =SUMPRODUCT((Turni!$R$5:$R$27<=$A13)*(Turni!$S$5:$S$27>$A13)*(Turni!$B$5:$B$27="RESP")) -> 2 | U13: =IF($A13<Parametri!F$63,0,MAX(Parametri!$B$66,IF(AND($A13>=8/24,$A13<21/24),INDEX(Casse!F$6:F$18,INT($A13*24)-7)+Parametri!$B$17,0)+INT((OreRichieste!F$17-Casse!F$19-Casse!F$25)*$B13/SUMIFS($B$6:$B$68,$A$6:$A$68,">="&Parametri!F$63)/0.25))) -> 4 | V13: =IF(S13<U13,"KO",IF(AND(S13>0,T13=0),"NO RESP","OK")) -> OK | W13: =SUMPRODUCT((Turni!$U$5:$U$27<=$A13)*(Turni!$V$5:$V$27>$A13)) -> 5 | X13: =SUMPRODUCT((Turni!$U$5:$U$27<=$A13)*(Turni!$V$5:$V$27>$A13)*(Turni!$B$5:$B$27="RESP")) -> 2 | Y13: =IF($A13<Parametri!G$63,0,MAX(Parametri!$B$66,IF(AND($A13>=8/24,$A13<21/24),INDEX(Casse!G$6:G$18,INT($A13*24)-7)+Parametri!$B$17,0)+INT((OreRichieste!G$17-Casse!G$19-Casse!G$25)*$B13/SUMIFS($B$6:$B$68,$A$6:$A$68,">="&Parametri!G$63)/0.25))) -> 5 | Z13: =IF(W13<Y13,"KO",IF(AND(W13>0,X13=0),"NO RESP","OK")) -> OK | AA13: =SUMPRODUCT((Turni!$X$5:$X$27<=$A13)*(Turni!$Y$5:$Y$27>$A13)) -> 4 | AB13: =SUMPRODUCT((Turni!$X$5:$X$27<=$A13)*(Turni!$Y$5:$Y$27>$A13)*(Turni!$B$5:$B$27="RESP")) -> 1 | AC13: =IF($A13<Parametri!H$63,0,MAX(Parametri!$B$66,IF(AND($A13>=8/24,$A13<21/24),INDEX(Casse!H$6:H$18,INT($A13*24)-7)+Parametri!$B$17,0)+INT((OreRichieste!H$17-Casse!H$19-Casse!H$25)*$B13/SUMIFS($B$6:$B$68,$A$6:$A$68,">="&Parametri!H$63)/0.25))) -> 4 | AD13: =IF(AA13<AC13,"KO",IF(AND(AA13>0,AB13=0),"NO RESP","OK")) -> OK | AE13: 07:15
A14: 0.3125 | B14: 2.2 | C14: =SUMPRODUCT((Turni!$F$5:$F$27<=$A14)*(Turni!$G$5:$G$27>$A14)) -> 5 | D14: =SUMPRODUCT((Turni!$F$5:$F$27<=$A14)*(Turni!$G$5:$G$27>$A14)*(Turni!$B$5:$B$27="RESP")) -> 3 | E14: =IF($A14<Parametri!B$63,0,MAX(Parametri!$B$66,IF(AND($A14>=8/24,$A14<21/24),INDEX(Casse!B$6:B$18,INT($A14*24)-7)+Parametri!$B$17,0)+INT((OreRichieste!B$17-Casse!B$19-Casse!B$25)*$B14/SUMIFS($B$6:$B$68,$A$6:$A$68,">="&Parametri!B$63)/0.25))) -> 5 | F14: =IF(C14<E14,"KO",IF(AND(C14>0,D14=0),"NO RESP","OK")) -> OK | G14: =SUMPRODUCT((Turni!$I$5:$I$27<=$A14)*(Turni!$J$5:$J$27>$A14)) -> 4 | H14: =SUMPRODUCT((Turni!$I$5:$I$27<=$A14)*(Turni!$J$5:$J$27>$A14)*(Turni!$B$5:$B$27="RESP")) -> 1 | I14: =IF($A14<Parametri!C$63,0,MAX(Parametri!$B$66,IF(AND($A14>=8/24,$A14<21/24),INDEX(Casse!C$6:C$18,INT($A14*24)-7)+Parametri!$B$17,0)+INT((OreRichieste!C$17-Casse!C$19-Casse!C$25)*$B14/SUMIFS($B$6:$B$68,$A$6:$A$68,">="&Parametri!C$63)/0.25))) -> 4 | J14: =IF(G14<I14,"KO",IF(AND(G14>0,H14=0),"NO RESP","OK")) -> OK | K14: =SUMPRODUCT((Turni!$L$5:$L$27<=$A14)*(Turni!$M$5:$M$27>$A14)) -> 4 | L14: =SUMPRODUCT((Turni!$L$5:$L$27<=$A14)*(Turni!$M$5:$M$27>$A14)*(Turni!$B$5:$B$27="RESP")) -> 1 | M14: =IF($A14<Parametri!D$63,0,MAX(Parametri!$B$66,IF(AND($A14>=8/24,$A14<21/24),INDEX(Casse!D$6:D$18,INT($A14*24)-7)+Parametri!$B$17,0)+INT((OreRichieste!D$17-Casse!D$19-Casse!D$25)*$B14/SUMIFS($B$6:$B$68,$A$6:$A$68,">="&Parametri!D$63)/0.25))) -> 4 | N14: =IF(K14<M14,"KO",IF(AND(K14>0,L14=0),"NO RESP","OK")) -> OK | O14: =SUMPRODUCT((Turni!$O$5:$O$27<=$A14)*(Turni!$P$5:$P$27>$A14)) -> 5 | P14: =SUMPRODUCT((Turni!$O$5:$O$27<=$A14)*(Turni!$P$5:$P$27>$A14)*(Turni!$B$5:$B$27="RESP")) -> 3 | Q14: =IF($A14<Parametri!E$63,0,MAX(Parametri!$B$66,IF(AND($A14>=8/24,$A14<21/24),INDEX(Casse!E$6:E$18,INT($A14*24)-7)+Parametri!$B$17,0)+INT((OreRichieste!E$17-Casse!E$19-Casse!E$25)*$B14/SUMIFS($B$6:$B$68,$A$6:$A$68,">="&Parametri!E$63)/0.25))) -> 5 | R14: =IF(O14<Q14,"KO",IF(AND(O14>0,P14=0),"NO RESP","OK")) -> OK | S14: =SUMPRODUCT((Turni!$R$5:$R$27<=$A14)*(Turni!$S$5:$S$27>$A14)) -> 4 | T14: =SUMPRODUCT((Turni!$R$5:$R$27<=$A14)*(Turni!$S$5:$S$27>$A14)*(Turni!$B$5:$B$27="RESP")) -> 2 | U14: =IF($A14<Parametri!F$63,0,MAX(Parametri!$B$66,IF(AND($A14>=8/24,$A14<21/24),INDEX(Casse!F$6:F$18,INT($A14*24)-7)+Parametri!$B$17,0)+INT((OreRichieste!F$17-Casse!F$19-Casse!F$25)*$B14/SUMIFS($B$6:$B$68,$A$6:$A$68,">="&Parametri!F$63)/0.25))) -> 4 | V14: =IF(S14<U14,"KO",IF(AND(S14>0,T14=0),"NO RESP","OK")) -> OK | W14: =SUMPRODUCT((Turni!$U$5:$U$27<=$A14)*(Turni!$V$5:$V$27>$A14)) -> 5 | X14: =SUMPRODUCT((Turni!$U$5:$U$27<=$A14)*(Turni!$V$5:$V$27>$A14)*(Turni!$B$5:$B$27="RESP")) -> 2 | Y14: =IF($A14<Parametri!G$63,0,MAX(Parametri!$B$66,IF(AND($A14>=8/24,$A14<21/24),INDEX(Casse!G$6:G$18,INT($A14*24)-7)+Parametri!$B$17,0)+INT((OreRichieste!G$17-Casse!G$19-Casse!G$25)*$B14/SUMIFS($B$6:$B$68,$A$6:$A$68,">="&Parametri!G$63)/0.25))) -> 5 | Z14: =IF(W14<Y14,"KO",IF(AND(W14>0,X14=0),"NO RESP","OK")) -> OK | AA14: =SUMPRODUCT((Turni!$X$5:$X$27<=$A14)*(Turni!$Y$5:$Y$27>$A14)) -> 4 | AB14: =SUMPRODUCT((Turni!$X$5:$X$27<=$A14)*(Turni!$Y$5:$Y$27>$A14)*(Turni!$B$5:$B$27="RESP")) -> 1 | AC14: =IF($A14<Parametri!H$63,0,MAX(Parametri!$B$66,IF(AND($A14>=8/24,$A14<21/24),INDEX(Casse!H$6:H$18,INT($A14*24)-7)+Parametri!$B$17,0)+INT((OreRichieste!H$17-Casse!H$19-Casse!H$25)*$B14/SUMIFS($B$6:$B$68,$A$6:$A$68,">="&Parametri!H$63)/0.25))) -> 4 | AD14: =IF(AA14<AC14,"KO",IF(AND(AA14>0,AB14=0),"NO RESP","OK")) -> OK | AE14: 07:30
A15: 0.32291667 | B15: 2.2 | C15: =SUMPRODUCT((Turni!$F$5:$F$27<=$A15)*(Turni!$G$5:$G$27>$A15)) -> 5 | D15: =SUMPRODUCT((Turni!$F$5:$F$27<=$A15)*(Turni!$G$5:$G$27>$A15)*(Turni!$B$5:$B$27="RESP")) -> 3 | E15: =IF($A15<Parametri!B$63,0,MAX(Parametri!$B$66,IF(AND($A15>=8/24,$A15<21/24),INDEX(Casse!B$6:B$18,INT($A15*24)-7)+Parametri!$B$17,0)+INT((OreRichieste!B$17-Casse!B$19-Casse!B$25)*$B15/SUMIFS($B$6:$B$68,$A$6:$A$68,">="&Parametri!B$63)/0.25))) -> 5 | F15: =IF(C15<E15,"KO",IF(AND(C15>0,D15=0),"NO RESP","OK")) -> OK | G15: =SUMPRODUCT((Turni!$I$5:$I$27<=$A15)*(Turni!$J$5:$J$27>$A15)) -> 4 | H15: =SUMPRODUCT((Turni!$I$5:$I$27<=$A15)*(Turni!$J$5:$J$27>$A15)*(Turni!$B$5:$B$27="RESP")) -> 1 | I15: =IF($A15<Parametri!C$63,0,MAX(Parametri!$B$66,IF(AND($A15>=8/24,$A15<21/24),INDEX(Casse!C$6:C$18,INT($A15*24)-7)+Parametri!$B$17,0)+INT((OreRichieste!C$17-Casse!C$19-Casse!C$25)*$B15/SUMIFS($B$6:$B$68,$A$6:$A$68,">="&Parametri!C$63)/0.25))) -> 4 | J15: =IF(G15<I15,"KO",IF(AND(G15>0,H15=0),"NO RESP","OK")) -> OK | K15: =SUMPRODUCT((Turni!$L$5:$L$27<=$A15)*(Turni!$M$5:$M$27>$A15)) -> 4 | L15: =SUMPRODUCT((Turni!$L$5:$L$27<=$A15)*(Turni!$M$5:$M$27>$A15)*(Turni!$B$5:$B$27="RESP")) -> 1 | M15: =IF($A15<Parametri!D$63,0,MAX(Parametri!$B$66,IF(AND($A15>=8/24,$A15<21/24),INDEX(Casse!D$6:D$18,INT($A15*24)-7)+Parametri!$B$17,0)+INT((OreRichieste!D$17-Casse!D$19-Casse!D$25)*$B15/SUMIFS($B$6:$B$68,$A$6:$A$68,">="&Parametri!D$63)/0.25))) -> 4 | N15: =IF(K15<M15,"KO",IF(AND(K15>0,L15=0),"NO RESP","OK")) -> OK | O15: =SUMPRODUCT((Turni!$O$5:$O$27<=$A15)*(Turni!$P$5:$P$27>$A15)) -> 5 | P15: =SUMPRODUCT((Turni!$O$5:$O$27<=$A15)*(Turni!$P$5:$P$27>$A15)*(Turni!$B$5:$B$27="RESP")) -> 3 | Q15: =IF($A15<Parametri!E$63,0,MAX(Parametri!$B$66,IF(AND($A15>=8/24,$A15<21/24),INDEX(Casse!E$6:E$18,INT($A15*24)-7)+Parametri!$B$17,0)+INT((OreRichieste!E$17-Casse!E$19-Casse!E$25)*$B15/SUMIFS($B$6:$B$68,$A$6:$A$68,">="&Parametri!E$63)/0.25))) -> 5 | R15: =IF(O15<Q15,"KO",IF(AND(O15>0,P15=0),"NO RESP","OK")) -> OK | S15: =SUMPRODUCT((Turni!$R$5:$R$27<=$A15)*(Turni!$S$5:$S$27>$A15)) -> 4 | T15: =SUMPRODUCT((Turni!$R$5:$R$27<=$A15)*(Turni!$S$5:$S$27>$A15)*(Turni!$B$5:$B$27="RESP")) -> 2 | U15: =IF($A15<Parametri!F$63,0,MAX(Parametri!$B$66,IF(AND($A15>=8/24,$A15<21/24),INDEX(Casse!F$6:F$18,INT($A15*24)-7)+Parametri!$B$17,0)+INT((OreRichieste!F$17-Casse!F$19-Casse!F$25)*$B15/SUMIFS($B$6:$B$68,$A$6:$A$68,">="&Parametri!F$63)/0.25))) -> 4 | V15: =IF(S15<U15,"KO",IF(AND(S15>0,T15=0),"NO RESP","OK")) -> OK | W15: =SUMPRODUCT((Turni!$U$5:$U$27<=$A15)*(Turni!$V$5:$V$27>$A15)) -> 5 | X15: =SUMPRODUCT((Turni!$U$5:$U$27<=$A15)*(Turni!$V$5:$V$27>$A15)*(Turni!$B$5:$B$27="RESP")) -> 2 | Y15: =IF($A15<Parametri!G$63,0,MAX(Parametri!$B$66,IF(AND($A15>=8/24,$A15<21/24),INDEX(Casse!G$6:G$18,INT($A15*24)-7)+Parametri!$B$17,0)+INT((OreRichieste!G$17-Casse!G$19-Casse!G$25)*$B15/SUMIFS($B$6:$B$68,$A$6:$A$68,">="&Parametri!G$63)/0.25))) -> 5 | Z15: =IF(W15<Y15,"KO",IF(AND(W15>0,X15=0),"NO RESP","OK")) -> OK | AA15: =SUMPRODUCT((Turni!$X$5:$X$27<=$A15)*(Turni!$Y$5:$Y$27>$A15)) -> 4 | AB15: =SUMPRODUCT((Turni!$X$5:$X$27<=$A15)*(Turni!$Y$5:$Y$27>$A15)*(Turni!$B$5:$B$27="RESP")) -> 1 | AC15: =IF($A15<Parametri!H$63,0,MAX(Parametri!$B$66,IF(AND($A15>=8/24,$A15<21/24),INDEX(Casse!H$6:H$18,INT($A15*24)-7)+Parametri!$B$17,0)+INT((OreRichieste!H$17-Casse!H$19-Casse!H$25)*$B15/SUMIFS($B$6:$B$68,$A$6:$A$68,">="&Parametri!H$63)/0.25))) -> 4 | AD15: =IF(AA15<AC15,"KO",IF(AND(AA15>0,AB15=0),"NO RESP","OK")) -> OK | AE15: 07:45
A16: 0.33333333 | B16: 1.7 | C16: =SUMPRODUCT((Turni!$F$5:$F$27<=$A16)*(Turni!$G$5:$G$27>$A16)) -> 7 | D16: =SUMPRODUCT((Turni!$F$5:$F$27<=$A16)*(Turni!$G$5:$G$27>$A16)*(Turni!$B$5:$B$27="RESP")) -> 3 | E16: =IF($A16<Parametri!B$63,0,MAX(Parametri!$B$66,IF(AND($A16>=8/24,$A16<21/24),INDEX(Casse!B$6:B$18,INT($A16*24)-7)+Parametri!$B$17,0)+INT((OreRichieste!B$17-Casse!B$19-Casse!B$25)*$B16/SUMIFS($B$6:$B$68,$A$6:$A$68,">="&Parametri!B$63)/0.25))) -> 7 | F16: =IF(C16<E16,"KO",IF(AND(C16>0,D16=0),"NO RESP","OK")) -> OK | G16: =SUMPRODUCT((Turni!$I$5:$I$27<=$A16)*(Turni!$J$5:$J$27>$A16)) -> 5 | H16: =SUMPRODUCT((Turni!$I$5:$I$27<=$A16)*(Turni!$J$5:$J$27>$A16)*(Turni!$B$5:$B$27="RESP")) -> 1 | I16: =IF($A16<Parametri!C$63,0,MAX(Parametri!$B$66,IF(AND($A16>=8/24,$A16<21/24),INDEX(Casse!C$6:C$18,INT($A16*24)-7)+Parametri!$B$17,0)+INT((OreRichieste!C$17-Casse!C$19-Casse!C$25)*$B16/SUMIFS($B$6:$B$68,$A$6:$A$68,">="&Parametri!C$63)/0.25))) -> 5 | J16: =IF(G16<I16,"KO",IF(AND(G16>0,H16=0),"NO RESP","OK")) -> OK | K16: =SUMPRODUCT((Turni!$L$5:$L$27<=$A16)*(Turni!$M$5:$M$27>$A16)) -> 5 | L16: =SUMPRODUCT((Turni!$L$5:$L$27<=$A16)*(Turni!$M$5:$M$27>$A16)*(Turni!$B$5:$B$27="RESP")) -> 1 | M16: =IF($A16<Parametri!D$63,0,MAX(Parametri!$B$66,IF(AND($A16>=8/24,$A16<21/24),INDEX(Casse!D$6:D$18,INT($A16*24)-7)+Parametri!$B$17,0)+INT((OreRichieste!D$17-Casse!D$19-Casse!D$25)*$B16/SUMIFS($B$6:$B$68,$A$6:$A$68,">="&Parametri!D$63)/0.25))) -> 5 | N16: =IF(K16<M16,"KO",IF(AND(K16>0,L16=0),"NO RESP","OK")) -> OK | O16: =SUMPRODUCT((Turni!$O$5:$O$27<=$A16)*(Turni!$P$5:$P$27>$A16)) -> 6 | P16: =SUMPRODUCT((Turni!$O$5:$O$27<=$A16)*(Turni!$P$5:$P$27>$A16)*(Turni!$B$5:$B$27="RESP")) -> 3 | Q16: =IF($A16<Parametri!E$63,0,MAX(Parametri!$B$66,IF(AND($A16>=8/24,$A16<21/24),INDEX(Casse!E$6:E$18,INT($A16*24)-7)+Parametri!$B$17,0)+INT((OreRichieste!E$17-Casse!E$19-Casse!E$25)*$B16/SUMIFS($B$6:$B$68,$A$6:$A$68,">="&Parametri!E$63)/0.25))) -> 6 | R16: =IF(O16<Q16,"KO",IF(AND(O16>0,P16=0),"NO RESP","OK")) -> OK | S16: =SUMPRODUCT((Turni!$R$5:$R$27<=$A16)*(Turni!$S$5:$S$27>$A16)) -> 6 | T16: =SUMPRODUCT((Turni!$R$5:$R$27<=$A16)*(Turni!$S$5:$S$27>$A16)*(Turni!$B$5:$B$27="RESP")) -> 2 | U16: =IF($A16<Parametri!F$63,0,MAX(Parametri!$B$66,IF(AND($A16>=8/24,$A16<21/24),INDEX(Casse!F$6:F$18,INT($A16*24)-7)+Parametri!$B$17,0)+INT((OreRichieste!F$17-Casse!F$19-Casse!F$25)*$B16/SUMIFS($B$6:$B$68,$A$6:$A$68,">="&Parametri!F$63)/0.25))) -> 6 | V16: =IF(S16<U16,"KO",IF(AND(S16>0,T16=0),"NO RESP","OK")) -> OK | W16: =SUMPRODUCT((Turni!$U$5:$U$27<=$A16)*(Turni!$V$5:$V$27>$A16)) -> 7 | X16: =SUMPRODUCT((Turni!$U$5:$U$27<=$A16)*(Turni!$V$5:$V$27>$A16)*(Turni!$B$5:$B$27="RESP")) -> 3 | Y16: =IF($A16<Parametri!G$63,0,MAX(Parametri!$B$66,IF(AND($A16>=8/24,$A16<21/24),INDEX(Casse!G$6:G$18,INT($A16*24)-7)+Parametri!$B$17,0)+INT((OreRichieste!G$17-Casse!G$19-Casse!G$25)*$B16/SUMIFS($B$6:$B$68,$A$6:$A$68,">="&Parametri!G$63)/0.25))) -> 7 | Z16: =IF(W16<Y16,"KO",IF(AND(W16>0,X16=0),"NO RESP","OK")) -> OK | AA16: =SUMPRODUCT((Turni!$X$5:$X$27<=$A16)*(Turni!$Y$5:$Y$27>$A16)) -> 5 | AB16: =SUMPRODUCT((Turni!$X$5:$X$27<=$A16)*(Turni!$Y$5:$Y$27>$A16)*(Turni!$B$5:$B$27="RESP")) -> 2 | AC16: =IF($A16<Parametri!H$63,0,MAX(Parametri!$B$66,IF(AND($A16>=8/24,$A16<21/24),INDEX(Casse!H$6:H$18,INT($A16*24)-7)+Parametri!$B$17,0)+INT((OreRichieste!H$17-Casse!H$19-Casse!H$25)*$B16/SUMIFS($B$6:$B$68,$A$6:$A$68,">="&Parametri!H$63)/0.25))) -> 5 | AD16: =IF(AA16<AC16,"KO",IF(AND(AA16>0,AB16=0),"NO RESP","OK")) -> OK | AE16: 08:00
A17: 0.34375 | B17: 1.7 | C17: =SUMPRODUCT((Turni!$F$5:$F$27<=$A17)*(Turni!$G$5:$G$27>$A17)) -> 7 | D17: =SUMPRODUCT((Turni!$F$5:$F$27<=$A17)*(Turni!$G$5:$G$27>$A17)*(Turni!$B$5:$B$27="RESP")) -> 3 | E17: =IF($A17<Parametri!B$63,0,MAX(Parametri!$B$66,IF(AND($A17>=8/24,$A17<21/24),INDEX(Casse!B$6:B$18,INT($A17*24)-7)+Parametri!$B$17,0)+INT((OreRichieste!B$17-Casse!B$19-Casse!B$25)*$B17/SUMIFS($B$6:$B$68,$A$6:$A$68,">="&Parametri!B$63)/0.25))) -> 7 | F17: =IF(C17<E17,"KO",IF(AND(C17>0,D17=0),"NO RESP","OK")) -> OK | G17: =SUMPRODUCT((Turni!$I$5:$I$27<=$A17)*(Turni!$J$5:$J$27>$A17)) -> 5 | H17: =SUMPRODUCT((Turni!$I$5:$I$27<=$A17)*(Turni!$J$5:$J$27>$A17)*(Turni!$B$5:$B$27="RESP")) -> 1 | I17: =IF($A17<Parametri!C$63,0,MAX(Parametri!$B$66,IF(AND($A17>=8/24,$A17<21/24),INDEX(Casse!C$6:C$18,INT($A17*24)-7)+Parametri!$B$17,0)+INT((OreRichieste!C$17-Casse!C$19-Casse!C$25)*$B17/SUMIFS($B$6:$B$68,$A$6:$A$68,">="&Parametri!C$63)/0.25))) -> 5 | J17: =IF(G17<I17,"KO",IF(AND(G17>0,H17=0),"NO RESP","OK")) -> OK | K17: =SUMPRODUCT((Turni!$L$5:$L$27<=$A17)*(Turni!$M$5:$M$27>$A17)) -> 5 | L17: =SUMPRODUCT((Turni!$L$5:$L$27<=$A17)*(Turni!$M$5:$M$27>$A17)*(Turni!$B$5:$B$27="RESP")) -> 1 | M17: =IF($A17<Parametri!D$63,0,MAX(Parametri!$B$66,IF(AND($A17>=8/24,$A17<21/24),INDEX(Casse!D$6:D$18,INT($A17*24)-7)+Parametri!$B$17,0)+INT((OreRichieste!D$17-Casse!D$19-Casse!D$25)*$B17/SUMIFS($B$6:$B$68,$A$6:$A$68,">="&Parametri!D$63)/0.25))) -> 5 | N17: =IF(K17<M17,"KO",IF(AND(K17>0,L17=0),"NO RESP","OK")) -> OK | O17: =SUMPRODUCT((Turni!$O$5:$O$27<=$A17)*(Turni!$P$5:$P$27>$A17)) -> 6 | P17: =SUMPRODUCT((Turni!$O$5:$O$27<=$A17)*(Turni!$P$5:$P$27>$A17)*(Turni!$B$5:$B$27="RESP")) -> 3 | Q17: =IF($A17<Parametri!E$63,0,MAX(Parametri!$B$66,IF(AND($A17>=8/24,$A17<21/24),INDEX(Casse!E$6:E$18,INT($A17*24)-7)+Parametri!$B$17,0)+INT((OreRichieste!E$17-Casse!E$19-Casse!E$25)*$B17/SUMIFS($B$6:$B$68,$A$6:$A$68,">="&Parametri!E$63)/0.25))) -> 6 | R17: =IF(O17<Q17,"KO",IF(AND(O17>0,P17=0),"NO RESP","OK")) -> OK | S17: =SUMPRODUCT((Turni!$R$5:$R$27<=$A17)*(Turni!$S$5:$S$27>$A17)) -> 6 | T17: =SUMPRODUCT((Turni!$R$5:$R$27<=$A17)*(Turni!$S$5:$S$27>$A17)*(Turni!$B$5:$B$27="RESP")) -> 2 | U17: =IF($A17<Parametri!F$63,0,MAX(Parametri!$B$66,IF(AND($A17>=8/24,$A17<21/24),INDEX(Casse!F$6:F$18,INT($A17*24)-7)+Parametri!$B$17,0)+INT((OreRichieste!F$17-Casse!F$19-Casse!F$25)*$B17/SUMIFS($B$6:$B$68,$A$6:$A$68,">="&Parametri!F$63)/0.25))) -> 6 | V17: =IF(S17<U17,"KO",IF(AND(S17>0,T17=0),"NO RESP","OK")) -> OK | W17: =SUMPRODUCT((Turni!$U$5:$U$27<=$A17)*(Turni!$V$5:$V$27>$A17)) -> 7 | X17: =SUMPRODUCT((Turni!$U$5:$U$27<=$A17)*(Turni!$V$5:$V$27>$A17)*(Turni!$B$5:$B$27="RESP")) -> 3 | Y17: =IF($A17<Parametri!G$63,0,MAX(Parametri!$B$66,IF(AND($A17>=8/24,$A17<21/24),INDEX(Casse!G$6:G$18,INT($A17*24)-7)+Parametri!$B$17,0)+INT((OreRichieste!G$17-Casse!G$19-Casse!G$25)*$B17/SUMIFS($B$6:$B$68,$A$6:$A$68,">="&Parametri!G$63)/0.25))) -> 7 | Z17: =IF(W17<Y17,"KO",IF(AND(W17>0,X17=0),"NO RESP","OK")) -> OK | AA17: =SUMPRODUCT((Turni!$X$5:$X$27<=$A17)*(Turni!$Y$5:$Y$27>$A17)) -> 5 | AB17: =SUMPRODUCT((Turni!$X$5:$X$27<=$A17)*(Turni!$Y$5:$Y$27>$A17)*(Turni!$B$5:$B$27="RESP")) -> 2 | AC17: =IF($A17<Parametri!H$63,0,MAX(Parametri!$B$66,IF(AND($A17>=8/24,$A17<21/24),INDEX(Casse!H$6:H$18,INT($A17*24)-7)+Parametri!$B$17,0)+INT((OreRichieste!H$17-Casse!H$19-Casse!H$25)*$B17/SUMIFS($B$6:$B$68,$A$6:$A$68,">="&Parametri!H$63)/0.25))) -> 5 | AD17: =IF(AA17<AC17,"KO",IF(AND(AA17>0,AB17=0),"NO RESP","OK")) -> OK | AE17: 08:15
... A68: 0.875 | B68: 1.4 | C68: =SUMPRODUCT((Turni!$F$5:$F$27<=$A68)*(Turni!$G$5:$G$27>$A68)) -> 3 | D68: =SUMPRODUCT((Turni!$F$5:$F$27<=$A68)*(Turni!$G$5:$G$27>$A68)*(Turni!$B$5:$B$27="RESP")) -> 1 | E68: =IF($A68<Parametri!B$63,0,MAX(Parametri!$B$66,IF(AND($A68>=8/24,$A68<21/24),INDEX(Casse!B$6:B$18,INT($A68*24)-7)+Parametri!$B$17,0)+INT((OreRichieste!B$17-Casse!B$19-Casse!B$25)*$B68/SUMIFS($B$6:$B$68,$A$6:$A$68,">="&Parametri!B$63)/0.25))) -> 3 | F68: =IF(C68<E68,"KO",IF(AND(C68>0,D68=0),"NO RESP","OK")) -> OK | G68: =SUMPRODUCT((Turni!$I$5:$I$27<=$A68)*(Turni!$J$5:$J$27>$A68)) -> 2 | H68: =SUMPRODUCT((Turni!$I$5:$I$27<=$A68)*(Turni!$J$5:$J$27>$A68)*(Turni!$B$5:$B$27="RESP")) -> 1 | I68: =IF($A68<Parametri!C$63,0,MAX(Parametri!$B$66,IF(AND($A68>=8/24,$A68<21/24),INDEX(Casse!C$6:C$18,INT($A68*24)-7)+Parametri!$B$17,0)+INT((OreRichieste!C$17-Casse!C$19-Casse!C$25)*$B68/SUMIFS($B$6:$B$68,$A$6:$A$68,">="&Parametri!C$63)/0.25))) -> 2 | J68: =IF(G68<I68,"KO",IF(AND(G68>0,H68=0),"NO RESP","OK")) -> OK | K68: =SUMPRODUCT((Turni!$L$5:$L$27<=$A68)*(Turni!$M$5:$M$27>$A68)) -> 2 | L68: =SUMPRODUCT((Turni!$L$5:$L$27<=$A68)*(Turni!$M$5:$M$27>$A68)*(Turni!$B$5:$B$27="RESP")) -> 1 | M68: =IF($A68<Parametri!D$63,0,MAX(Parametri!$B$66,IF(AND($A68>=8/24,$A68<21/24),INDEX(Casse!D$6:D$18,INT($A68*24)-7)+Parametri!$B$17,0)+INT((OreRichieste!D$17-Casse!D$19-Casse!D$25)*$B68/SUMIFS($B$6:$B$68,$A$6:$A$68,">="&Parametri!D$63)/0.25))) -> 2 | N68: =IF(K68<M68,"KO",IF(AND(K68>0,L68=0),"NO RESP","OK")) -> OK | O68: =SUMPRODUCT((Turni!$O$5:$O$27<=$A68)*(Turni!$P$5:$P$27>$A68)) -> 3 | P68: =SUMPRODUCT((Turni!$O$5:$O$27<=$A68)*(Turni!$P$5:$P$27>$A68)*(Turni!$B$5:$B$27="RESP")) -> 2 | Q68: =IF($A68<Parametri!E$63,0,MAX(Parametri!$B$66,IF(AND($A68>=8/24,$A68<21/24),INDEX(Casse!E$6:E$18,INT($A68*24)-7)+Parametri!$B$17,0)+INT((OreRichieste!E$17-Casse!E$19-Casse!E$25)*$B68/SUMIFS($B$6:$B$68,$A$6:$A$68,">="&Parametri!E$63)/0.25))) -> 3 | R68: =IF(O68<Q68,"KO",IF(AND(O68>0,P68=0),"NO RESP","OK")) -> OK | S68: =SUMPRODUCT((Turni!$R$5:$R$27<=$A68)*(Turni!$S$5:$S$27>$A68)) -> 3 | T68: =SUMPRODUCT((Turni!$R$5:$R$27<=$A68)*(Turni!$S$5:$S$27>$A68)*(Turni!$B$5:$B$27="RESP")) -> 1 | U68: =IF($A68<Parametri!F$63,0,MAX(Parametri!$B$66,IF(AND($A68>=8/24,$A68<21/24),INDEX(Casse!F$6:F$18,INT($A68*24)-7)+Parametri!$B$17,0)+INT((OreRichieste!F$17-Casse!F$19-Casse!F$25)*$B68/SUMIFS($B$6:$B$68,$A$6:$A$68,">="&Parametri!F$63)/0.25))) -> 3 | V68: =IF(S68<U68,"KO",IF(AND(S68>0,T68=0),"NO RESP","OK")) -> OK | W68: =SUMPRODUCT((Turni!$U$5:$U$27<=$A68)*(Turni!$V$5:$V$27>$A68)) -> 3 | X68: =SUMPRODUCT((Turni!$U$5:$U$27<=$A68)*(Turni!$V$5:$V$27>$A68)*(Turni!$B$5:$B$27="RESP")) -> 2 | Y68: =IF($A68<Parametri!G$63,0,MAX(Parametri!$B$66,IF(AND($A68>=8/24,$A68<21/24),INDEX(Casse!G$6:G$18,INT($A68*24)-7)+Parametri!$B$17,0)+INT((OreRichieste!G$17-Casse!G$19-Casse!G$25)*$B68/SUMIFS($B$6:$B$68,$A$6:$A$68,">="&Parametri!G$63)/0.25))) -> 3 | Z68: =IF(W68<Y68,"KO",IF(AND(W68>0,X68=0),"NO RESP","OK")) -> OK | AA68: =SUMPRODUCT((Turni!$X$5:$X$27<=$A68)*(Turni!$Y$5:$Y$27>$A68)) -> 3 | AB68: =SUMPRODUCT((Turni!$X$5:$X$27<=$A68)*(Turni!$Y$5:$Y$27>$A68)*(Turni!$B$5:$B$27="RESP")) -> 1 | AC68: =IF($A68<Parametri!H$63,0,MAX(Parametri!$B$66,IF(AND($A68>=8/24,$A68<21/24),INDEX(Casse!H$6:H$18,INT($A68*24)-7)+Parametri!$B$17,0)+INT((OreRichieste!H$17-Casse!H$19-Casse!H$25)*$B68/SUMIFS($B$6:$B$68,$A$6:$A$68,">="&Parametri!H$63)/0.25))) -> 2 | AD68: =IF(AA68<AC68,"KO",IF(AND(AA68>0,AB68=0),"NO RESP","OK")) -> OK | AE68: 21:00
A70: Slot sotto copertura (KO) | C70: =COUNTIF(F6:F68,"KO") -> 2 | G70: =COUNTIF(J6:J68,"KO") -> 1 | K70: =COUNTIF(N6:N68,"KO") -> 0 | O70: =COUNTIF(R6:R68,"KO") -> 2 | S70: =COUNTIF(V6:V68,"KO") -> 2 | W70: =COUNTIF(Z6:Z68,"KO") -> 0 | AA70: =COUNTIF(AD6:AD68,"KO") -> 0
A71: Slot senza responsabile | C71: =COUNTIF(F6:F68,"NO RESP") -> 0 | G71: =COUNTIF(J6:J68,"NO RESP") -> 0 | K71: =COUNTIF(N6:N68,"NO RESP") -> 0 | O71: =COUNTIF(R6:R68,"NO RESP") -> 0 | S71: =COUNTIF(V6:V68,"NO RESP") -> 0 | W71: =COUNTIF(Z6:Z68,"NO RESP") -> 0 | AA71: =COUNTIF(AD6:AD68,"NO RESP") -> 0
A72: Minimo presenti in orario | C72: =_xlfn.MINIFS(C6:C68,$A$6:$A$68,">="&Parametri!B$63) -> 3 | G72: =_xlfn.MINIFS(G6:G68,$A$6:$A$68,">="&Parametri!C$63) -> 2 | K72: =_xlfn.MINIFS(K6:K68,$A$6:$A$68,">="&Parametri!D$63) -> 2 | O72: =_xlfn.MINIFS(O6:O68,$A$6:$A$68,">="&Parametri!E$63) -> 3 | S72: =_xlfn.MINIFS(S6:S68,$A$6:$A$68,">="&Parametri!F$63) -> 3 | W72: =_xlfn.MINIFS(W6:W68,$A$6:$A$68,">="&Parametri!G$63) -> 3 | AA72: =_xlfn.MINIFS(AA6:AA68,$A$6:$A$68,">="&Parametri!H$63) -> 3
A73: Esito giorno | C73: =IF(AND(C70=0,C71=0),"OK","KO") -> KO | G73: =IF(AND(G70=0,G71=0),"OK","KO") -> KO | K73: =IF(AND(K70=0,K71=0),"OK","KO") -> OK | O73: =IF(AND(O70=0,O71=0),"OK","KO") -> KO | S73: =IF(AND(S70=0,S71=0),"OK","KO") -> KO | W73: =IF(AND(W70=0,W71=0),"OK","KO") -> OK | AA73: =IF(AND(AA70=0,AA71=0),"OK","KO") -> OK

Sheet Parametri
A1: PARAMETRI DEL MODELLO · STORE HOURS ENGINE
A2: Standard SEGNAPOSTO di settore discount: da calibrare sui dati reali (regressione su storici o settimana fotografia).
A4: LEVE PRINCIPALI (input)
A5: Fatturato settimanale (EUR) | B5: 226000
A6: Pezzi venduti a settimana | B6: 136000
A7: Scontrino medio (EUR) | B7: 27.77
A8: Scontrini settimanali (calcolato) | B8: =B5/B7 -> 8138.2787
A9: Pezzi per scontrino (calcolato) | B9: =B6/B8 -> 16.71115
A10: Costo orario medio aziendale (EUR) | B10: 22
A12: CASSE E SELF-CHECKOUT (SCO)
A13: Coefficiente di sicurezza casse (dimensiona ~P75-P80) | B13: 1.15
A14: Capacita cassa barriera (scontrini/ora) | B14: 45
A15: Numero casse SCO installate | B15: 6
A16: Quota scontrini gestita dalle SCO quando attive | B16: 0.3
A17: Addetti di presidio SCO quando attive | B17: 1
A18: Casse barriera disponibili (fisiche) | B18: 4
A20: CATEGORIE MERCEOLOGICHE - RIFORNIMENTO A PEDANA (driver: pezzi venduti, logica PLT)
A21: Categoria | B21: % pezzi | C21: Pezzi/sett | D21: Pezzi per PLT | E21: PLT/sett | F21: Min per PLT | G21: Ore richieste/sett
A22: FV | B22: 0.12 | C22: =$B$6*B22 -> 16320 | D22: 480 | E22: =C22/D22 -> 34 | F22: 52 | G22: =E22*F22/60 -> 29.466667
A23: BAKE | B23: 0.129 | C23: =$B$6*B23 -> 17544 | D23: 540 | E23: =C23/D23 -> 32.488889 | F23: 90 | G23: =E23*F23/60 -> 48.733333
A24: CARNE | B24: 0.029 | C24: =$B$6*B24 -> 3944 | D24: 450 | E24: =C24/D24 -> 8.7644444 | F24: 58 | G24: =E24*F24/60 -> 8.4722963
A25: SECCHI | B25: 0.448 | C25: =$B$6*B25 -> 60928 | D25: 1356 | E25: =C25/D25 -> 44.932153 | F25: 66 | G25: =E25*F25/60 -> 49.425369
A26: SURGELATI | B26: 0.0299 | C26: =$B$6*B26 -> 4066.4 | D26: 425 | E26: =C26/D26 -> 9.568 | F26: 64 | G26: =E26*F26/60 -> 10.205867
A27: FRESCHI | B27: 0.1754 | C27: =$B$6*B27 -> 23854.4 | D27: 1154 | E27: =C27/D27 -> 20.671057 | F27: 67 | G27: =E27*F27/60 -> 23.082681
A28: PROMO FOOD | B28: 0.04 | C28: =$B$6*B28 -> 5440 | D28: 1085 | E28: =C28/D28 -> 5.0138249 | F28: 45 | G28: =E28*F28/60 -> 3.7603687 | H28: GESTIONE FOOD
A29: PROMO NF | B29: 0.029 | C29: =$B$6*B29 -> 3944 | D29: 410 | E29: =C29/D29 -> 9.6195122 | F29: 60 | G29: =E29*F29/60 -> 9.6195122 | H29: GESTIONE E RIPASSO NF
A30: Totale | B30: =SUM(B22:B29) -> 1.0003 | C30: =SUM(C22:C29) -> 136040.8 | E30: =SUM(E22:E29) -> 165.05788 | G30: =SUM(G22:G29) -> 182.76609
A33: CONTROLLO SCORTE E ORDINI
A34: Controllo scorte e ordini merce | B34: 1
A36: ATTIVITA FISSE GIORNALIERE
A37: Attivita fissa | B37: Ore/giorno
A38: Cura, controllo freschezza e rotazione FV | B38: 1.5
A39: Pulizia e gestione forni BAKE | B39: 0.5
A40: Controllo scadenze e ribassi | B40: 1.5
A41: Riordino sala e facing di chiusura | B41: 4
A42: Pulizie negozio e piazzale | B42: 1.5
A43: Gestione negozio (ordini, cassaforte, amministrazione) | B43: 2.5
A44: Totale | B44: =SUM(B38:B43) -> 11.5
A46: ATTIVITA SETTIMANALI (caricate sul giorno indicato)
A47: Attivita settimanale | B47: Ore/settimana | C47: Giorno
A48: Allestimento promo di lunedi (PROMO FOOD / PROMO NF) | B48: 10 | C48: Lun
A49: Allestimento promo di giovedi (PROMO FOOD / PROMO NF) | B49: 8 | C49: Gio
A50: Resi,NA NF | B50: 3 | C50: Mer
A51: Inventari rotativi | B51: 1 | C51: Lun
A53: BENCHMARK PRODUTTIVITA (target di verifica, usati in Dashboard)
A54: Produttivita minima (pezzi/ora lavorata) | B54: 280
A55: Produttivita massima (pezzi/ora lavorata) | B55: 300
A56: Produttivita minima (EUR/ora lavorata) | B56: 340
A57: Produttivita massima (EUR/ora lavorata) | B57: 420
A58: Incidenza massima costo lavoro su fatturato | B58: 0.07
A59: Range tipici formato discount hard: 200-240 pz/h e 330-420 EUR/h a totale negozio; da tarare sul cluster aziendale.
A61: REGOLE ORARIO DI LAVORO (vincoli di legge e di negozio)
A62: Regola | B62: Lun | C62: Mar | D62: Mer | E62: Gio | F62: Ven | G62: Sab | H62: Dom
A63: Orario di ingresso | B63: 0.22916667 | C63: 0.25 | D63: 0.25 | E63: 0.22916667 | F63: 0.25 | G63: 0.22916667 | H63: 0.25
A64: Orario di uscita (chiusura) | B64: 0.88541667 | C64: 0.88541667 | D64: 0.88541667 | E64: 0.88541667 | F64: 0.88541667 | G64: 0.88541667 | H64: 0.88541667
A65: Stacco minimo tra un turno e il successivo (ore) | B65: 11
A66: Presenza minima contemporanea in negozio (persone) | B66: 2
A67: Persone minime in apertura | B67: 2
A68: Persone minime in chiusura | B68: 2
A69: Part time: 25h -> 5 giorni x 5h; 30h -> 5 giorni x 6h (ore/giorno = monte ore / giorni, foglio Personale). Un responsabile deve essere sempre presente.

Sheet Volumi
A1: VOLUMI SETTIMANA TIPO · derivati da fatturato e pezzi (Parametri)
A2: Le % in blu sono dimostrative: calibrale con i dati di cassa reali. Tutto il resto si ricalcola da solo.
A4: RIPARTIZIONE DELLA SETTIMANA PER GIORNO
A5: Voce | B5: Lun | C5: Mar | D5: Mer | E5: Gio | F5: Ven | G5: Sab | H5: Dom | I5: Tot
A6: % del totale settimanale | B6: 0.137 | C6: 0.126 | D6: 0.124 | E6: 0.135 | F6: 0.15 | G6: 0.198 | H6: 0.13 | I6: =SUM(B6:H6) -> 1
A7: Pezzi venduti | B7: =Parametri!$B$6*B6 -> 18632 | C7: =Parametri!$B$6*C6 -> 17136 | D7: =Parametri!$B$6*D6 -> 16864 | E7: =Parametri!$B$6*E6 -> 18360 | F7: =Parametri!$B$6*F6 -> 20400 | G7: =Parametri!$B$6*G6 -> 26928 | H7: =Parametri!$B$6*H6 -> 17680 | I7: =SUM(B7:H7) -> 136000
A8: Scontrini | B8: =Parametri!$B$8*B6 -> 1114.9442 | C8: =Parametri!$B$8*C6 -> 1025.4231 | D8: =Parametri!$B$8*D6 -> 1009.1466 | E8: =Parametri!$B$8*E6 -> 1098.6676 | F8: =Parametri!$B$8*F6 -> 1220.7418 | G8: =Parametri!$B$8*G6 -> 1611.3792 | H8: =Parametri!$B$8*H6 -> 1057.9762 | I8: =SUM(B8:H8) -> 8138.2787
A9: Fatturato (EUR) | B9: =Parametri!$B$5*B6 -> 30962 | C9: =Parametri!$B$5*C6 -> 28476 | D9: =Parametri!$B$5*D6 -> 28024 | E9: =Parametri!$B$5*E6 -> 30510 | F9: =Parametri!$B$5*F6 -> 33900 | G9: =Parametri!$B$5*G6 -> 44748 | H9: =Parametri!$B$5*H6 -> 29380 | I9: =SUM(B9:H9) -> 226000
A10: Controllo ripartizione giorni | B10: =IF(ABS(I6-1)<0.0001,"OK","ERRORE: 100%") -> OK
A12: PEZZI VENDUTI PER CATEGORIA E GIORNO
A13: Categoria | B13: Lun | C13: Mar | D13: Mer | E13: Gio | F13: Ven | G13: Sab | H13: Dom | I13: Tot
A14: =Parametri!A22 -> FV | B14: =Parametri!$B$22*B$7 -> 2235.84 | C14: =Parametri!$B$22*C$7 -> 2056.32 | D14: =Parametri!$B$22*D$7 -> 2023.68 | E14: =Parametri!$B$22*E$7 -> 2203.2 | F14: =Parametri!$B$22*F$7 -> 2448 | G14: =Parametri!$B$22*G$7 -> 3231.36 | H14: =Parametri!$B$22*H$7 -> 2121.6 | I14: =SUM(B14:H14) -> 16320
A15: =Parametri!A23 -> BAKE | B15: =Parametri!$B$23*B$7 -> 2403.528 | C15: =Parametri!$B$23*C$7 -> 2210.544 | D15: =Parametri!$B$23*D$7 -> 2175.456 | E15: =Parametri!$B$23*E$7 -> 2368.44 | F15: =Parametri!$B$23*F$7 -> 2631.6 | G15: =Parametri!$B$23*G$7 -> 3473.712 | H15: =Parametri!$B$23*H$7 -> 2280.72 | I15: =SUM(B15:H15) -> 17544
A16: =Parametri!A24 -> CARNE | B16: =Parametri!$B$24*B$7 -> 540.328 | C16: =Parametri!$B$24*C$7 -> 496.944 | D16: =Parametri!$B$24*D$7 -> 489.056 | E16: =Parametri!$B$24*E$7 -> 532.44 | F16: =Parametri!$B$24*F$7 -> 591.6 | G16: =Parametri!$B$24*G$7 -> 780.912 | H16: =Parametri!$B$24*H$7 -> 512.72 | I16: =SUM(B16:H16) -> 3944
A17: =Parametri!A25 -> SECCHI | B17: =Parametri!$B$25*B$7 -> 8347.136 | C17: =Parametri!$B$25*C$7 -> 7676.928 | D17: =Parametri!$B$25*D$7 -> 7555.072 | E17: =Parametri!$B$25*E$7 -> 8225.28 | F17: =Parametri!$B$25*F$7 -> 9139.2 | G17: =Parametri!$B$25*G$7 -> 12063.744 | H17: =Parametri!$B$25*H$7 -> 7920.64 | I17: =SUM(B17:H17) -> 60928
A18: =Parametri!A26 -> SURGELATI | B18: =Parametri!$B$26*B$7 -> 557.0968 | C18: =Parametri!$B$26*C$7 -> 512.3664 | D18: =Parametri!$B$26*D$7 -> 504.2336 | E18: =Parametri!$B$26*E$7 -> 548.964 | F18: =Parametri!$B$26*F$7 -> 609.96 | G18: =Parametri!$B$26*G$7 -> 805.1472 | H18: =Parametri!$B$26*H$7 -> 528.632 | I18: =SUM(B18:H18) -> 4066.4
A19: =Parametri!A27 -> FRESCHI | B19: =Parametri!$B$27*B$7 -> 3268.0528 | C19: =Parametri!$B$27*C$7 -> 3005.6544 | D19: =Parametri!$B$27*D$7 -> 2957.9456 | E19: =Parametri!$B$27*E$7 -> 3220.344 | F19: =Parametri!$B$27*F$7 -> 3578.16 | G19: =Parametri!$B$27*G$7 -> 4723.1712 | H19: =Parametri!$B$27*H$7 -> 3101.072 | I19: =SUM(B19:H19) -> 23854.4
A20: =Parametri!A28 -> PROMO FOOD | B20: =Parametri!$B$28*B$7 -> 745.28 | C20: =Parametri!$B$28*C$7 -> 685.44 | D20: =Parametri!$B$28*D$7 -> 674.56 | E20: =Parametri!$B$28*E$7 -> 734.4 | F20: =Parametri!$B$28*F$7 -> 816 | G20: =Parametri!$B$28*G$7 -> 1077.12 | H20: =Parametri!$B$28*H$7 -> 707.2 | I20: =SUM(B20:H20) -> 5440
A21: =Parametri!A29 -> PROMO NF | B21: =Parametri!$B$29*B$7 -> 540.328 | C21: =Parametri!$B$29*C$7 -> 496.944 | D21: =Parametri!$B$29*D$7 -> 489.056 | E21: =Parametri!$B$29*E$7 -> 532.44 | F21: =Parametri!$B$29*F$7 -> 591.6 | G21: =Parametri!$B$29*G$7 -> 780.912 | H21: =Parametri!$B$29*H$7 -> 512.72 | I21: =SUM(B21:H21) -> 3944
A22: Totale pezzi | B22: =SUM(B14:B21) -> 18637.59 | C22: =SUM(C14:C21) -> 17141.141 | D22: =SUM(D14:D21) -> 16869.059 | E22: =SUM(E14:E21) -> 18365.508 | F22: =SUM(F14:F21) -> 20406.12 | G22: =SUM(G14:G21) -> 26936.078 | H22: =SUM(H14:H21) -> 17685.304 | I22: =SUM(I14:I21) -> 136040.8
A24: PLT MOVIMENTATE PER CATEGORIA E GIORNO (pezzi / pezzi per PLT)
A25: Categoria | B25: Lun | C25: Mar | D25: Mer | E25: Gio | F25: Ven | G25: Sab | H25: Dom | I25: Tot
A26: =Parametri!A22 -> FV | B26: =B14/Parametri!$D$22 -> 4.658 | C26: =C14/Parametri!$D$22 -> 4.284 | D26: =D14/Parametri!$D$22 -> 4.216 | E26: =E14/Parametri!$D$22 -> 4.59 | F26: =F14/Parametri!$D$22 -> 5.1 | G26: =G14/Parametri!$D$22 -> 6.732 | H26: =H14/Parametri!$D$22 -> 4.42 | I26: =SUM(B26:H26) -> 34
A27: =Parametri!A23 -> BAKE | B27: =B15/Parametri!$D$23 -> 4.4509778 | C27: =C15/Parametri!$D$23 -> 4.0936 | D27: =D15/Parametri!$D$23 -> 4.0286222 | E27: =E15/Parametri!$D$23 -> 4.386 | F27: =F15/Parametri!$D$23 -> 4.8733333 | G27: =G15/Parametri!$D$23 -> 6.4328 | H27: =H15/Parametri!$D$23 -> 4.2235556 | I27: =SUM(B27:H27) -> 32.488889
A28: =Parametri!A24 -> CARNE | B28: =B16/Parametri!$D$24 -> 1.2007289 | C28: =C16/Parametri!$D$24 -> 1.10432 | D28: =D16/Parametri!$D$24 -> 1.0867911 | E28: =E16/Parametri!$D$24 -> 1.1832 | F28: =F16/Parametri!$D$24 -> 1.3146667 | G28: =G16/Parametri!$D$24 -> 1.73536 | H28: =H16/Parametri!$D$24 -> 1.1393778 | I28: =SUM(B28:H28) -> 8.7644444
A29: =Parametri!A25 -> SECCHI | B29: =B17/Parametri!$D$25 -> 6.155705 | C29: =C17/Parametri!$D$25 -> 5.6614513 | D29: =D17/Parametri!$D$25 -> 5.571587 | E29: =E17/Parametri!$D$25 -> 6.0658407 | F29: =F17/Parametri!$D$25 -> 6.739823 | G29: =G17/Parametri!$D$25 -> 8.8965664 | H29: =H17/Parametri!$D$25 -> 5.8411799 | I29: =SUM(B29:H29) -> 44.932153
A30: =Parametri!A26 -> SURGELATI | B30: =B18/Parametri!$D$26 -> 1.310816 | C30: =C18/Parametri!$D$26 -> 1.205568 | D30: =D18/Parametri!$D$26 -> 1.186432 | E30: =E18/Parametri!$D$26 -> 1.29168 | F30: =F18/Parametri!$D$26 -> 1.4352 | G30: =G18/Parametri!$D$26 -> 1.894464 | H30: =H18/Parametri!$D$26 -> 1.24384 | I30: =SUM(B30:H30) -> 9.568
A31: =Parametri!A27 -> FRESCHI | B31: =B19/Parametri!$D$27 -> 2.8319348 | C31: =C19/Parametri!$D$27 -> 2.6045532 | D31: =D19/Parametri!$D$27 -> 2.5632111 | E31: =E19/Parametri!$D$27 -> 2.7905927 | F31: =F19/Parametri!$D$27 -> 3.1006586 | G31: =G19/Parametri!$D$27 -> 4.0928693 | H31: =H19/Parametri!$D$27 -> 2.6872374 | I31: =SUM(B31:H31) -> 20.671057
A32: =Parametri!A28 -> PROMO FOOD | B32: =B20/Parametri!$D$28 -> 0.68689401 | C32: =C20/Parametri!$D$28 -> 0.63174194 | D32: =D20/Parametri!$D$28 -> 0.62171429 | E32: =E20/Parametri!$D$28 -> 0.67686636 | F32: =F20/Parametri!$D$28 -> 0.75207373 | G32: =G20/Parametri!$D$28 -> 0.99273733 | H32: =H20/Parametri!$D$28 -> 0.65179724 | I32: =SUM(B32:H32) -> 5.0138249
A33: =Parametri!A29 -> PROMO NF | B33: =B21/Parametri!$D$29 -> 1.3178732 | C33: =C21/Parametri!$D$29 -> 1.2120585 | D33: =D21/Parametri!$D$29 -> 1.1928195 | E33: =E21/Parametri!$D$29 -> 1.2986341 | F33: =F21/Parametri!$D$29 -> 1.4429268 | G33: =G21/Parametri!$D$29 -> 1.9046634 | H33: =H21/Parametri!$D$29 -> 1.2505366 | I33: =SUM(B33:H33) -> 9.6195122
A34: Totale PLT | B34: =SUM(B26:B33) -> 22.61293 | C34: =SUM(C26:C33) -> 20.797293 | D34: =SUM(D26:D33) -> 20.467177 | E34: =SUM(E26:E33) -> 22.282814 | F34: =SUM(F26:F33) -> 24.758682 | G34: =SUM(G26:G33) -> 32.68146 | H34: =SUM(H26:H33) -> 21.457525 | I34: =SUM(I26:I33) -> 165.05788
A36: HEATMAP DOMANDA · scontrini per fascia oraria
A37: Fascia | B37: % del giorno | C37: Lun | D37: Mar | E37: Mer | F37: Gio | G37: Ven | H37: Sab | I37: Dom
A38: 08-09 | B38: 0.052 | C38: =$B38*B$8 -> 57.977098 | D38: =$B38*C$8 -> 53.322002 | E38: =$B38*D$8 -> 52.475621 | F38: =$B38*E$8 -> 57.130717 | G38: =$B38*F$8 -> 63.478574 | H38: =$B38*G$8 -> 83.791718 | I38: =$B38*H$8 -> 55.014764
A39: 09-10 | B39: 0.073 | C39: =$B39*B$8 -> 81.390925 | D39: =$B39*C$8 -> 74.855888 | E39: =$B39*D$8 -> 73.667699 | F39: =$B39*E$8 -> 80.202737 | G39: =$B39*F$8 -> 89.114152 | H39: =$B39*G$8 -> 117.63068 | I39: =$B39*H$8 -> 77.232265
A40: 10-11 | B40: 0.094 | C40: =$B40*B$8 -> 104.80475 | D40: =$B40*C$8 -> 96.389773 | E40: =$B40*D$8 -> 94.859777 | F40: =$B40*E$8 -> 103.27476 | G40: =$B40*F$8 -> 114.74973 | H40: =$B40*G$8 -> 151.46964 | I40: =$B40*H$8 -> 99.449766
A41: 11-12 | B41: 0.104 | C41: =$B41*B$8 -> 115.9542 | D41: =$B41*C$8 -> 106.644 | E41: =$B41*D$8 -> 104.95124 | F41: =$B41*E$8 -> 114.26143 | G41: =$B41*F$8 -> 126.95715 | H41: =$B41*G$8 -> 167.58344 | I41: =$B41*H$8 -> 110.02953
A42: 12-13 | B42: 0.083 | C42: =$B42*B$8 -> 92.540367 | D42: =$B42*C$8 -> 85.110119 | E42: =$B42*D$8 -> 83.759165 | F42: =$B42*E$8 -> 91.189413 | G42: =$B42*F$8 -> 101.32157 | H42: =$B42*G$8 -> 133.74447 | I42: =$B42*H$8 -> 87.812027
A43: 13-14 | B43: 0.073 | C43: =$B43*B$8 -> 81.390925 | D43: =$B43*C$8 -> 74.855888 | E43: =$B43*D$8 -> 73.667699 | F43: =$B43*E$8 -> 80.202737 | G43: =$B43*F$8 -> 89.114152 | H43: =$B43*G$8 -> 117.63068 | I43: =$B43*H$8 -> 77.232265
A44: 14-15 | B44: 0.062 | C44: =$B44*B$8 -> 69.126539 | D44: =$B44*C$8 -> 63.576233 | E44: =$B44*D$8 -> 62.567087 | F44: =$B44*E$8 -> 68.117393 | G44: =$B44*F$8 -> 75.685992 | H44: =$B44*G$8 -> 99.90551 | I44: =$B44*H$8 -> 65.594526
A45: 15-16 | B45: 0.062 | C45: =$B45*B$8 -> 69.126539 | D45: =$B45*C$8 -> 63.576233 | E45: =$B45*D$8 -> 62.567087 | F45: =$B45*E$8 -> 68.117393 | G45: =$B45*F$8 -> 75.685992 | H45: =$B45*G$8 -> 99.90551 | I45: =$B45*H$8 -> 65.594526
A46: 16-17 | B46: 0.073 | C46: =$B46*B$8 -> 81.390925 | D46: =$B46*C$8 -> 74.855888 | E46: =$B46*D$8 -> 73.667699 | F46: =$B46*E$8 -> 80.202737 | G46: =$B46*F$8 -> 89.114152 | H46: =$B46*G$8 -> 117.63068 | I46: =$B46*H$8 -> 77.232265
A47: 17-18 | B47: 0.094 | C47: =$B47*B$8 -> 104.80475 | D47: =$B47*C$8 -> 96.389773 | E47: =$B47*D$8 -> 94.859777 | F47: =$B47*E$8 -> 103.27476 | G47: =$B47*F$8 -> 114.74973 | H47: =$B47*G$8 -> 151.46964 | I47: =$B47*H$8 -> 99.449766
A48: 18-19 | B48: 0.104 | C48: =$B48*B$8 -> 115.9542 | D48: =$B48*C$8 -> 106.644 | E48: =$B48*D$8 -> 104.95124 | F48: =$B48*E$8 -> 114.26143 | G48: =$B48*F$8 -> 126.95715 | H48: =$B48*G$8 -> 167.58344 | I48: =$B48*H$8 -> 110.02953
A49: 19-20 | B49: 0.083 | C49: =$B49*B$8 -> 92.540367 | D49: =$B49*C$8 -> 85.110119 | E49: =$B49*D$8 -> 83.759165 | F49: =$B49*E$8 -> 91.189413 | G49: =$B49*F$8 -> 101.32157 | H49: =$B49*G$8 -> 133.74447 | I49: =$B49*H$8 -> 87.812027
A50: 20-21 | B50: 0.043 | C50: =$B50*B$8 -> 47.9426 | D50: =$B50*C$8 -> 44.093194 | E50: =$B50*D$8 -> 43.393302 | F50: =$B50*E$8 -> 47.242708 | G50: =$B50*F$8 -> 52.491898 | H50: =$B50*G$8 -> 69.289305 | I50: =$B50*H$8 -> 45.492978
A51: Totale | B51: =SUM(B38:B50) -> 1 | C51: =SUM(C38:C50) -> 1114.9442 | D51: =SUM(D38:D50) -> 1025.4231 | E51: =SUM(E38:E50) -> 1009.1466 | F51: =SUM(F38:F50) -> 1098.6676 | G51: =SUM(G38:G50) -> 1220.7418 | H51: =SUM(H38:H50) -> 1611.3792 | I51: =SUM(I38:I50) -> 1057.9762
A52: Controllo profilo fasce | B52: =IF(ABS(B51-1)<0.0001,"OK","ERRORE: 100%") -> OK

Sheet Casse
A1: FRONT-END · barriera casse + self-checkout (SCO)
A2: Casse necessarie = scontrini barriera x coefficiente sicurezza / capacita cassa (minimo 1 a negozio aperto).
A3: Scontrini barriera = scontrini totali x (1 - quota SCO). Parametri modificabili nel foglio Parametri.
A5: Fascia | B5: Lun | C5: Mar | D5: Mer | E5: Gio | F5: Ven | G5: Sab | H5: Dom
A6: 08-09 | B6: =MAX(1,ROUNDUP(Volumi!C38*(1-Parametri!$B$16)*Parametri!$B$13/Parametri!$B$14,0)) -> 2 | C6: =MAX(1,ROUNDUP(Volumi!D38*(1-Parametri!$B$16)*Parametri!$B$13/Parametri!$B$14,0)) -> 1 | D6: =MAX(1,ROUNDUP(Volumi!E38*(1-Parametri!$B$16)*Parametri!$B$13/Parametri!$B$14,0)) -> 1 | E6: =MAX(1,ROUNDUP(Volumi!F38*(1-Parametri!$B$16)*Parametri!$B$13/Parametri!$B$14,0)) -> 2 | F6: =MAX(1,ROUNDUP(Volumi!G38*(1-Parametri!$B$16)*Parametri!$B$13/Parametri!$B$14,0)) -> 2 | G6: =MAX(1,ROUNDUP(Volumi!H38*(1-Parametri!$B$16)*Parametri!$B$13/Parametri!$B$14,0)) -> 2 | H6: =MAX(1,ROUNDUP(Volumi!I38*(1-Parametri!$B$16)*Parametri!$B$13/Parametri!$B$14,0)) -> 1
A7: 09-10 | B7: =MAX(1,ROUNDUP(Volumi!C39*(1-Parametri!$B$16)*Parametri!$B$13/Parametri!$B$14,0)) -> 2 | C7: =MAX(1,ROUNDUP(Volumi!D39*(1-Parametri!$B$16)*Parametri!$B$13/Parametri!$B$14,0)) -> 2 | D7: =MAX(1,ROUNDUP(Volumi!E39*(1-Parametri!$B$16)*Parametri!$B$13/Parametri!$B$14,0)) -> 2 | E7: =MAX(1,ROUNDUP(Volumi!F39*(1-Parametri!$B$16)*Parametri!$B$13/Parametri!$B$14,0)) -> 2 | F7: =MAX(1,ROUNDUP(Volumi!G39*(1-Parametri!$B$16)*Parametri!$B$13/Parametri!$B$14,0)) -> 2 | G7: =MAX(1,ROUNDUP(Volumi!H39*(1-Parametri!$B$16)*Parametri!$B$13/Parametri!$B$14,0)) -> 3 | H7: =MAX(1,ROUNDUP(Volumi!I39*(1-Parametri!$B$16)*Parametri!$B$13/Parametri!$B$14,0)) -> 2
A8: 10-11 | B8: =MAX(1,ROUNDUP(Volumi!C40*(1-Parametri!$B$16)*Parametri!$B$13/Parametri!$B$14,0)) -> 2 | C8: =MAX(1,ROUNDUP(Volumi!D40*(1-Parametri!$B$16)*Parametri!$B$13/Parametri!$B$14,0)) -> 2 | D8: =MAX(1,ROUNDUP(Volumi!E40*(1-Parametri!$B$16)*Parametri!$B$13/Parametri!$B$14,0)) -> 2 | E8: =MAX(1,ROUNDUP(Volumi!F40*(1-Parametri!$B$16)*Parametri!$B$13/Parametri!$B$14,0)) -> 2 | F8: =MAX(1,ROUNDUP(Volumi!G40*(1-Parametri!$B$16)*Parametri!$B$13/Parametri!$B$14,0)) -> 3 | G8: =MAX(1,ROUNDUP(Volumi!H40*(1-Parametri!$B$16)*Parametri!$B$13/Parametri!$B$14,0)) -> 3 | H8: =MAX(1,ROUNDUP(Volumi!I40*(1-Parametri!$B$16)*Parametri!$B$13/Parametri!$B$14,0)) -> 2
A9: 11-12 | B9: =MAX(1,ROUNDUP(Volumi!C41*(1-Parametri!$B$16)*Parametri!$B$13/Parametri!$B$14,0)) -> 3 | C9: =MAX(1,ROUNDUP(Volumi!D41*(1-Parametri!$B$16)*Parametri!$B$13/Parametri!$B$14,0)) -> 2 | D9: =MAX(1,ROUNDUP(Volumi!E41*(1-Parametri!$B$16)*Parametri!$B$13/Parametri!$B$14,0)) -> 2 | E9: =MAX(1,ROUNDUP(Volumi!F41*(1-Parametri!$B$16)*Parametri!$B$13/Parametri!$B$14,0)) -> 3 | F9: =MAX(1,ROUNDUP(Volumi!G41*(1-Parametri!$B$16)*Parametri!$B$13/Parametri!$B$14,0)) -> 3 | G9: =MAX(1,ROUNDUP(Volumi!H41*(1-Parametri!$B$16)*Parametri!$B$13/Parametri!$B$14,0)) -> 3 | H9: =MAX(1,ROUNDUP(Volumi!I41*(1-Parametri!$B$16)*Parametri!$B$13/Parametri!$B$14,0)) -> 2
A10: 12-13 | B10: =MAX(1,ROUNDUP(Volumi!C42*(1-Parametri!$B$16)*Parametri!$B$13/Parametri!$B$14,0)) -> 2 | C10: =MAX(1,ROUNDUP(Volumi!D42*(1-Parametri!$B$16)*Parametri!$B$13/Parametri!$B$14,0)) -> 2 | D10: =MAX(1,ROUNDUP(Volumi!E42*(1-Parametri!$B$16)*Parametri!$B$13/Parametri!$B$14,0)) -> 2 | E10: =MAX(1,ROUNDUP(Volumi!F42*(1-Parametri!$B$16)*Parametri!$B$13/Parametri!$B$14,0)) -> 2 | F10: =MAX(1,ROUNDUP(Volumi!G42*(1-Parametri!$B$16)*Parametri!$B$13/Parametri!$B$14,0)) -> 2 | G10: =MAX(1,ROUNDUP(Volumi!H42*(1-Parametri!$B$16)*Parametri!$B$13/Parametri!$B$14,0)) -> 3 | H10: =MAX(1,ROUNDUP(Volumi!I42*(1-Parametri!$B$16)*Parametri!$B$13/Parametri!$B$14,0)) -> 2
A11: 13-14 | B11: =MAX(1,ROUNDUP(Volumi!C43*(1-Parametri!$B$16)*Parametri!$B$13/Parametri!$B$14,0)) -> 2 | C11: =MAX(1,ROUNDUP(Volumi!D43*(1-Parametri!$B$16)*Parametri!$B$13/Parametri!$B$14,0)) -> 2 | D11: =MAX(1,ROUNDUP(Volumi!E43*(1-Parametri!$B$16)*Parametri!$B$13/Parametri!$B$14,0)) -> 2 | E11: =MAX(1,ROUNDUP(Volumi!F43*(1-Parametri!$B$16)*Parametri!$B$13/Parametri!$B$14,0)) -> 2 | F11: =MAX(1,ROUNDUP(Volumi!G43*(1-Parametri!$B$16)*Parametri!$B$13/Parametri!$B$14,0)) -> 2 | G11: =MAX(1,ROUNDUP(Volumi!H43*(1-Parametri!$B$16)*Parametri!$B$13/Parametri!$B$14,0)) -> 3 | H11: =MAX(1,ROUNDUP(Volumi!I43*(1-Parametri!$B$16)*Parametri!$B$13/Parametri!$B$14,0)) -> 2
A12: 14-15 | B12: =MAX(1,ROUNDUP(Volumi!C44*(1-Parametri!$B$16)*Parametri!$B$13/Parametri!$B$14,0)) -> 2 | C12: =MAX(1,ROUNDUP(Volumi!D44*(1-Parametri!$B$16)*Parametri!$B$13/Parametri!$B$14,0)) -> 2 | D12: =MAX(1,ROUNDUP(Volumi!E44*(1-Parametri!$B$16)*Parametri!$B$13/Parametri!$B$14,0)) -> 2 | E12: =MAX(1,ROUNDUP(Volumi!F44*(1-Parametri!$B$16)*Parametri!$B$13/Parametri!$B$14,0)) -> 2 | F12: =MAX(1,ROUNDUP(Volumi!G44*(1-Parametri!$B$16)*Parametri!$B$13/Parametri!$B$14,0)) -> 2 | G12: =MAX(1,ROUNDUP(Volumi!H44*(1-Parametri!$B$16)*Parametri!$B$13/Parametri!$B$14,0)) -> 2 | H12: =MAX(1,ROUNDUP(Volumi!I44*(1-Parametri!$B$16)*Parametri!$B$13/Parametri!$B$14,0)) -> 2
A13: 15-16 | B13: =MAX(1,ROUNDUP(Volumi!C45*(1-Parametri!$B$16)*Parametri!$B$13/Parametri!$B$14,0)) -> 2 | C13: =MAX(1,ROUNDUP(Volumi!D45*(1-Parametri!$B$16)*Parametri!$B$13/Parametri!$B$14,0)) -> 2 | D13: =MAX(1,ROUNDUP(Volumi!E45*(1-Parametri!$B$16)*Parametri!$B$13/Parametri!$B$14,0)) -> 2 | E13: =MAX(1,ROUNDUP(Volumi!F45*(1-Parametri!$B$16)*Parametri!$B$13/Parametri!$B$14,0)) -> 2 | F13: =MAX(1,ROUNDUP(Volumi!G45*(1-Parametri!$B$16)*Parametri!$B$13/Parametri!$B$14,0)) -> 2 | G13: =MAX(1,ROUNDUP(Volumi!H45*(1-Parametri!$B$16)*Parametri!$B$13/Parametri!$B$14,0)) -> 2 | H13: =MAX(1,ROUNDUP(Volumi!I45*(1-Parametri!$B$16)*Parametri!$B$13/Parametri!$B$14,0)) -> 2
A14: 16-17 | B14: =MAX(1,ROUNDUP(Volumi!C46*(1-Parametri!$B$16)*Parametri!$B$13/Parametri!$B$14,0)) -> 2 | C14: =MAX(1,ROUNDUP(Volumi!D46*(1-Parametri!$B$16)*Parametri!$B$13/Parametri!$B$14,0)) -> 2 | D14: =MAX(1,ROUNDUP(Volumi!E46*(1-Parametri!$B$16)*Parametri!$B$13/Parametri!$B$14,0)) -> 2 | E14: =MAX(1,ROUNDUP(Volumi!F46*(1-Parametri!$B$16)*Parametri!$B$13/Parametri!$B$14,0)) -> 2 | F14: =MAX(1,ROUNDUP(Volumi!G46*(1-Parametri!$B$16)*Parametri!$B$13/Parametri!$B$14,0)) -> 2 | G14: =MAX(1,ROUNDUP(Volumi!H46*(1-Parametri!$B$16)*Parametri!$B$13/Parametri!$B$14,0)) -> 3 | H14: =MAX(1,ROUNDUP(Volumi!I46*(1-Parametri!$B$16)*Parametri!$B$13/Parametri!$B$14,0)) -> 2
A15: 17-18 | B15: =MAX(1,ROUNDUP(Volumi!C47*(1-Parametri!$B$16)*Parametri!$B$13/Parametri!$B$14,0)) -> 2 | C15: =MAX(1,ROUNDUP(Volumi!D47*(1-Parametri!$B$16)*Parametri!$B$13/Parametri!$B$14,0)) -> 2 | D15: =MAX(1,ROUNDUP(Volumi!E47*(1-Parametri!$B$16)*Parametri!$B$13/Parametri!$B$14,0)) -> 2 | E15: =MAX(1,ROUNDUP(Volumi!F47*(1-Parametri!$B$16)*Parametri!$B$13/Parametri!$B$14,0)) -> 2 | F15: =MAX(1,ROUNDUP(Volumi!G47*(1-Parametri!$B$16)*Parametri!$B$13/Parametri!$B$14,0)) -> 3 | G15: =MAX(1,ROUNDUP(Volumi!H47*(1-Parametri!$B$16)*Parametri!$B$13/Parametri!$B$14,0)) -> 3 | H15: =MAX(1,ROUNDUP(Volumi!I47*(1-Parametri!$B$16)*Parametri!$B$13/Parametri!$B$14,0)) -> 2
A16: 18-19 | B16: =MAX(1,ROUNDUP(Volumi!C48*(1-Parametri!$B$16)*Parametri!$B$13/Parametri!$B$14,0)) -> 3 | C16: =MAX(1,ROUNDUP(Volumi!D48*(1-Parametri!$B$16)*Parametri!$B$13/Parametri!$B$14,0)) -> 2 | D16: =MAX(1,ROUNDUP(Volumi!E48*(1-Parametri!$B$16)*Parametri!$B$13/Parametri!$B$14,0)) -> 2 | E16: =MAX(1,ROUNDUP(Volumi!F48*(1-Parametri!$B$16)*Parametri!$B$13/Parametri!$B$14,0)) -> 3 | F16: =MAX(1,ROUNDUP(Volumi!G48*(1-Parametri!$B$16)*Parametri!$B$13/Parametri!$B$14,0)) -> 3 | G16: =MAX(1,ROUNDUP(Volumi!H48*(1-Parametri!$B$16)*Parametri!$B$13/Parametri!$B$14,0)) -> 3 | H16: =MAX(1,ROUNDUP(Volumi!I48*(1-Parametri!$B$16)*Parametri!$B$13/Parametri!$B$14,0)) -> 2
A17: 19-20 | B17: =MAX(1,ROUNDUP(Volumi!C49*(1-Parametri!$B$16)*Parametri!$B$13/Parametri!$B$14,0)) -> 2 | C17: =MAX(1,ROUNDUP(Volumi!D49*(1-Parametri!$B$16)*Parametri!$B$13/Parametri!$B$14,0)) -> 2 | D17: =MAX(1,ROUNDUP(Volumi!E49*(1-Parametri!$B$16)*Parametri!$B$13/Parametri!$B$14,0)) -> 2 | E17: =MAX(1,ROUNDUP(Volumi!F49*(1-Parametri!$B$16)*Parametri!$B$13/Parametri!$B$14,0)) -> 2 | F17: =MAX(1,ROUNDUP(Volumi!G49*(1-Parametri!$B$16)*Parametri!$B$13/Parametri!$B$14,0)) -> 2 | G17: =MAX(1,ROUNDUP(Volumi!H49*(1-Parametri!$B$16)*Parametri!$B$13/Parametri!$B$14,0)) -> 3 | H17: =MAX(1,ROUNDUP(Volumi!I49*(1-Parametri!$B$16)*Parametri!$B$13/Parametri!$B$14,0)) -> 2
A18: 20-21 | B18: =MAX(1,ROUNDUP(Volumi!C50*(1-Parametri!$B$16)*Parametri!$B$13/Parametri!$B$14,0)) -> 1 | C18: =MAX(1,ROUNDUP(Volumi!D50*(1-Parametri!$B$16)*Parametri!$B$13/Parametri!$B$14,0)) -> 1 | D18: =MAX(1,ROUNDUP(Volumi!E50*(1-Parametri!$B$16)*Parametri!$B$13/Parametri!$B$14,0)) -> 1 | E18: =MAX(1,ROUNDUP(Volumi!F50*(1-Parametri!$B$16)*Parametri!$B$13/Parametri!$B$14,0)) -> 1 | F18: =MAX(1,ROUNDUP(Volumi!G50*(1-Parametri!$B$16)*Parametri!$B$13/Parametri!$B$14,0)) -> 1 | G18: =MAX(1,ROUNDUP(Volumi!H50*(1-Parametri!$B$16)*Parametri!$B$13/Parametri!$B$14,0)) -> 2 | H18: =MAX(1,ROUNDUP(Volumi!I50*(1-Parametri!$B$16)*Parametri!$B$13/Parametri!$B$14,0)) -> 1
A19: Ore barriera richieste | B19: =SUM(B6:B18) -> 27 | C19: =SUM(C6:C18) -> 24 | D19: =SUM(D6:D18) -> 24 | E19: =SUM(E6:E18) -> 27 | F19: =SUM(F6:F18) -> 29 | G19: =SUM(G6:G18) -> 35 | H19: =SUM(H6:H18) -> 24 | I19: =SUM(B19:H19) -> 190
A20: Casse max in contemporanea | B20: =MAX(B6:B18) -> 3 | C20: =MAX(C6:C18) -> 2 | D20: =MAX(D6:D18) -> 2 | E20: =MAX(E6:E18) -> 3 | F20: =MAX(F6:F18) -> 3 | G20: =MAX(G6:G18) -> 3 | H20: =MAX(H6:H18) -> 2 | I20: =MAX(B20:H20) -> 3
A21: Verifica vs casse disponibili | B21: =IF(B20<=Parametri!$B$18,"OK","OLTRE") -> OK | C21: =IF(C20<=Parametri!$B$18,"OK","OLTRE") -> OK | D21: =IF(D20<=Parametri!$B$18,"OK","OLTRE") -> OK | E21: =IF(E20<=Parametri!$B$18,"OK","OLTRE") -> OK | F21: =IF(F20<=Parametri!$B$18,"OK","OLTRE") -> OK | G21: =IF(G20<=Parametri!$B$18,"OK","OLTRE") -> OK | H21: =IF(H20<=Parametri!$B$18,"OK","OLTRE") -> OK
A23: PRESIDIO SCO · 6 casse automatiche, 1 addetto quando attive
A24: Ore di attivazione SCO al giorno | B24: 10 | C24: 9 | D24: 9 | E24: 10 | F24: 10 | G24: 10 | H24: 10 | I24: =SUM(B24:H24) -> 68
A25: Ore presidio SCO richieste | B25: =B24*Parametri!$B$17 -> 10 | C25: =C24*Parametri!$B$17 -> 9 | D25: =D24*Parametri!$B$17 -> 9 | E25: =E24*Parametri!$B$17 -> 10 | F25: =F24*Parametri!$B$17 -> 10 | G25: =G24*Parametri!$B$17 -> 10 | H25: =H24*Parametri!$B$17 -> 10 | I25: =SUM(B25:H25) -> 68
A27: Totale ore front-end (barriera + SCO) | B27: =B19+B25 -> 37 | C27: =C19+C25 -> 33 | D27: =D19+D25 -> 33 | E27: =E19+E25 -> 37 | F27: =F19+F25 -> 39 | G27: =G19+G25 -> 45 | H27: =H19+H25 -> 34 | I27: =SUM(B27:H27) -> 258

Sheet OreRichieste
A1: ORE RICHIESTE PER ATTIVITA E GIORNO · motore del modello
A2: Staff polivalente: le ore sono per attivita, chiunque puo coprirle.
A3: Attivita | B3: Lun | C3: Mar | D3: Mer | E3: Gio | F3: Ven | G3: Sab | H3: Dom | I3: Tot
A4: Controllo scorte e ordini merce | B4: 1.5 | C4: 1.5 | D4: 1.5 | E4: 1.5 | F4: 1.5 | G4: 1.5 | H4: 1.5 | I4: =SUM(B4:H4) -> 10.5
A5: Rifornimento FV | B5: =Volumi!B26*Parametri!$F$22/60 -> 4.0369333 | C5: =Volumi!C26*Parametri!$F$22/60 -> 3.7128 | D5: =Volumi!D26*Parametri!$F$22/60 -> 3.6538667 | E5: =Volumi!E26*Parametri!$F$22/60 -> 3.978 | F5: =Volumi!F26*Parametri!$F$22/60 -> 4.42 | G5: =Volumi!G26*Parametri!$F$22/60 -> 5.8344 | H5: =Volumi!H26*Parametri!$F$22/60 -> 3.8306667 | I5: =SUM(B5:H5) -> 29.466667
A6: BAKE: cottura ed esposizione | B6: =Volumi!B27*Parametri!$F$23/60 -> 6.6764667 | C6: =Volumi!C27*Parametri!$F$23/60 -> 6.1404 | D6: =Volumi!D27*Parametri!$F$23/60 -> 6.0429333 | E6: =Volumi!E27*Parametri!$F$23/60 -> 6.579 | F6: =Volumi!F27*Parametri!$F$23/60 -> 7.31 | G6: =Volumi!G27*Parametri!$F$23/60 -> 9.6492 | H6: =Volumi!H27*Parametri!$F$23/60 -> 6.3353333 | I6: =SUM(B6:H6) -> 48.733333
A7: Rifornimento CARNE | B7: =Volumi!B28*Parametri!$F$24/60 -> 1.1607046 | C7: =Volumi!C28*Parametri!$F$24/60 -> 1.0675093 | D7: =Volumi!D28*Parametri!$F$24/60 -> 1.0505647 | E7: =Volumi!E28*Parametri!$F$24/60 -> 1.14376 | F7: =Volumi!F28*Parametri!$F$24/60 -> 1.2708444 | G7: =Volumi!G28*Parametri!$F$24/60 -> 1.6775147 | H7: =Volumi!H28*Parametri!$F$24/60 -> 1.1013985 | I7: =SUM(B7:H7) -> 8.4722963
A8: Rifornimento SECCHI | B8: =Volumi!B29*Parametri!$F$25/60 -> 6.7712755 | C8: =Volumi!C29*Parametri!$F$25/60 -> 6.2275965 | D8: =Volumi!D29*Parametri!$F$25/60 -> 6.1287457 | E8: =Volumi!E29*Parametri!$F$25/60 -> 6.6724248 | F8: =Volumi!F29*Parametri!$F$25/60 -> 7.4138053 | G8: =Volumi!G29*Parametri!$F$25/60 -> 9.786223 | H8: =Volumi!H29*Parametri!$F$25/60 -> 6.4252979 | I8: =SUM(B8:H8) -> 49.425369
A9: Rifornimento SURGELATI | B9: =Volumi!B30*Parametri!$F$26/60 -> 1.3982037 | C9: =Volumi!C30*Parametri!$F$26/60 -> 1.2859392 | D9: =Volumi!D30*Parametri!$F$26/60 -> 1.2655275 | E9: =Volumi!E30*Parametri!$F$26/60 -> 1.377792 | F9: =Volumi!F30*Parametri!$F$26/60 -> 1.53088 | G9: =Volumi!G30*Parametri!$F$26/60 -> 2.0207616 | H9: =Volumi!H30*Parametri!$F$26/60 -> 1.3267627 | I9: =SUM(B9:H9) -> 10.205867
A10: Rifornimento FRESCHI | B10: =Volumi!B31*Parametri!$F$27/60 -> 3.1623272 | C10: =Volumi!C31*Parametri!$F$27/60 -> 2.9084177 | D10: =Volumi!D31*Parametri!$F$27/60 -> 2.8622524 | E10: =Volumi!E31*Parametri!$F$27/60 -> 3.1161619 | F10: =Volumi!F31*Parametri!$F$27/60 -> 3.4624021 | G10: =Volumi!G31*Parametri!$F$27/60 -> 4.5703707 | H10: =Volumi!H31*Parametri!$F$27/60 -> 3.0007485 | I10: =SUM(B10:H10) -> 23.082681
A11: Allestimento PROMO FOOD | B11: =Volumi!B32*Parametri!$F$28/60 -> 0.51517051 | C11: =Volumi!C32*Parametri!$F$28/60 -> 0.47380645 | D11: =Volumi!D32*Parametri!$F$28/60 -> 0.46628571 | E11: =Volumi!E32*Parametri!$F$28/60 -> 0.50764977 | F11: =Volumi!F32*Parametri!$F$28/60 -> 0.5640553 | G11: =Volumi!G32*Parametri!$F$28/60 -> 0.744553 | H11: =Volumi!H32*Parametri!$F$28/60 -> 0.48884793 | I11: =SUM(B11:H11) -> 3.7603687
A12: Allestimento PROMO NF | B12: =Volumi!B33*Parametri!$F$29/60 -> 1.3178732 | C12: =Volumi!C33*Parametri!$F$29/60 -> 1.2120585 | D12: =Volumi!D33*Parametri!$F$29/60 -> 1.1928195 | E12: =Volumi!E33*Parametri!$F$29/60 -> 1.2986341 | F12: =Volumi!F33*Parametri!$F$29/60 -> 1.4429268 | G12: =Volumi!G33*Parametri!$F$29/60 -> 1.9046634 | H12: =Volumi!H33*Parametri!$F$29/60 -> 1.2505366 | I12: =SUM(B12:H12) -> 9.6195122
A13: Barriera casse | B13: =Casse!B19 -> 27 | C13: =Casse!C19 -> 24 | D13: =Casse!D19 -> 24 | E13: =Casse!E19 -> 27 | F13: =Casse!F19 -> 29 | G13: =Casse!G19 -> 35 | H13: =Casse!H19 -> 24 | I13: =SUM(B13:H13) -> 190
A14: Presidio SCO | B14: =Casse!B25 -> 10 | C14: =Casse!C25 -> 9 | D14: =Casse!D25 -> 9 | E14: =Casse!E25 -> 10 | F14: =Casse!F25 -> 10 | G14: =Casse!G25 -> 10 | H14: =Casse!H25 -> 10 | I14: =SUM(B14:H14) -> 68
A15: Attivita fisse giornaliere | B15: =Parametri!$B$44 -> 11.5 | C15: =Parametri!$B$44 -> 11.5 | D15: =Parametri!$B$44 -> 11.5 | E15: =Parametri!$B$44 -> 11.5 | F15: =Parametri!$B$44 -> 11.5 | G15: =Parametri!$B$44 -> 11.5 | H15: =Parametri!$B$44 -> 11.5 | I15: =SUM(B15:H15) -> 80.5
A16: Attivita settimanali | B16: =SUMIFS(Parametri!$B$48:$B$51,Parametri!$C$48:$C$51,B$3) -> 11 | C16: =SUMIFS(Parametri!$B$48:$B$51,Parametri!$C$48:$C$51,C$3) -> 0 | D16: =SUMIFS(Parametri!$B$48:$B$51,Parametri!$C$48:$C$51,D$3) -> 3 | E16: =SUMIFS(Parametri!$B$48:$B$51,Parametri!$C$48:$C$51,E$3) -> 8 | F16: =SUMIFS(Parametri!$B$48:$B$51,Parametri!$C$48:$C$51,F$3) -> 0 | G16: =SUMIFS(Parametri!$B$48:$B$51,Parametri!$C$48:$C$51,G$3) -> 0 | H16: =SUMIFS(Parametri!$B$48:$B$51,Parametri!$C$48:$C$51,H$3) -> 0 | I16: =SUM(B16:H16) -> 22
A17: Totale | B17: =SUM(B4:B16) -> 86.038955 | C17: =SUM(C4:C16) -> 69.028528 | D17: =SUM(D4:D16) -> 71.662996 | E17: =SUM(E4:E16) -> 82.673423 | F17: =SUM(F4:F16) -> 79.414914 | G17: =SUM(G4:G16) -> 94.187686 | H17: =SUM(H4:H16) -> 70.759592 | I17: =SUM(B17:H17) -> 553.76609

Sheet Organico
A1: ORE PIANIFICATE PER TURNO E GIORNO · dati dimostrativi
A2: Calcolato automaticamente dal foglio Turni: ore per fascia di inizio turno. Non serve inserire nulla qui.
A3: Turno | B3: Lun | C3: Mar | D3: Mer | E3: Gio | F3: Ven | G3: Sab | H3: Dom | I3: Tot
A4: Turno mattina (inizio prima delle 9:00) | B4: =SUMIFS(Turni!H$5:H$27,Turni!F$5:F$27,"<"&9/24) -> 38 | C4: =SUMIFS(Turni!K$5:K$27,Turni!I$5:I$27,"<"&9/24) -> 28.5 | D4: =SUMIFS(Turni!N$5:N$27,Turni!L$5:L$27,"<"&9/24) -> 34.5 | E4: =SUMIFS(Turni!Q$5:Q$27,Turni!O$5:O$27,"<"&9/24) -> 35.5 | F4: =SUMIFS(Turni!T$5:T$27,Turni!R$5:R$27,"<"&9/24) -> 34 | G4: =SUMIFS(Turni!W$5:W$27,Turni!U$5:U$27,"<"&9/24) -> 38.5 | H4: =SUMIFS(Turni!Z$5:Z$27,Turni!X$5:X$27,"<"&9/24) -> 37 | I4: =SUM(B4:H4) -> 246
A5: Turno centrale (inizio 9:00-12:59) | B5: =SUMIFS(Turni!H$5:H$27,Turni!F$5:F$27,">="&9/24,Turni!F$5:F$27,"<"&13/24) -> 16 | C5: =SUMIFS(Turni!K$5:K$27,Turni!I$5:I$27,">="&9/24,Turni!I$5:I$27,"<"&13/24) -> 16.5 | D5: =SUMIFS(Turni!N$5:N$27,Turni!L$5:L$27,">="&9/24,Turni!L$5:L$27,"<"&13/24) -> 11.5 | E5: =SUMIFS(Turni!Q$5:Q$27,Turni!O$5:O$27,">="&9/24,Turni!O$5:O$27,"<"&13/24) -> 14.5 | F5: =SUMIFS(Turni!T$5:T$27,Turni!R$5:R$27,">="&9/24,Turni!R$5:R$27,"<"&13/24) -> 19 | G5: =SUMIFS(Turni!W$5:W$27,Turni!U$5:U$27,">="&9/24,Turni!U$5:U$27,"<"&13/24) -> 26 | H5: =SUMIFS(Turni!Z$5:Z$27,Turni!X$5:X$27,">="&9/24,Turni!X$5:X$27,"<"&13/24) -> 5 | I5: =SUM(B5:H5) -> 108.5
A6: Turno pomeriggio e chiusura (inizio dalle 13:00) | B6: =SUMIFS(Turni!H$5:H$27,Turni!F$5:F$27,">="&13/24) -> 32 | C6: =SUMIFS(Turni!K$5:K$27,Turni!I$5:I$27,">="&13/24) -> 24 | D6: =SUMIFS(Turni!N$5:N$27,Turni!L$5:L$27,">="&13/24) -> 25.5 | E6: =SUMIFS(Turni!Q$5:Q$27,Turni!O$5:O$27,">="&13/24) -> 32.5 | F6: =SUMIFS(Turni!T$5:T$27,Turni!R$5:R$27,">="&13/24) -> 26 | G6: =SUMIFS(Turni!W$5:W$27,Turni!U$5:U$27,">="&13/24) -> 29.5 | H6: =SUMIFS(Turni!Z$5:Z$27,Turni!X$5:X$27,">="&13/24) -> 28.5 | I6: =SUM(B6:H6) -> 198
A7: Totale | B7: =SUM(B4:B6) -> 86 | C7: =SUM(C4:C6) -> 69 | D7: =SUM(D4:D6) -> 71.5 | E7: =SUM(E4:E6) -> 82.5 | F7: =SUM(F4:F6) -> 79 | G7: =SUM(G4:G6) -> 94 | H7: =SUM(H4:H6) -> 70.5 | I7: =SUM(I4:I6) -> 552.5
A9: Fonte: foglio Turni (orario generato). La Dashboard confronta queste ore con le ore richieste dal modello.

Sheet Grafici
B2: GRAFICI TURNI · copertura e buchi
B3: Grafici collegati con formule ai fogli Turni e Copertura: si aggiornano da soli quando modifichi un orario. Non modificare le celle grigie di questo foglio.
B5: 1 · Mappa settimanale dei buchi di copertura
B6: Ogni cella = persone mancanti (Richiesti - Presenti) in quella mezz'ora. Verde chiaro = coperto, rosso = scoperto. Fasce da 30 minuti, 05:30 -> 21:00.
B8: Giorno / ora | C8: =Copertura!$A$6 -> 0.22916667 | D8: =Copertura!$A$8 -> 0.25 | E8: =Copertura!$A$10 -> 0.27083333 | F8: =Copertura!$A$12 -> 0.29166667 | G8: =Copertura!$A$14 -> 0.3125 | H8: =Copertura!$A$16 -> 0.33333333 | I8: =Copertura!$A$18 -> 0.35416667 | J8: =Copertura!$A$20 -> 0.375 | K8: =Copertura!$A$22 -> 0.39583333 | L8: =Copertura!$A$24 -> 0.41666667 | M8: =Copertura!$A$26 -> 0.4375 | N8: =Copertura!$A$28 -> 0.45833333 | O8: =Copertura!$A$30 -> 0.47916667 | P8: =Copertura!$A$32 -> 0.5 | Q8: =Copertura!$A$34 -> 0.52083333 | R8: =Copertura!$A$36 -> 0.54166667 | S8: =Copertura!$A$38 -> 0.5625 | T8: =Copertura!$A$40 -> 0.58333333 | U8: =Copertura!$A$42 -> 0.60416667 | V8: =Copertura!$A$44 -> 0.625 | W8: =Copertura!$A$46 -> 0.64583333 | X8: =Copertura!$A$48 -> 0.66666667 | Y8: =Copertura!$A$50 -> 0.6875 | Z8: =Copertura!$A$52 -> 0.70833333 | AA8: =Copertura!$A$54 -> 0.72916667 | AB8: =Copertura!$A$56 -> 0.75 | AC8: =Copertura!$A$58 -> 0.77083333 | AD8: =Copertura!$A$60 -> 0.79166667 | AE8: =Copertura!$A$62 -> 0.8125 | AF8: =Copertura!$A$64 -> 0.83333333 | AG8: =Copertura!$A$66 -> 0.85416667 | AI8: h mancanti
B9: Lun | C9: =MAX(0,Copertura!$E$6-Copertura!$C$6,Copertura!$E$7-Copertura!$C$7) -> 0 | D9: =MAX(0,Copertura!$E$8-Copertura!$C$8,Copertura!$E$9-Copertura!$C$9) -> 0 | E9: =MAX(0,Copertura!$E$10-Copertura!$C$10,Copertura!$E$11-Copertura!$C$11) -> 0 | F9: =MAX(0,Copertura!$E$12-Copertura!$C$12,Copertura!$E$13-Copertura!$C$13) -> 0 | G9: =MAX(0,Copertura!$E$14-Copertura!$C$14,Copertura!$E$15-Copertura!$C$15) -> 0 | H9: =MAX(0,Copertura!$E$16-Copertura!$C$16,Copertura!$E$17-Copertura!$C$17) -> 0 | I9: =MAX(0,Copertura!$E$18-Copertura!$C$18,Copertura!$E$19-Copertura!$C$19) -> 0 | J9: =MAX(0,Copertura!$E$20-Copertura!$C$20,Copertura!$E$21-Copertura!$C$21) -> 0 | K9: =MAX(0,Copertura!$E$22-Copertura!$C$22,Copertura!$E$23-Copertura!$C$23) -> 0 | L9: =MAX(0,Copertura!$E$24-Copertura!$C$24,Copertura!$E$25-Copertura!$C$25) -> 0 | M9: =MAX(0,Copertura!$E$26-Copertura!$C$26,Copertura!$E$27-Copertura!$C$27) -> 0 | N9: =MAX(0,Copertura!$E$28-Copertura!$C$28,Copertura!$E$29-Copertura!$C$29) -> 0 | O9: =MAX(0,Copertura!$E$30-Copertura!$C$30,Copertura!$E$31-Copertura!$C$31) -> 1 | P9: =MAX(0,Copertura!$E$32-Copertura!$C$32,Copertura!$E$33-Copertura!$C$33) -> 0 | Q9: =MAX(0,Copertura!$E$34-Copertura!$C$34,Copertura!$E$35-Copertura!$C$35) -> 0 | R9: =MAX(0,Copertura!$E$36-Copertura!$C$36,Copertura!$E$37-Copertura!$C$37) -> 0 | S9: =MAX(0,Copertura!$E$38-Copertura!$C$38,Copertura!$E$39-Copertura!$C$39) -> 0 | T9: =MAX(0,Copertura!$E$40-Copertura!$C$40,Copertura!$E$41-Copertura!$C$41) -> 0 | U9: =MAX(0,Copertura!$E$42-Copertura!$C$42,Copertura!$E$43-Copertura!$C$43) -> 0 | V9: =MAX(0,Copertura!$E$44-Copertura!$C$44,Copertura!$E$45-Copertura!$C$45) -> 0 | W9: =MAX(0,Copertura!$E$46-Copertura!$C$46,Copertura!$E$47-Copertura!$C$47) -> 0 | X9: =MAX(0,Copertura!$E$48-Copertura!$C$48,Copertura!$E$49-Copertura!$C$49) -> 0 | Y9: =MAX(0,Copertura!$E$50-Copertura!$C$50,Copertura!$E$51-Copertura!$C$51) -> 0 | Z9: =MAX(0,Copertura!$E$52-Copertura!$C$52,Copertura!$E$53-Copertura!$C$53) -> 0 | AA9: =MAX(0,Copertura!$E$54-Copertura!$C$54,Copertura!$E$55-Copertura!$C$55) -> 0 | AB9: =MAX(0,Copertura!$E$56-Copertura!$C$56,Copertura!$E$57-Copertura!$C$57) -> 0 | AC9: =MAX(0,Copertura!$E$58-Copertura!$C$58,Copertura!$E$59-Copertura!$C$59) -> 0 | AD9: =MAX(0,Copertura!$E$60-Copertura!$C$60,Copertura!$E$61-Copertura!$C$61) -> 0 | AE9: =MAX(0,Copertura!$E$62-Copertura!$C$62,Copertura!$E$63-Copertura!$C$63) -> 0 | AF9: =MAX(0,Copertura!$E$64-Copertura!$C$64,Copertura!$E$65-Copertura!$C$65) -> 0 | AG9: =MAX(0,Copertura!$E$66-Copertura!$C$66,Copertura!$E$67-Copertura!$C$67) -> 0 | AI9: =SUMPRODUCT(--(Copertura!$E$6:$E$68>Copertura!$C$6:$C$68),(Copertura!$E$6:$E$68-Copertura!$C$6:$C$68))*0.25 -> 0.5
B10: Mar | C10: =MAX(0,Copertura!$I$6-Copertura!$G$6,Copertura!$I$7-Copertura!$G$7) -> 0 | D10: =MAX(0,Copertura!$I$8-Copertura!$G$8,Copertura!$I$9-Copertura!$G$9) -> 0 | E10: =MAX(0,Copertura!$I$10-Copertura!$G$10,Copertura!$I$11-Copertura!$G$11) -> 0 | F10: =MAX(0,Copertura!$I$12-Copertura!$G$12,Copertura!$I$13-Copertura!$G$13) -> 0 | G10: =MAX(0,Copertura!$I$14-Copertura!$G$14,Copertura!$I$15-Copertura!$G$15) -> 0 | H10: =MAX(0,Copertura!$I$16-Copertura!$G$16,Copertura!$I$17-Copertura!$G$17) -> 0 | I10: =MAX(0,Copertura!$I$18-Copertura!$G$18,Copertura!$I$19-Copertura!$G$19) -> 0 | J10: =MAX(0,Copertura!$I$20-Copertura!$G$20,Copertura!$I$21-Copertura!$G$21) -> 0 | K10: =MAX(0,Copertura!$I$22-Copertura!$G$22,Copertura!$I$23-Copertura!$G$23) -> 0 | L10: =MAX(0,Copertura!$I$24-Copertura!$G$24,Copertura!$I$25-Copertura!$G$25) -> 0 | M10: =MAX(0,Copertura!$I$26-Copertura!$G$26,Copertura!$I$27-Copertura!$G$27) -> 0 | N10: =MAX(0,Copertura!$I$28-Copertura!$G$28,Copertura!$I$29-Copertura!$G$29) -> 0 | O10: =MAX(0,Copertura!$I$30-Copertura!$G$30,Copertura!$I$31-Copertura!$G$31) -> 0 | P10: =MAX(0,Copertura!$I$32-Copertura!$G$32,Copertura!$I$33-Copertura!$G$33) -> 0 | Q10: =MAX(0,Copertura!$I$34-Copertura!$G$34,Copertura!$I$35-Copertura!$G$35) -> 0 | R10: =MAX(0,Copertura!$I$36-Copertura!$G$36,Copertura!$I$37-Copertura!$G$37) -> 0 | S10: =MAX(0,Copertura!$I$38-Copertura!$G$38,Copertura!$I$39-Copertura!$G$39) -> 0 | T10: =MAX(0,Copertura!$I$40-Copertura!$G$40,Copertura!$I$41-Copertura!$G$41) -> 0 | U10: =MAX(0,Copertura!$I$42-Copertura!$G$42,Copertura!$I$43-Copertura!$G$43) -> 0 | V10: =MAX(0,Copertura!$I$44-Copertura!$G$44,Copertura!$I$45-Copertura!$G$45) -> 1 | W10: =MAX(0,Copertura!$I$46-Copertura!$G$46,Copertura!$I$47-Copertura!$G$47) -> 0 | X10: =MAX(0,Copertura!$I$48-Copertura!$G$48,Copertura!$I$49-Copertura!$G$49) -> 0 | Y10: =MAX(0,Copertura!$I$50-Copertura!$G$50,Copertura!$I$51-Copertura!$G$51) -> 0 | Z10: =MAX(0,Copertura!$I$52-Copertura!$G$52,Copertura!$I$53-Copertura!$G$53) -> 0 | AA10: =MAX(0,Copertura!$I$54-Copertura!$G$54,Copertura!$I$55-Copertura!$G$55) -> 0 | AB10: =MAX(0,Copertura!$I$56-Copertura!$G$56,Copertura!$I$57-Copertura!$G$57) -> 0 | AC10: =MAX(0,Copertura!$I$58-Copertura!$G$58,Copertura!$I$59-Copertura!$G$59) -> 0 | AD10: =MAX(0,Copertura!$I$60-Copertura!$G$60,Copertura!$I$61-Copertura!$G$61) -> 0 | AE10: =MAX(0,Copertura!$I$62-Copertura!$G$62,Copertura!$I$63-Copertura!$G$63) -> 0 | AF10: =MAX(0,Copertura!$I$64-Copertura!$G$64,Copertura!$I$65-Copertura!$G$65) -> 0 | AG10: =MAX(0,Copertura!$I$66-Copertura!$G$66,Copertura!$I$67-Copertura!$G$67) -> 0 | AI10: =SUMPRODUCT(--(Copertura!$I$6:$I$68>Copertura!$G$6:$G$68),(Copertura!$I$6:$I$68-Copertura!$G$6:$G$68))*0.25 -> 0.25
B11: Mer | C11: =MAX(0,Copertura!$M$6-Copertura!$K$6,Copertura!$M$7-Copertura!$K$7) -> 0 | D11: =MAX(0,Copertura!$M$8-Copertura!$K$8,Copertura!$M$9-Copertura!$K$9) -> 0 | E11: =MAX(0,Copertura!$M$10-Copertura!$K$10,Copertura!$M$11-Copertura!$K$11) -> 0 | F11: =MAX(0,Copertura!$M$12-Copertura!$K$12,Copertura!$M$13-Copertura!$K$13) -> 0 | G11: =MAX(0,Copertura!$M$14-Copertura!$K$14,Copertura!$M$15-Copertura!$K$15) -> 0 | H11: =MAX(0,Copertura!$M$16-Copertura!$K$16,Copertura!$M$17-Copertura!$K$17) -> 0 | I11: =MAX(0,Copertura!$M$18-Copertura!$K$18,Copertura!$M$19-Copertura!$K$19) -> 0 | J11: =MAX(0,Copertura!$M$20-Copertura!$K$20,Copertura!$M$21-Copertura!$K$21) -> 0 | K11: =MAX(0,Copertura!$M$22-Copertura!$K$22,Copertura!$M$23-Copertura!$K$23) -> 0 | L11: =MAX(0,Copertura!$M$24-Copertura!$K$24,Copertura!$M$25-Copertura!$K$25) -> 0 | M11: =MAX(0,Copertura!$M$26-Copertura!$K$26,Copertura!$M$27-Copertura!$K$27) -> 0 | N11: =MAX(0,Copertura!$M$28-Copertura!$K$28,Copertura!$M$29-Copertura!$K$29) -> 0 | O11: =MAX(0,Copertura!$M$30-Copertura!$K$30,Copertura!$M$31-Copertura!$K$31) -> 0 | P11: =MAX(0,Copertura!$M$32-Copertura!$K$32,Copertura!$M$33-Copertura!$K$33) -> 0 | Q11: =MAX(0,Copertura!$M$34-Copertura!$K$34,Copertura!$M$35-Copertura!$K$35) -> 0 | R11: =MAX(0,Copertura!$M$36-Copertura!$K$36,Copertura!$M$37-Copertura!$K$37) -> 0 | S11: =MAX(0,Copertura!$M$38-Copertura!$K$38,Copertura!$M$39-Copertura!$K$39) -> 0 | T11: =MAX(0,Copertura!$M$40-Copertura!$K$40,Copertura!$M$41-Copertura!$K$41) -> 0 | U11: =MAX(0,Copertura!$M$42-Copertura!$K$42,Copertura!$M$43-Copertura!$K$43) -> 0 | V11: =MAX(0,Copertura!$M$44-Copertura!$K$44,Copertura!$M$45-Copertura!$K$45) -> 0 | W11: =MAX(0,Copertura!$M$46-Copertura!$K$46,Copertura!$M$47-Copertura!$K$47) -> 0 | X11: =MAX(0,Copertura!$M$48-Copertura!$K$48,Copertura!$M$49-Copertura!$K$49) -> 0 | Y11: =MAX(0,Copertura!$M$50-Copertura!$K$50,Copertura!$M$51-Copertura!$K$51) -> 0 | Z11: =MAX(0,Copertura!$M$52-Copertura!$K$52,Copertura!$M$53-Copertura!$K$53) -> 0 | AA11: =MAX(0,Copertura!$M$54-Copertura!$K$54,Copertura!$M$55-Copertura!$K$55) -> 0 | AB11: =MAX(0,Copertura!$M$56-Copertura!$K$56,Copertura!$M$57-Copertura!$K$57) -> 0 | AC11: =MAX(0,Copertura!$M$58-Copertura!$K$58,Copertura!$M$59-Copertura!$K$59) -> 0 | AD11: =MAX(0,Copertura!$M$60-Copertura!$K$60,Copertura!$M$61-Copertura!$K$61) -> 0 | AE11: =MAX(0,Copertura!$M$62-Copertura!$K$62,Copertura!$M$63-Copertura!$K$63) -> 0 | AF11: =MAX(0,Copertura!$M$64-Copertura!$K$64,Copertura!$M$65-Copertura!$K$65) -> 0 | AG11: =MAX(0,Copertura!$M$66-Copertura!$K$66,Copertura!$M$67-Copertura!$K$67) -> 0 | AI11: =SUMPRODUCT(--(Copertura!$M$6:$M$68>Copertura!$K$6:$K$68),(Copertura!$M$6:$M$68-Copertura!$K$6:$K$68))*0.25 -> 0
B12: Gio | C12: =MAX(0,Copertura!$Q$6-Copertura!$O$6,Copertura!$Q$7-Copertura!$O$7) -> 0 | D12: =MAX(0,Copertura!$Q$8-Copertura!$O$8,Copertura!$Q$9-Copertura!$O$9) -> 0 | E12: =MAX(0,Copertura!$Q$10-Copertura!$O$10,Copertura!$Q$11-Copertura!$O$11) -> 0 | F12: =MAX(0,Copertura!$Q$12-Copertura!$O$12,Copertura!$Q$13-Copertura!$O$13) -> 0 | G12: =MAX(0,Copertura!$Q$14-Copertura!$O$14,Copertura!$Q$15-Copertura!$O$15) -> 0 | H12: =MAX(0,Copertura!$Q$16-Copertura!$O$16,Copertura!$Q$17-Copertura!$O$17) -> 0 | I12: =MAX(0,Copertura!$Q$18-Copertura!$O$18,Copertura!$Q$19-Copertura!$O$19) -> 0 | J12: =MAX(0,Copertura!$Q$20-Copertura!$O$20,Copertura!$Q$21-Copertura!$O$21) -> 0 | K12: =MAX(0,Copertura!$Q$22-Copertura!$O$22,Copertura!$Q$23-Copertura!$O$23) -> 0 | L12: =MAX(0,Copertura!$Q$24-Copertura!$O$24,Copertura!$Q$25-Copertura!$O$25) -> 0 | M12: =MAX(0,Copertura!$Q$26-Copertura!$O$26,Copertura!$Q$27-Copertura!$O$27) -> 0 | N12: =MAX(0,Copertura!$Q$28-Copertura!$O$28,Copertura!$Q$29-Copertura!$O$29) -> 0 | O12: =MAX(0,Copertura!$Q$30-Copertura!$O$30,Copertura!$Q$31-Copertura!$O$31) -> 0 | P12: =MAX(0,Copertura!$Q$32-Copertura!$O$32,Copertura!$Q$33-Copertura!$O$33) -> 0 | Q12: =MAX(0,Copertura!$Q$34-Copertura!$O$34,Copertura!$Q$35-Copertura!$O$35) -> 0 | R12: =MAX(0,Copertura!$Q$36-Copertura!$O$36,Copertura!$Q$37-Copertura!$O$37) -> 0 | S12: =MAX(0,Copertura!$Q$38-Copertura!$O$38,Copertura!$Q$39-Copertura!$O$39) -> 0 | T12: =MAX(0,Copertura!$Q$40-Copertura!$O$40,Copertura!$Q$41-Copertura!$O$41) -> 0 | U12: =MAX(0,Copertura!$Q$42-Copertura!$O$42,Copertura!$Q$43-Copertura!$O$43) -> 0 | V12: =MAX(0,Copertura!$Q$44-Copertura!$O$44,Copertura!$Q$45-Copertura!$O$45) -> 0 | W12: =MAX(0,Copertura!$Q$46-Copertura!$O$46,Copertura!$Q$47-Copertura!$O$47) -> 0 | X12: =MAX(0,Copertura!$Q$48-Copertura!$O$48,Copertura!$Q$49-Copertura!$O$49) -> 0 | Y12: =MAX(0,Copertura!$Q$50-Copertura!$O$50,Copertura!$Q$51-Copertura!$O$51) -> 0 | Z12: =MAX(0,Copertura!$Q$52-Copertura!$O$52,Copertura!$Q$53-Copertura!$O$53) -> 0 | AA12: =MAX(0,Copertura!$Q$54-Copertura!$O$54,Copertura!$Q$55-Copertura!$O$55) -> 0 | AB12: =MAX(0,Copertura!$Q$56-Copertura!$O$56,Copertura!$Q$57-Copertura!$O$57) -> 0 | AC12: =MAX(0,Copertura!$Q$58-Copertura!$O$58,Copertura!$Q$59-Copertura!$O$59) -> 0 | AD12: =MAX(0,Copertura!$Q$60-Copertura!$O$60,Copertura!$Q$61-Copertura!$O$61) -> 0 | AE12: =MAX(0,Copertura!$Q$62-Copertura!$O$62,Copertura!$Q$63-Copertura!$O$63) -> 1 | AF12: =MAX(0,Copertura!$Q$64-Copertura!$O$64,Copertura!$Q$65-Copertura!$O$65) -> 0 | AG12: =MAX(0,Copertura!$Q$66-Copertura!$O$66,Copertura!$Q$67-Copertura!$O$67) -> 0 | AI12: =SUMPRODUCT(--(Copertura!$Q$6:$Q$68>Copertura!$O$6:$O$68),(Copertura!$Q$6:$Q$68-Copertura!$O$6:$O$68))*0.25 -> 0.5
B13: Ven | C13: =MAX(0,Copertura!$U$6-Copertura!$S$6,Copertura!$U$7-Copertura!$S$7) -> 0 | D13: =MAX(0,Copertura!$U$8-Copertura!$S$8,Copertura!$U$9-Copertura!$S$9) -> 0 | E13: =MAX(0,Copertura!$U$10-Copertura!$S$10,Copertura!$U$11-Copertura!$S$11) -> 0 | F13: =MAX(0,Copertura!$U$12-Copertura!$S$12,Copertura!$U$13-Copertura!$S$13) -> 0 | G13: =MAX(0,Copertura!$U$14-Copertura!$S$14,Copertura!$U$15-Copertura!$S$15) -> 0 | H13: =MAX(0,Copertura!$U$16-Copertura!$S$16,Copertura!$U$17-Copertura!$S$17) -> 0 | I13: =MAX(0,Copertura!$U$18-Copertura!$S$18,Copertura!$U$19-Copertura!$S$19) -> 0 | J13: =MAX(0,Copertura!$U$20-Copertura!$S$20,Copertura!$U$21-Copertura!$S$21) -> 0 | K13: =MAX(0,Copertura!$U$22-Copertura!$S$22,Copertura!$U$23-Copertura!$S$23) -> 0 | L13: =MAX(0,Copertura!$U$24-Copertura!$S$24,Copertura!$U$25-Copertura!$S$25) -> 0 | M13: =MAX(0,Copertura!$U$26-Copertura!$S$26,Copertura!$U$27-Copertura!$S$27) -> 0 | N13: =MAX(0,Copertura!$U$28-Copertura!$S$28,Copertura!$U$29-Copertura!$S$29) -> 0 | O13: =MAX(0,Copertura!$U$30-Copertura!$S$30,Copertura!$U$31-Copertura!$S$31) -> 0 | P13: =MAX(0,Copertura!$U$32-Copertura!$S$32,Copertura!$U$33-Copertura!$S$33) -> 0 | Q13: =MAX(0,Copertura!$U$34-Copertura!$S$34,Copertura!$U$35-Copertura!$S$35) -> 0 | R13: =MAX(0,Copertura!$U$36-Copertura!$S$36,Copertura!$U$37-Copertura!$S$37) -> 0 | S13: =MAX(0,Copertura!$U$38-Copertura!$S$38,Copertura!$U$39-Copertura!$S$39) -> 0 | T13: =MAX(0,Copertura!$U$40-Copertura!$S$40,Copertura!$U$41-Copertura!$S$41) -> 0 | U13: =MAX(0,Copertura!$U$42-Copertura!$S$42,Copertura!$U$43-Copertura!$S$43) -> 0 | V13: =MAX(0,Copertura!$U$44-Copertura!$S$44,Copertura!$U$45-Copertura!$S$45) -> 0 | W13: =MAX(0,Copertura!$U$46-Copertura!$S$46,Copertura!$U$47-Copertura!$S$47) -> 0 | X13: =MAX(0,Copertura!$U$48-Copertura!$S$48,Copertura!$U$49-Copertura!$S$49) -> 0 | Y13: =MAX(0,Copertura!$U$50-Copertura!$S$50,Copertura!$U$51-Copertura!$S$51) -> 0 | Z13: =MAX(0,Copertura!$U$52-Copertura!$S$52,Copertura!$U$53-Copertura!$S$53) -> 0 | AA13: =MAX(0,Copertura!$U$54-Copertura!$S$54,Copertura!$U$55-Copertura!$S$55) -> 0 | AB13: =MAX(0,Copertura!$U$56-Copertura!$S$56,Copertura!$U$57-Copertura!$S$57) -> 0 | AC13: =MAX(0,Copertura!$U$58-Copertura!$S$58,Copertura!$U$59-Copertura!$S$59) -> 1 | AD13: =MAX(0,Copertura!$U$60-Copertura!$S$60,Copertura!$U$61-Copertura!$S$61) -> 0 | AE13: =MAX(0,Copertura!$U$62-Copertura!$S$62,Copertura!$U$63-Copertura!$S$63) -> 0 | AF13: =MAX(0,Copertura!$U$64-Copertura!$S$64,Copertura!$U$65-Copertura!$S$65) -> 0 | AG13: =MAX(0,Copertura!$U$66-Copertura!$S$66,Copertura!$U$67-Copertura!$S$67) -> 0 | AI13: =SUMPRODUCT(--(Copertura!$U$6:$U$68>Copertura!$S$6:$S$68),(Copertura!$U$6:$U$68-Copertura!$S$6:$S$68))*0.25 -> 0.5
B14: Sab | C14: =MAX(0,Copertura!$Y$6-Copertura!$W$6,Copertura!$Y$7-Copertura!$W$7) -> 0 | D14: =MAX(0,Copertura!$Y$8-Copertura!$W$8,Copertura!$Y$9-Copertura!$W$9) -> 0 | E14: =MAX(0,Copertura!$Y$10-Copertura!$W$10,Copertura!$Y$11-Copertura!$W$11) -> 0 | F14: =MAX(0,Copertura!$Y$12-Copertura!$W$12,Copertura!$Y$13-Copertura!$W$13) -> 0 | G14: =MAX(0,Copertura!$Y$14-Copertura!$W$14,Copertura!$Y$15-Copertura!$W$15) -> 0 | H14: =MAX(0,Copertura!$Y$16-Copertura!$W$16,Copertura!$Y$17-Copertura!$W$17) -> 0 | I14: =MAX(0,Copertura!$Y$18-Copertura!$W$18,Copertura!$Y$19-Copertura!$W$19) -> 0 | J14: =MAX(0,Copertura!$Y$20-Copertura!$W$20,Copertura!$Y$21-Copertura!$W$21) -> 0 | K14: =MAX(0,Copertura!$Y$22-Copertura!$W$22,Copertura!$Y$23-Copertura!$W$23) -> 0 | L14: =MAX(0,Copertura!$Y$24-Copertura!$W$24,Copertura!$Y$25-Copertura!$W$25) -> 0 | M14: =MAX(0,Copertura!$Y$26-Copertura!$W$26,Copertura!$Y$27-Copertura!$W$27) -> 0 | N14: =MAX(0,Copertura!$Y$28-Copertura!$W$28,Copertura!$Y$29-Copertura!$W$29) -> 0 | O14: =MAX(0,Copertura!$Y$30-Copertura!$W$30,Copertura!$Y$31-Copertura!$W$31) -> 0 | P14: =MAX(0,Copertura!$Y$32-Copertura!$W$32,Copertura!$Y$33-Copertura!$W$33) -> 0 | Q14: =MAX(0,Copertura!$Y$34-Copertura!$W$34,Copertura!$Y$35-Copertura!$W$35) -> 0 | R14: =MAX(0,Copertura!$Y$36-Copertura!$W$36,Copertura!$Y$37-Copertura!$W$37) -> 0 | S14: =MAX(0,Copertura!$Y$38-Copertura!$W$38,Copertura!$Y$39-Copertura!$W$39) -> 0 | T14: =MAX(0,Copertura!$Y$40-Copertura!$W$40,Copertura!$Y$41-Copertura!$W$41) -> 0 | U14: =MAX(0,Copertura!$Y$42-Copertura!$W$42,Copertura!$Y$43-Copertura!$W$43) -> 0 | V14: =MAX(0,Copertura!$Y$44-Copertura!$W$44,Copertura!$Y$45-Copertura!$W$45) -> 0 | W14: =MAX(0,Copertura!$Y$46-Copertura!$W$46,Copertura!$Y$47-Copertura!$W$47) -> 0 | X14: =MAX(0,Copertura!$Y$48-Copertura!$W$48,Copertura!$Y$49-Copertura!$W$49) -> 0 | Y14: =MAX(0,Copertura!$Y$50-Copertura!$W$50,Copertura!$Y$51-Copertura!$W$51) -> 0 | Z14: =MAX(0,Copertura!$Y$52-Copertura!$W$52,Copertura!$Y$53-Copertura!$W$53) -> 0 | AA14: =MAX(0,Copertura!$Y$54-Copertura!$W$54,Copertura!$Y$55-Copertura!$W$55) -> 0 | AB14: =MAX(0,Copertura!$Y$56-Copertura!$W$56,Copertura!$Y$57-Copertura!$W$57) -> 0 | AC14: =MAX(0,Copertura!$Y$58-Copertura!$W$58,Copertura!$Y$59-Copertura!$W$59) -> 0 | AD14: =MAX(0,Copertura!$Y$60-Copertura!$W$60,Copertura!$Y$61-Copertura!$W$61) -> 0 | AE14: =MAX(0,Copertura!$Y$62-Copertura!$W$62,Copertura!$Y$63-Copertura!$W$63) -> 0 | AF14: =MAX(0,Copertura!$Y$64-Copertura!$W$64,Copertura!$Y$65-Copertura!$W$65) -> 0 | AG14: =MAX(0,Copertura!$Y$66-Copertura!$W$66,Copertura!$Y$67-Copertura!$W$67) -> 0 | AI14: =SUMPRODUCT(--(Copertura!$Y$6:$Y$68>Copertura!$W$6:$W$68),(Copertura!$Y$6:$Y$68-Copertura!$W$6:$W$68))*0.25 -> 0
B15: Dom | C15: =MAX(0,Copertura!$AC$6-Copertura!$AA$6,Copertura!$AC$7-Copertura!$AA$7) -> 0 | D15: =MAX(0,Copertura!$AC$8-Copertura!$AA$8,Copertura!$AC$9-Copertura!$AA$9) -> 0 | E15: =MAX(0,Copertura!$AC$10-Copertura!$AA$10,Copertura!$AC$11-Copertura!$AA$11) -> 0 | F15: =MAX(0,Copertura!$AC$12-Copertura!$AA$12,Copertura!$AC$13-Copertura!$AA$13) -> 0 | G15: =MAX(0,Copertura!$AC$14-Copertura!$AA$14,Copertura!$AC$15-Copertura!$AA$15) -> 0 | H15: =MAX(0,Copertura!$AC$16-Copertura!$AA$16,Copertura!$AC$17-Copertura!$AA$17) -> 0 | I15: =MAX(0,Copertura!$AC$18-Copertura!$AA$18,Copertura!$AC$19-Copertura!$AA$19) -> 0 | J15: =MAX(0,Copertura!$AC$20-Copertura!$AA$20,Copertura!$AC$21-Copertura!$AA$21) -> 0 | K15: =MAX(0,Copertura!$AC$22-Copertura!$AA$22,Copertura!$AC$23-Copertura!$AA$23) -> 0 | L15: =MAX(0,Copertura!$AC$24-Copertura!$AA$24,Copertura!$AC$25-Copertura!$AA$25) -> 0 | M15: =MAX(0,Copertura!$AC$26-Copertura!$AA$26,Copertura!$AC$27-Copertura!$AA$27) -> 0 | N15: =MAX(0,Copertura!$AC$28-Copertura!$AA$28,Copertura!$AC$29-Copertura!$AA$29) -> 0 | O15: =MAX(0,Copertura!$AC$30-Copertura!$AA$30,Copertura!$AC$31-Copertura!$AA$31) -> 0 | P15: =MAX(0,Copertura!$AC$32-Copertura!$AA$32,Copertura!$AC$33-Copertura!$AA$33) -> 0 | Q15: =MAX(0,Copertura!$AC$34-Copertura!$AA$34,Copertura!$AC$35-Copertura!$AA$35) -> 0 | R15: =MAX(0,Copertura!$AC$36-Copertura!$AA$36,Copertura!$AC$37-Copertura!$AA$37) -> 0 | S15: =MAX(0,Copertura!$AC$38-Copertura!$AA$38,Copertura!$AC$39-Copertura!$AA$39) -> 0 | T15: =MAX(0,Copertura!$AC$40-Copertura!$AA$40,Copertura!$AC$41-Copertura!$AA$41) -> 0 | U15: =MAX(0,Copertura!$AC$42-Copertura!$AA$42,Copertura!$AC$43-Copertura!$AA$43) -> 0 | V15: =MAX(0,Copertura!$AC$44-Copertura!$AA$44,Copertura!$AC$45-Copertura!$AA$45) -> 0 | W15: =MAX(0,Copertura!$AC$46-Copertura!$AA$46,Copertura!$AC$47-Copertura!$AA$47) -> 0 | X15: =MAX(0,Copertura!$AC$48-Copertura!$AA$48,Copertura!$AC$49-Copertura!$AA$49) -> 0 | Y15: =MAX(0,Copertura!$AC$50-Copertura!$AA$50,Copertura!$AC$51-Copertura!$AA$51) -> 0 | Z15: =MAX(0,Copertura!$AC$52-Copertura!$AA$52,Copertura!$AC$53-Copertura!$AA$53) -> 0 | AA15: =MAX(0,Copertura!$AC$54-Copertura!$AA$54,Copertura!$AC$55-Copertura!$AA$55) -> 0 | AB15: =MAX(0,Copertura!$AC$56-Copertura!$AA$56,Copertura!$AC$57-Copertura!$AA$57) -> 0 | AC15: =MAX(0,Copertura!$AC$58-Copertura!$AA$58,Copertura!$AC$59-Copertura!$AA$59) -> 0 | AD15: =MAX(0,Copertura!$AC$60-Copertura!$AA$60,Copertura!$AC$61-Copertura!$AA$61) -> 0 | AE15: =MAX(0,Copertura!$AC$62-Copertura!$AA$62,Copertura!$AC$63-Copertura!$AA$63) -> 0 | AF15: =MAX(0,Copertura!$AC$64-Copertura!$AA$64,Copertura!$AC$65-Copertura!$AA$65) -> 0 | AG15: =MAX(0,Copertura!$AC$66-Copertura!$AA$66,Copertura!$AC$67-Copertura!$AA$67) -> 0 | AI15: =SUMPRODUCT(--(Copertura!$AC$6:$AC$68>Copertura!$AA$6:$AA$68),(Copertura!$AC$6:$AC$68-Copertura!$AA$6:$AA$68))*0.25 -> 0
B19: 2 · Grafico del giorno
B20: Giorno selezionato: | C20: Dom | E20: <- scegli qui il giorno (menu a tendina). I due grafici sotto seguono la scelta.
B21: =MATCH($C$20,{"Lun","Mar","Mer","Gio","Ven","Sab","Dom"},0) -> 7
AN22: (tabelle di servizio dei grafici - non modificare)
AN23: Ora | AO23: Presenti | AP23: Richiesti | AR23: Dipendente | AS23: Inizio (h) | AT23: Durata (h)
AN24: =Copertura!$A$6 -> 0.22916667 | AO24: =CHOOSE($B$21,Copertura!C6,Copertura!G6,Copertura!K6,Copertura!O6,Copertura!S6,Copertura!W6,Copertura!AA6) -> 0 | AP24: =CHOOSE($B$21,Copertura!E6,Copertura!I6,Copertura!M6,Copertura!Q6,Copertura!U6,Copertura!Y6,Copertura!AC6) -> 0 | AR24: =Turni!$A$5 -> DE PICCOLI | AS24: =IF(ISNUMBER(CHOOSE($B$21,Turni!F5,Turni!I5,Turni!L5,Turni!O5,Turni!R5,Turni!U5,Turni!X5)),CHOOSE($B$21,Turni!F5,Turni!I5,Turni!L5,Turni!O5,Turni!R5,Turni!U5,Turni!X5)*24,0) -> 8 | AT24: =IF(AND(ISNUMBER(CHOOSE($B$21,Turni!F5,Turni!I5,Turni!L5,Turni!O5,Turni!R5,Turni!U5,Turni!X5)),ISNUMBER(CHOOSE($B$21,Turni!G5,Turni!J5,Turni!M5,Turni!P5,Turni!S5,Turni!V5,Turni!Y5))),(CHOOSE($B$21,Turni!G5,Turni!J5,Turni!M5,Turni!P5,Turni!S5,Turni!V5,Turni!Y5)-CHOOSE($B$21,Turni!F5,Turni!I5,Turni!L5,Turni!O5,Turni!R5,Turni!U5,Turni!X5))*24,0) -> 7.5
AN25: =Copertura!$A$7 -> 0.23958333 | AO25: =CHOOSE($B$21,Copertura!C7,Copertura!G7,Copertura!K7,Copertura!O7,Copertura!S7,Copertura!W7,Copertura!AA7) -> 0 | AP25: =CHOOSE($B$21,Copertura!E7,Copertura!I7,Copertura!M7,Copertura!Q7,Copertura!U7,Copertura!Y7,Copertura!AC7) -> 0 | AR25: =Turni!$A$6 -> DA PARE’ | AS25: =IF(ISNUMBER(CHOOSE($B$21,Turni!F6,Turni!I6,Turni!L6,Turni!O6,Turni!R6,Turni!U6,Turni!X6)),CHOOSE($B$21,Turni!F6,Turni!I6,Turni!L6,Turni!O6,Turni!R6,Turni!U6,Turni!X6)*24,0) -> 0 | AT25: =IF(AND(ISNUMBER(CHOOSE($B$21,Turni!F6,Turni!I6,Turni!L6,Turni!O6,Turni!R6,Turni!U6,Turni!X6)),ISNUMBER(CHOOSE($B$21,Turni!G6,Turni!J6,Turni!M6,Turni!P6,Turni!S6,Turni!V6,Turni!Y6))),(CHOOSE($B$21,Turni!G6,Turni!J6,Turni!M6,Turni!P6,Turni!S6,Turni!V6,Turni!Y6)-CHOOSE($B$21,Turni!F6,Turni!I6,Turni!L6,Turni!O6,Turni!R6,Turni!U6,Turni!X6))*24,0) -> 0
AM26: =Turni!$A$26 -> 0 | AN26: =Copertura!$A$8 -> 0.25 | AO26: =IF(ISNUMBER(CHOOSE($B$21,Turni!F26,Turni!I26,Turni!L26,Turni!O26,Turni!R26,Turni!U26,Turni!X26)),CHOOSE($B$21,Turni!F26,Turni!I26,Turni!L26,Turni!O26,Turni!R26,Turni!U26,Turni!X26)*24,0) -> 0 | AP26: =IF(AND(ISNUMBER(CHOOSE($B$21,Turni!F26,Turni!I26,Turni!L26,Turni!O26,Turni!R26,Turni!U26,Turni!X26)),ISNUMBER(CHOOSE($B$21,Turni!G26,Turni!J26,Turni!M26,Turni!P26,Turni!S26,Turni!V26,Turni!Y26))),(CHOOSE($B$21,Turni!G26,Turni!J26,Turni!M26,Turni!P26,Turni!S26,Turni!V26,Turni!Y26)-CHOOSE($B$21,Turni!F26,Turni!I26,Turni!L26,Turni!O26,Turni!R26,Turni!U26,Turni!X26))*24,0) -> 0 | AR26: =Turni!$A$7 -> DE PELLEGRIN | AS26: =IF(ISNUMBER(CHOOSE($B$21,Turni!F7,Turni!I7,Turni!L7,Turni!O7,Turni!R7,Turni!U7,Turni!X7)),CHOOSE($B$21,Turni!F7,Turni!I7,Turni!L7,Turni!O7,Turni!R7,Turni!U7,Turni!X7)*24,0) -> 0 | AT26: =IF(AND(ISNUMBER(CHOOSE($B$21,Turni!F7,Turni!I7,Turni!L7,Turni!O7,Turni!R7,Turni!U7,Turni!X7)),ISNUMBER(CHOOSE($B$21,Turni!G7,Turni!J7,Turni!M7,Turni!P7,Turni!S7,Turni!V7,Turni!Y7))),(CHOOSE($B$21,Turni!G7,Turni!J7,Turni!M7,Turni!P7,Turni!S7,Turni!V7,Turni!Y7)-CHOOSE($B$21,Turni!F7,Turni!I7,Turni!L7,Turni!O7,Turni!R7,Turni!U7,Turni!X7))*24,0) -> 0
AM27: =Turni!$A$27 -> Totale | AN27: =Copertura!$A$9 -> 0.26041667 | AO27: =IF(ISNUMBER(CHOOSE($B$21,Turni!F27,Turni!I27,Turni!L27,Turni!O27,Turni!R27,Turni!U27,Turni!X27)),CHOOSE($B$21,Turni!F27,Turni!I27,Turni!L27,Turni!O27,Turni!R27,Turni!U27,Turni!X27)*24,0) -> 0 | AP27: =IF(AND(ISNUMBER(CHOOSE($B$21,Turni!F27,Turni!I27,Turni!L27,Turni!O27,Turni!R27,Turni!U27,Turni!X27)),ISNUMBER(CHOOSE($B$21,Turni!G27,Turni!J27,Turni!M27,Turni!P27,Turni!S27,Turni!V27,Turni!Y27))),(CHOOSE($B$21,Turni!G27,Turni!J27,Turni!M27,Turni!P27,Turni!S27,Turni!V27,Turni!Y27)-CHOOSE($B$21,Turni!F27,Turni!I27,Turni!L27,Turni!O27,Turni!R27,Turni!U27,Turni!X27))*24,0) -> 0 | AR27: =Turni!$A$8 -> DUBON | AS27: =IF(ISNUMBER(CHOOSE($B$21,Turni!F8,Turni!I8,Turni!L8,Turni!O8,Turni!R8,Turni!U8,Turni!X8)),CHOOSE($B$21,Turni!F8,Turni!I8,Turni!L8,Turni!O8,Turni!R8,Turni!U8,Turni!X8)*24,0) -> 14.25 | AT27: =IF(AND(ISNUMBER(CHOOSE($B$21,Turni!F8,Turni!I8,Turni!L8,Turni!O8,Turni!R8,Turni!U8,Turni!X8)),ISNUMBER(CHOOSE($B$21,Turni!G8,Turni!J8,Turni!M8,Turni!P8,Turni!S8,Turni!V8,Turni!Y8))),(CHOOSE($B$21,Turni!G8,Turni!J8,Turni!M8,Turni!P8,Turni!S8,Turni!V8,Turni!Y8)-CHOOSE($B$21,Turni!F8,Turni!I8,Turni!L8,Turni!O8,Turni!R8,Turni!U8,Turni!X8))*24,0) -> 7
AN28: =Copertura!$A$10 -> 0.27083333 | AO28: =CHOOSE($B$21,Copertura!C10,Copertura!G10,Copertura!K10,Copertura!O10,Copertura!S10,Copertura!W10,Copertura!AA10) -> 4 | AP28: =CHOOSE($B$21,Copertura!E10,Copertura!I10,Copertura!M10,Copertura!Q10,Copertura!U10,Copertura!Y10,Copertura!AC10) -> 4 | AR28: =Turni!$A$9 -> MUNERATI | AS28: =IF(ISNUMBER(CHOOSE($B$21,Turni!F9,Turni!I9,Turni!L9,Turni!O9,Turni!R9,Turni!U9,Turni!X9)),CHOOSE($B$21,Turni!F9,Turni!I9,Turni!L9,Turni!O9,Turni!R9,Turni!U9,Turni!X9)*24,0) -> 0 | AT28: =IF(AND(ISNUMBER(CHOOSE($B$21,Turni!F9,Turni!I9,Turni!L9,Turni!O9,Turni!R9,Turni!U9,Turni!X9)),ISNUMBER(CHOOSE($B$21,Turni!G9,Turni!J9,Turni!M9,Turni!P9,Turni!S9,Turni!V9,Turni!Y9))),(CHOOSE($B$21,Turni!G9,Turni!J9,Turni!M9,Turni!P9,Turni!S9,Turni!V9,Turni!Y9)-CHOOSE($B$21,Turni!F9,Turni!I9,Turni!L9,Turni!O9,Turni!R9,Turni!U9,Turni!X9))*24,0) -> 0
AN29: =Copertura!$A$11 -> 0.28125 | AO29: =CHOOSE($B$21,Copertura!C11,Copertura!G11,Copertura!K11,Copertura!O11,Copertura!S11,Copertura!W11,Copertura!AA11) -> 4 | AP29: =CHOOSE($B$21,Copertura!E11,Copertura!I11,Copertura!M11,Copertura!Q11,Copertura!U11,Copertura!Y11,Copertura!AC11) -> 4 | AR29: =Turni!$A$10 -> SEGAT | AS29: =IF(ISNUMBER(CHOOSE($B$21,Turni!F10,Turni!I10,Turni!L10,Turni!O10,Turni!R10,Turni!U10,Turni!X10)),CHOOSE($B$21,Turni!F10,Turni!I10,Turni!L10,Turni!O10,Turni!R10,Turni!U10,Turni!X10)*24,0) -> 6 | AT29: =IF(AND(ISNUMBER(CHOOSE($B$21,Turni!F10,Turni!I10,Turni!L10,Turni!O10,Turni!R10,Turni!U10,Turni!X10)),ISNUMBER(CHOOSE($B$21,Turni!G10,Turni!J10,Turni!M10,Turni!P10,Turni!S10,Turni!V10,Turni!Y10))),(CHOOSE($B$21,Turni!G10,Turni!J10,Turni!M10,Turni!P10,Turni!S10,Turni!V10,Turni!Y10)-CHOOSE($B$21,Turni!F10,Turni!I10,Turni!L10,Turni!O10,Turni!R10,Turni!U10,Turni!X10))*24,0) -> 6
AN30: =Copertura!$A$12 -> 0.29166667 | AO30: =CHOOSE($B$21,Copertura!C12,Copertura!G12,Copertura!K12,Copertura!O12,Copertura!S12,Copertura!W12,Copertura!AA12) -> 4 | AP30: =CHOOSE($B$21,Copertura!E12,Copertura!I12,Copertura!M12,Copertura!Q12,Copertura!U12,Copertura!Y12,Copertura!AC12) -> 4 | AR30: =Turni!$A$11 -> ANDREOLI | AS30: =IF(ISNUMBER(CHOOSE($B$21,Turni!F11,Turni!I11,Turni!L11,Turni!O11,Turni!R11,Turni!U11,Turni!X11)),CHOOSE($B$21,Turni!F11,Turni!I11,Turni!L11,Turni!O11,Turni!R11,Turni!U11,Turni!X11)*24,0) -> 11.5 | AT30: =IF(AND(ISNUMBER(CHOOSE($B$21,Turni!F11,Turni!I11,Turni!L11,Turni!O11,Turni!R11,Turni!U11,Turni!X11)),ISNUMBER(CHOOSE($B$21,Turni!G11,Turni!J11,Turni!M11,Turni!P11,Turni!S11,Turni!V11,Turni!Y11))),(CHOOSE($B$21,Turni!G11,Turni!J11,Turni!M11,Turni!P11,Turni!S11,Turni!V11,Turni!Y11)-CHOOSE($B$21,Turni!F11,Turni!I11,Turni!L11,Turni!O11,Turni!R11,Turni!U11,Turni!X11))*24,0) -> 5
AN31: =Copertura!$A$13 -> 0.30208333 | AO31: =CHOOSE($B$21,Copertura!C13,Copertura!G13,Copertura!K13,Copertura!O13,Copertura!S13,Copertura!W13,Copertura!AA13) -> 4 | AP31: =CHOOSE($B$21,Copertura!E13,Copertura!I13,Copertura!M13,Copertura!Q13,Copertura!U13,Copertura!Y13,Copertura!AC13) -> 4 | AR31: =Turni!$A$12 -> BELLUCCO | AS31: =IF(ISNUMBER(CHOOSE($B$21,Turni!F12,Turni!I12,Turni!L12,Turni!O12,Turni!R12,Turni!U12,Turni!X12)),CHOOSE($B$21,Turni!F12,Turni!I12,Turni!L12,Turni!O12,Turni!R12,Turni!U12,Turni!X12)*24,0) -> 15 | AT31: =IF(AND(ISNUMBER(CHOOSE($B$21,Turni!F12,Turni!I12,Turni!L12,Turni!O12,Turni!R12,Turni!U12,Turni!X12)),ISNUMBER(CHOOSE($B$21,Turni!G12,Turni!J12,Turni!M12,Turni!P12,Turni!S12,Turni!V12,Turni!Y12))),(CHOOSE($B$21,Turni!G12,Turni!J12,Turni!M12,Turni!P12,Turni!S12,Turni!V12,Turni!Y12)-CHOOSE($B$21,Turni!F12,Turni!I12,Turni!L12,Turni!O12,Turni!R12,Turni!U12,Turni!X12))*24,0) -> 5
AN32: =Copertura!$A$14 -> 0.3125 | AO32: =CHOOSE($B$21,Copertura!C14,Copertura!G14,Copertura!K14,Copertura!O14,Copertura!S14,Copertura!W14,Copertura!AA14) -> 4 | AP32: =CHOOSE($B$21,Copertura!E14,Copertura!I14,Copertura!M14,Copertura!Q14,Copertura!U14,Copertura!Y14,Copertura!AC14) -> 4 | AR32: =Turni!$A$13 -> BUORO | AS32: =IF(ISNUMBER(CHOOSE($B$21,Turni!F13,Turni!I13,Turni!L13,Turni!O13,Turni!R13,Turni!U13,Turni!X13)),CHOOSE($B$21,Turni!F13,Turni!I13,Turni!L13,Turni!O13,Turni!R13,Turni!U13,Turni!X13)*24,0) -> 13 | AT32: =IF(AND(ISNUMBER(CHOOSE($B$21,Turni!F13,Turni!I13,Turni!L13,Turni!O13,Turni!R13,Turni!U13,Turni!X13)),ISNUMBER(CHOOSE($B$21,Turni!G13,Turni!J13,Turni!M13,Turni!P13,Turni!S13,Turni!V13,Turni!Y13))),(CHOOSE($B$21,Turni!G13,Turni!J13,Turni!M13,Turni!P13,Turni!S13,Turni!V13,Turni!Y13)-CHOOSE($B$21,Turni!F13,Turni!I13,Turni!L13,Turni!O13,Turni!R13,Turni!U13,Turni!X13))*24,0) -> 5
AN33: =Copertura!$A$15 -> 0.32291667 | AO33: =CHOOSE($B$21,Copertura!C15,Copertura!G15,Copertura!K15,Copertura!O15,Copertura!S15,Copertura!W15,Copertura!AA15) -> 4 | AP33: =CHOOSE($B$21,Copertura!E15,Copertura!I15,Copertura!M15,Copertura!Q15,Copertura!U15,Copertura!Y15,Copertura!AC15) -> 4 | AR33: =Turni!$A$14 -> CANOVA | AS33: =IF(ISNUMBER(CHOOSE($B$21,Turni!F14,Turni!I14,Turni!L14,Turni!O14,Turni!R14,Turni!U14,Turni!X14)),CHOOSE($B$21,Turni!F14,Turni!I14,Turni!L14,Turni!O14,Turni!R14,Turni!U14,Turni!X14)*24,0) -> 8.5 | AT33: =IF(AND(ISNUMBER(CHOOSE($B$21,Turni!F14,Turni!I14,Turni!L14,Turni!O14,Turni!R14,Turni!U14,Turni!X14)),ISNUMBER(CHOOSE($B$21,Turni!G14,Turni!J14,Turni!M14,Turni!P14,Turni!S14,Turni!V14,Turni!Y14))),(CHOOSE($B$21,Turni!G14,Turni!J14,Turni!M14,Turni!P14,Turni!S14,Turni!V14,Turni!Y14)-CHOOSE($B$21,Turni!F14,Turni!I14,Turni!L14,Turni!O14,Turni!R14,Turni!U14,Turni!X14))*24,0) -> 6
AN34: =Copertura!$A$16 -> 0.33333333 | AO34: =CHOOSE($B$21,Copertura!C16,Copertura!G16,Copertura!K16,Copertura!O16,Copertura!S16,Copertura!W16,Copertura!AA16) -> 5 | AP34: =CHOOSE($B$21,Copertura!E16,Copertura!I16,Copertura!M16,Copertura!Q16,Copertura!U16,Copertura!Y16,Copertura!AC16) -> 5 | AR34: =Turni!$A$15 -> CHIERZI | AS34: =IF(ISNUMBER(CHOOSE($B$21,Turni!F15,Turni!I15,Turni!L15,Turni!O15,Turni!R15,Turni!U15,Turni!X15)),CHOOSE($B$21,Turni!F15,Turni!I15,Turni!L15,Turni!O15,Turni!R15,Turni!U15,Turni!X15)*24,0) -> 0 | AT34: =IF(AND(ISNUMBER(CHOOSE($B$21,Turni!F15,Turni!I15,Turni!L15,Turni!O15,Turni!R15,Turni!U15,Turni!X15)),ISNUMBER(CHOOSE($B$21,Turni!G15,Turni!J15,Turni!M15,Turni!P15,Turni!S15,Turni!V15,Turni!Y15))),(CHOOSE($B$21,Turni!G15,Turni!J15,Turni!M15,Turni!P15,Turni!S15,Turni!V15,Turni!Y15)-CHOOSE($B$21,Turni!F15,Turni!I15,Turni!L15,Turni!O15,Turni!R15,Turni!U15,Turni!X15))*24,0) -> 0
AN35: =Copertura!$A$17 -> 0.34375 | AO35: =CHOOSE($B$21,Copertura!C17,Copertura!G17,Copertura!K17,Copertura!O17,Copertura!S17,Copertura!W17,Copertura!AA17) -> 5 | AP35: =CHOOSE($B$21,Copertura!E17,Copertura!I17,Copertura!M17,Copertura!Q17,Copertura!U17,Copertura!Y17,Copertura!AC17) -> 5 | AR35: =Turni!$A$16 -> BUGRYM | AS35: =IF(ISNUMBER(CHOOSE($B$21,Turni!F16,Turni!I16,Turni!L16,Turni!O16,Turni!R16,Turni!U16,Turni!X16)),CHOOSE($B$21,Turni!F16,Turni!I16,Turni!L16,Turni!O16,Turni!R16,Turni!U16,Turni!X16)*24,0) -> 14.75 | AT35: =IF(AND(ISNUMBER(CHOOSE($B$21,Turni!F16,Turni!I16,Turni!L16,Turni!O16,Turni!R16,Turni!U16,Turni!X16)),ISNUMBER(CHOOSE($B$21,Turni!G16,Turni!J16,Turni!M16,Turni!P16,Turni!S16,Turni!V16,Turni!Y16))),(CHOOSE($B$21,Turni!G16,Turni!J16,Turni!M16,Turni!P16,Turni!S16,Turni!V16,Turni!Y16)-CHOOSE($B$21,Turni!F16,Turni!I16,Turni!L16,Turni!O16,Turni!R16,Turni!U16,Turni!X16))*24,0) -> 6.5
AN36: =Copertura!$A$18 -> 0.35416667 | AO36: =CHOOSE($B$21,Copertura!C18,Copertura!G18,Copertura!K18,Copertura!O18,Copertura!S18,Copertura!W18,Copertura!AA18) -> 6 | AP36: =CHOOSE($B$21,Copertura!E18,Copertura!I18,Copertura!M18,Copertura!Q18,Copertura!U18,Copertura!Y18,Copertura!AC18) -> 5 | AR36: =Turni!$A$17 -> DAL ZOT | AS36: =IF(ISNUMBER(CHOOSE($B$21,Turni!F17,Turni!I17,Turni!L17,Turni!O17,Turni!R17,Turni!U17,Turni!X17)),CHOOSE($B$21,Turni!F17,Turni!I17,Turni!L17,Turni!O17,Turni!R17,Turni!U17,Turni!X17)*24,0) -> 16.25 | AT36: =IF(AND(ISNUMBER(CHOOSE($B$21,Turni!F17,Turni!I17,Turni!L17,Turni!O17,Turni!R17,Turni!U17,Turni!X17)),ISNUMBER(CHOOSE($B$21,Turni!G17,Turni!J17,Turni!M17,Turni!P17,Turni!S17,Turni!V17,Turni!Y17))),(CHOOSE($B$21,Turni!G17,Turni!J17,Turni!M17,Turni!P17,Turni!S17,Turni!V17,Turni!Y17)-CHOOSE($B$21,Turni!F17,Turni!I17,Turni!L17,Turni!O17,Turni!R17,Turni!U17,Turni!X17))*24,0) -> 5
AN37: =Copertura!$A$19 -> 0.36458333 | AO37: =CHOOSE($B$21,Copertura!C19,Copertura!G19,Copertura!K19,Copertura!O19,Copertura!S19,Copertura!W19,Copertura!AA19) -> 6 | AP37: =CHOOSE($B$21,Copertura!E19,Copertura!I19,Copertura!M19,Copertura!Q19,Copertura!U19,Copertura!Y19,Copertura!AC19) -> 5 | AR37: =Turni!$A$18 -> DE NARDIN | AS37: =IF(ISNUMBER(CHOOSE($B$21,Turni!F18,Turni!I18,Turni!L18,Turni!O18,Turni!R18,Turni!U18,Turni!X18)),CHOOSE($B$21,Turni!F18,Turni!I18,Turni!L18,Turni!O18,Turni!R18,Turni!U18,Turni!X18)*24,0) -> 6 | AT37: =IF(AND(ISNUMBER(CHOOSE($B$21,Turni!F18,Turni!I18,Turni!L18,Turni!O18,Turni!R18,Turni!U18,Turni!X18)),ISNUMBER(CHOOSE($B$21,Turni!G18,Turni!J18,Turni!M18,Turni!P18,Turni!S18,Turni!V18,Turni!Y18))),(CHOOSE($B$21,Turni!G18,Turni!J18,Turni!M18,Turni!P18,Turni!S18,Turni!V18,Turni!Y18)-CHOOSE($B$21,Turni!F18,Turni!I18,Turni!L18,Turni!O18,Turni!R18,Turni!U18,Turni!X18))*24,0) -> 5.5
AN38: =Copertura!$A$20 -> 0.375 | AO38: =CHOOSE($B$21,Copertura!C20,Copertura!G20,Copertura!K20,Copertura!O20,Copertura!S20,Copertura!W20,Copertura!AA20) -> 6 | AP38: =CHOOSE($B$21,Copertura!E20,Copertura!I20,Copertura!M20,Copertura!Q20,Copertura!U20,Copertura!Y20,Copertura!AC20) -> 6 | AR38: =Turni!$A$19 -> DE VIDO | AS38: =IF(ISNUMBER(CHOOSE($B$21,Turni!F19,Turni!I19,Turni!L19,Turni!O19,Turni!R19,Turni!U19,Turni!X19)),CHOOSE($B$21,Turni!F19,Turni!I19,Turni!L19,Turni!O19,Turni!R19,Turni!U19,Turni!X19)*24,0) -> 6 | AT38: =IF(AND(ISNUMBER(CHOOSE($B$21,Turni!F19,Turni!I19,Turni!L19,Turni!O19,Turni!R19,Turni!U19,Turni!X19)),ISNUMBER(CHOOSE($B$21,Turni!G19,Turni!J19,Turni!M19,Turni!P19,Turni!S19,Turni!V19,Turni!Y19))),(CHOOSE($B$21,Turni!G19,Turni!J19,Turni!M19,Turni!P19,Turni!S19,Turni!V19,Turni!Y19)-CHOOSE($B$21,Turni!F19,Turni!I19,Turni!L19,Turni!O19,Turni!R19,Turni!U19,Turni!X19))*24,0) -> 7
AN39: =Copertura!$A$21 -> 0.38541667 | AO39: =CHOOSE($B$21,Copertura!C21,Copertura!G21,Copertura!K21,Copertura!O21,Copertura!S21,Copertura!W21,Copertura!AA21) -> 6 | AP39: =CHOOSE($B$21,Copertura!E21,Copertura!I21,Copertura!M21,Copertura!Q21,Copertura!U21,Copertura!Y21,Copertura!AC21) -> 6 | AR39: =Turni!$A$20 -> GALLINA | AS39: =IF(ISNUMBER(CHOOSE($B$21,Turni!F20,Turni!I20,Turni!L20,Turni!O20,Turni!R20,Turni!U20,Turni!X20)),CHOOSE($B$21,Turni!F20,Turni!I20,Turni!L20,Turni!O20,Turni!R20,Turni!U20,Turni!X20)*24,0) -> 0 | AT39: =IF(AND(ISNUMBER(CHOOSE($B$21,Turni!F20,Turni!I20,Turni!L20,Turni!O20,Turni!R20,Turni!U20,Turni!X20)),ISNUMBER(CHOOSE($B$21,Turni!G20,Turni!J20,Turni!M20,Turni!P20,Turni!S20,Turni!V20,Turni!Y20))),(CHOOSE($B$21,Turni!G20,Turni!J20,Turni!M20,Turni!P20,Turni!S20,Turni!V20,Turni!Y20)-CHOOSE($B$21,Turni!F20,Turni!I20,Turni!L20,Turni!O20,Turni!R20,Turni!U20,Turni!X20))*24,0) -> 0
AN40: =Copertura!$A$22 -> 0.39583333 | AO40: =CHOOSE($B$21,Copertura!C22,Copertura!G22,Copertura!K22,Copertura!O22,Copertura!S22,Copertura!W22,Copertura!AA22) -> 6 | AP40: =CHOOSE($B$21,Copertura!E22,Copertura!I22,Copertura!M22,Copertura!Q22,Copertura!U22,Copertura!Y22,Copertura!AC22) -> 6 | AR40: =Turni!$A$21 -> MARZANO | AS40: =IF(ISNUMBER(CHOOSE($B$21,Turni!F21,Turni!I21,Turni!L21,Turni!O21,Turni!R21,Turni!U21,Turni!X21)),CHOOSE($B$21,Turni!F21,Turni!I21,Turni!L21,Turni!O21,Turni!R21,Turni!U21,Turni!X21)*24,0) -> 0 | AT40: =IF(AND(ISNUMBER(CHOOSE($B$21,Turni!F21,Turni!I21,Turni!L21,Turni!O21,Turni!R21,Turni!U21,Turni!X21)),ISNUMBER(CHOOSE($B$21,Turni!G21,Turni!J21,Turni!M21,Turni!P21,Turni!S21,Turni!V21,Turni!Y21))),(CHOOSE($B$21,Turni!G21,Turni!J21,Turni!M21,Turni!P21,Turni!S21,Turni!V21,Turni!Y21)-CHOOSE($B$21,Turni!F21,Turni!I21,Turni!L21,Turni!O21,Turni!R21,Turni!U21,Turni!X21))*24,0) -> 0
AN41: =Copertura!$A$23 -> 0.40625 | AO41: =CHOOSE($B$21,Copertura!C23,Copertura!G23,Copertura!K23,Copertura!O23,Copertura!S23,Copertura!W23,Copertura!AA23) -> 6 | AP41: =CHOOSE($B$21,Copertura!E23,Copertura!I23,Copertura!M23,Copertura!Q23,Copertura!U23,Copertura!Y23,Copertura!AC23) -> 6 | AR41: =Turni!$A$22 -> RIGONI | AS41: =IF(ISNUMBER(CHOOSE($B$21,Turni!F22,Turni!I22,Turni!L22,Turni!O22,Turni!R22,Turni!U22,Turni!X22)),CHOOSE($B$21,Turni!F22,Turni!I22,Turni!L22,Turni!O22,Turni!R22,Turni!U22,Turni!X22)*24,0) -> 6 | AT41: =IF(AND(ISNUMBER(CHOOSE($B$21,Turni!F22,Turni!I22,Turni!L22,Turni!O22,Turni!R22,Turni!U22,Turni!X22)),ISNUMBER(CHOOSE($B$21,Turni!G22,Turni!J22,Turni!M22,Turni!P22,Turni!S22,Turni!V22,Turni!Y22))),(CHOOSE($B$21,Turni!G22,Turni!J22,Turni!M22,Turni!P22,Turni!S22,Turni!V22,Turni!Y22)-CHOOSE($B$21,Turni!F22,Turni!I22,Turni!L22,Turni!O22,Turni!R22,Turni!U22,Turni!X22))*24,0) -> 5
AN42: =Copertura!$A$24 -> 0.41666667 | AO42: =CHOOSE($B$21,Copertura!C24,Copertura!G24,Copertura!K24,Copertura!O24,Copertura!S24,Copertura!W24,Copertura!AA24) -> 6 | AP42: =CHOOSE($B$21,Copertura!E24,Copertura!I24,Copertura!M24,Copertura!Q24,Copertura!U24,Copertura!Y24,Copertura!AC24) -> 5 | AR42: =Turni!$A$23 -> SCHENA | AS42: =IF(ISNUMBER(CHOOSE($B$21,Turni!F23,Turni!I23,Turni!L23,Turni!O23,Turni!R23,Turni!U23,Turni!X23)),CHOOSE($B$21,Turni!F23,Turni!I23,Turni!L23,Turni!O23,Turni!R23,Turni!U23,Turni!X23)*24,0) -> 0 | AT42: =IF(AND(ISNUMBER(CHOOSE($B$21,Turni!F23,Turni!I23,Turni!L23,Turni!O23,Turni!R23,Turni!U23,Turni!X23)),ISNUMBER(CHOOSE($B$21,Turni!G23,Turni!J23,Turni!M23,Turni!P23,Turni!S23,Turni!V23,Turni!Y23))),(CHOOSE($B$21,Turni!G23,Turni!J23,Turni!M23,Turni!P23,Turni!S23,Turni!V23,Turni!Y23)-CHOOSE($B$21,Turni!F23,Turni!I23,Turni!L23,Turni!O23,Turni!R23,Turni!U23,Turni!X23))*24,0) -> 0
AN43: =Copertura!$A$25 -> 0.42708333 | AO43: =CHOOSE($B$21,Copertura!C25,Copertura!G25,Copertura!K25,Copertura!O25,Copertura!S25,Copertura!W25,Copertura!AA25) -> 6 | AP43: =CHOOSE($B$21,Copertura!E25,Copertura!I25,Copertura!M25,Copertura!Q25,Copertura!U25,Copertura!Y25,Copertura!AC25) -> 5 | AR43: =Turni!$A$24 -> TAMBURLIN | AS43: =IF(ISNUMBER(CHOOSE($B$21,Turni!F24,Turni!I24,Turni!L24,Turni!O24,Turni!R24,Turni!U24,Turni!X24)),CHOOSE($B$21,Turni!F24,Turni!I24,Turni!L24,Turni!O24,Turni!R24,Turni!U24,Turni!X24)*24,0) -> 0 | AT43: =IF(AND(ISNUMBER(CHOOSE($B$21,Turni!F24,Turni!I24,Turni!L24,Turni!O24,Turni!R24,Turni!U24,Turni!X24)),ISNUMBER(CHOOSE($B$21,Turni!G24,Turni!J24,Turni!M24,Turni!P24,Turni!S24,Turni!V24,Turni!Y24))),(CHOOSE($B$21,Turni!G24,Turni!J24,Turni!M24,Turni!P24,Turni!S24,Turni!V24,Turni!Y24)-CHOOSE($B$21,Turni!F24,Turni!I24,Turni!L24,Turni!O24,Turni!R24,Turni!U24,Turni!X24))*24,0) -> 0
AN44: =Copertura!$A$26 -> 0.4375 | AO44: =CHOOSE($B$21,Copertura!C26,Copertura!G26,Copertura!K26,Copertura!O26,Copertura!S26,Copertura!W26,Copertura!AA26) -> 6 | AP44: =CHOOSE($B$21,Copertura!E26,Copertura!I26,Copertura!M26,Copertura!Q26,Copertura!U26,Copertura!Y26,Copertura!AC26) -> 5 | AR44: =#REF! -> #REF! | AS44: =IF(ISNUMBER(CHOOSE($B$21,#REF!,#REF!,#REF!,#REF!,#REF!,#REF!,#REF!)),CHOOSE($B$21,#REF!,#REF!,#REF!,#REF!,#REF!,#REF!,#REF!)*24,0) -> 0 | AT44: =IF(AND(ISNUMBER(CHOOSE($B$21,#REF!,#REF!,#REF!,#REF!,#REF!,#REF!,#REF!)),ISNUMBER(CHOOSE($B$21,#REF!,#REF!,#REF!,#REF!,#REF!,#REF!,#REF!))),(CHOOSE($B$21,#REF!,#REF!,#REF!,#REF!,#REF!,#REF!,#REF!)-CHOOSE($B$21,#REF!,#REF!,#REF!,#REF!,#REF!,#REF!,#REF!))*24,0) -> 0
AN45: =Copertura!$A$27 -> 0.44791667 | AO45: =CHOOSE($B$21,Copertura!C27,Copertura!G27,Copertura!K27,Copertura!O27,Copertura!S27,Copertura!W27,Copertura!AA27) -> 6 | AP45: =CHOOSE($B$21,Copertura!E27,Copertura!I27,Copertura!M27,Copertura!Q27,Copertura!U27,Copertura!Y27,Copertura!AC27) -> 5 | AR45: =Turni!$A$27 -> Totale | AS45: =IF(ISNUMBER(CHOOSE($B$21,Turni!F27,Turni!I27,Turni!L27,Turni!O27,Turni!R27,Turni!U27,Turni!X27)),CHOOSE($B$21,Turni!F27,Turni!I27,Turni!L27,Turni!O27,Turni!R27,Turni!U27,Turni!X27)*24,0) -> 0 | AT45: =IF(AND(ISNUMBER(CHOOSE($B$21,Turni!F27,Turni!I27,Turni!L27,Turni!O27,Turni!R27,Turni!U27,Turni!X27)),ISNUMBER(CHOOSE($B$21,Turni!G27,Turni!J27,Turni!M27,Turni!P27,Turni!S27,Turni!V27,Turni!Y27))),(CHOOSE($B$21,Turni!G27,Turni!J27,Turni!M27,Turni!P27,Turni!S27,Turni!V27,Turni!Y27)-CHOOSE($B$21,Turni!F27,Turni!I27,Turni!L27,Turni!O27,Turni!R27,Turni!U27,Turni!X27))*24,0) -> 0
AN46: =Copertura!$A$28 -> 0.45833333 | AO46: =CHOOSE($B$21,Copertura!C28,Copertura!G28,Copertura!K28,Copertura!O28,Copertura!S28,Copertura!W28,Copertura!AA28) -> 5 | AP46: =CHOOSE($B$21,Copertura!E28,Copertura!I28,Copertura!M28,Copertura!Q28,Copertura!U28,Copertura!Y28,Copertura!AC28) -> 5
AN47: =Copertura!$A$29 -> 0.46875 | AO47: =CHOOSE($B$21,Copertura!C29,Copertura!G29,Copertura!K29,Copertura!O29,Copertura!S29,Copertura!W29,Copertura!AA29) -> 5 | AP47: =CHOOSE($B$21,Copertura!E29,Copertura!I29,Copertura!M29,Copertura!Q29,Copertura!U29,Copertura!Y29,Copertura!AC29) -> 5
B48: 3 · Scenario assenze · reggi la settimana? | AN48: =Copertura!$A$30 -> 0.47916667 | AO48: =CHOOSE($B$21,Copertura!C30,Copertura!G30,Copertura!K30,Copertura!O30,Copertura!S30,Copertura!W30,Copertura!AA30) -> 5 | AP48: =CHOOSE($B$21,Copertura!E30,Copertura!I30,Copertura!M30,Copertura!Q30,Copertura!U30,Copertura!Y30,Copertura!AC30) -> 5
B49: Segna le assenze nel foglio Personale (colonna Assenza: F=ferie, M=malattia). Questo pannello si aggiorna da solo e ti dice cosa fare. | AN49: =Copertura!$A$31 -> 0.48958333 | AO49: =CHOOSE($B$21,Copertura!C31,Copertura!G31,Copertura!K31,Copertura!O31,Copertura!S31,Copertura!W31,Copertura!AA31) -> 5 | AP49: =CHOOSE($B$21,Copertura!E31,Copertura!I31,Copertura!M31,Copertura!Q31,Copertura!U31,Copertura!Y31,Copertura!AC31) -> 5
B50: Voce | D50: Valore | AN50: =Copertura!$A$32 -> 0.5 | AO50: =CHOOSE($B$21,Copertura!C32,Copertura!G32,Copertura!K32,Copertura!O32,Copertura!S32,Copertura!W32,Copertura!AA32) -> 4 | AP50: =CHOOSE($B$21,Copertura!E32,Copertura!I32,Copertura!M32,Copertura!Q32,Copertura!U32,Copertura!Y32,Copertura!AC32) -> 4
B51: Monte ore contrattuale | D51: =Personale!$C$41 -> 504 | AN51: =Copertura!$A$33 -> 0.51041667 | AO51: =CHOOSE($B$21,Copertura!C33,Copertura!G33,Copertura!K33,Copertura!O33,Copertura!S33,Copertura!W33,Copertura!AA33) -> 4 | AP51: =CHOOSE($B$21,Copertura!E33,Copertura!I33,Copertura!M33,Copertura!Q33,Copertura!U33,Copertura!Y33,Copertura!AC33) -> 4
B52: Assenze segnate | D52: =Personale!$H$41 -> 5 ass. | AN52: =Copertura!$A$34 -> 0.52083333 | AO52: =CHOOSE($B$21,Copertura!C34,Copertura!G34,Copertura!K34,Copertura!O34,Copertura!S34,Copertura!W34,Copertura!AA34) -> 4 | AP52: =CHOOSE($B$21,Copertura!E34,Copertura!I34,Copertura!M34,Copertura!Q34,Copertura!U34,Copertura!Y34,Copertura!AC34) -> 4
B53: Ore perse per assenze | D53: =Personale!$I$41 -> 140 | AN53: =Copertura!$A$35 -> 0.53125 | AO53: =CHOOSE($B$21,Copertura!C35,Copertura!G35,Copertura!K35,Copertura!O35,Copertura!S35,Copertura!W35,Copertura!AA35) -> 4 | AP53: =CHOOSE($B$21,Copertura!E35,Copertura!I35,Copertura!M35,Copertura!Q35,Copertura!U35,Copertura!Y35,Copertura!AC35) -> 4
B54: Capacita effettiva | D54: =(Personale!$C$41-Personale!$I$41) -> 364 | AN54: =Copertura!$A$36 -> 0.54166667 | AO54: =CHOOSE($B$21,Copertura!C36,Copertura!G36,Copertura!K36,Copertura!O36,Copertura!S36,Copertura!W36,Copertura!AA36) -> 4 | AP54: =CHOOSE($B$21,Copertura!E36,Copertura!I36,Copertura!M36,Copertura!Q36,Copertura!U36,Copertura!Y36,Copertura!AC36) -> 4
B55: Ore richieste | D55: =OreRichieste!$I$17 -> 553.76609 | AN55: =Copertura!$A$37 -> 0.55208333 | AO55: =CHOOSE($B$21,Copertura!C37,Copertura!G37,Copertura!K37,Copertura!O37,Copertura!S37,Copertura!W37,Copertura!AA37) -> 4 | AP55: =CHOOSE($B$21,Copertura!E37,Copertura!I37,Copertura!M37,Copertura!Q37,Copertura!U37,Copertura!Y37,Copertura!AC37) -> 4
B56: Margine / deficit | D56: =(Personale!$C$41-Personale!$I$41)-OreRichieste!$I$17 -> -189.76609 | AN56: =Copertura!$A$38 -> 0.5625 | AO56: =CHOOSE($B$21,Copertura!C38,Copertura!G38,Copertura!K38,Copertura!O38,Copertura!S38,Copertura!W38,Copertura!AA38) -> 4 | AP56: =CHOOSE($B$21,Copertura!E38,Copertura!I38,Copertura!M38,Copertura!Q38,Copertura!U38,Copertura!Y38,Copertura!AC38) -> 4
B57: Copertura % del fabbisogno | D57: =(Personale!$C$41-Personale!$I$41)/OreRichieste!$I$17 -> 0.65731724 | AN57: =Copertura!$A$39 -> 0.57291667 | AO57: =CHOOSE($B$21,Copertura!C39,Copertura!G39,Copertura!K39,Copertura!O39,Copertura!S39,Copertura!W39,Copertura!AA39) -> 4 | AP57: =CHOOSE($B$21,Copertura!E39,Copertura!I39,Copertura!M39,Copertura!Q39,Copertura!U39,Copertura!Y39,Copertura!AC39) -> 4
